Workbook
Name Slicer_Region1: #N/A

Sheet Dashboard
A2: TrendMart
A3: Profitability Leakage Analysis
J29: High Sales- Low Profits Products | O29: Top 5 Brands By Profit Margin | S29: KEY INSIGHTS & ACTIONS
J30: Row Labels | K30: Sales | L30: Profit | M30: Margin % | O30: Row Labels | P30: Sales | Q30: Profit | R30: Margin % | S30: 📈 Focus on High Sales – Low Margin Products
J31: Aurelia Earrings Sky Blue | K31: 243671.75 | L31: 31775.83 | M31: 0.09850509 | O31: Arrow | P31: 112698.86 | Q31: 28574.26 | R31: 0.27365496
J32: Global Desi Earrings Green | K32: 207013.85 | L32: 40366.38 | M32: 0.17780678 | O32: Blackberrys | P32: 149336.38 | Q32: 35414.16 | R32: 0.25425815 | S32: 🎯 Increase Online Sales Contribution
J33: Nike Earrings Teal | K33: 173911.74 | L33: 32108.45 | M33: 0.15779037 | O33: Being Human | P33: 115603.02 | Q33: 32170.64 | R33: 0.24888538
J34: Max Fashion Georgette Saree Brown | K34: 138420.26 | L34: 26849.36 | M34: 0.17449247 | O34: Wrangler | P34: 239340.92 | Q34: 61119.52 | R34: 0.23340589 | S34: 🔄 Reduce Return Rate
J35: Global Desi Analog Watch Cream | K35: 133863.46 | L35: 24220.3 | M35: 0.16302135 | O35: Pantaloons | P35: 272553.97 | Q35: 63645.75 | R35: 0.22847732

Sheet Calculations
A2: TOTAL SALES | C2: CURRENT MONTHLY AVG(SALES) | E2: CURRENT MONTHLY AVG(PROFIT) | G2: CURRENT MONTHLY AVG(AVG ORDER VAL)
A3: =SUM(Table2[Sales Amount]) -> 9227180 | C3: =AVERAGE(Sales_Transactions!AC7:AC2997) -> 3073.2408 | E3: =AVERAGE(Sales_Transactions!AE2870:AE2997) -> 558.1843 | G3: =SUM(Sales_Transactions!AC7:AC2997)/COUNTA(Sales_Transactions!AK7:AK2997) -> 3073.2408
A5: TOTAL PROFIT | C5: PREVIOUS MONTHLY AVG(SALES) | E5: PREVIOUS MONTHLY AVG(PROFIT) | G5: PREVIOUS MONTHLY AVG(AVG ORDER VAL)
A6: =SUM(Table2[Profit]) -> 1804518.5 | C6: =AVERAGE(Table2[Sales Amount]) -> 3075.7267 | E6: =AVERAGE(Table2[Profit]) -> 601.50618 | G6: =SUM(Table2[Sales Amount])/COUNTA(Table2[Order Time]) -> 3075.7267
A8: AVERAGE TRANSACTIONS | C8: SALES GROWTH | E8: PROFIT GROWTH | G8: AVG ORDER VALUE GROWTH
A9: =A3/A12 -> 3075.7267 | C9: =((C3-C6)/C6) -> -0.00080821147 | E9: =((E3-E6)/E6) -> -0.072022341 | G9: =((G3-G6)/G6) -> -0.00080821147
A11: TOTAL TRANSACTIONS | C11: =IF(Calculations!C9>=0,"▲ "&TEXT(Calculations!C9,"0.00%")&" vs Last Year","▼ "&TEXT(Calculations!C9,"0.00%")&" vs Last Year") -> ▼ -0.08% vs Last Year | E11: =IF(Calculations!E9>=0,"▲ "&TEXT(Calculations!E9,"0.00%")&" vs Last Year","▼ "&TEXT(Calculations!E9,"0.00%")&" vs Last Year") -> ▼ -7.20% vs Last Year | G11: =IF(Calculations!G9>=0,"▲ "&TEXT(Calculations!G9,"0.00%")&" vs Last Year","▼ "&TEXT(Calculations!G9,"0.00%")&" vs Last Year") -> ▼ -0.08% vs Last Year
A12: =COUNTA(Table2[Invoice No]) -> 3000
A14: PROFIT MARGIN | C14: TOTAL COST
A15: =A6/A3 -> 0.19556555 | C15: =SUM(Table2[Cost Amount]) -> 6596441.1
A17: TOTAL QUANTITY
A18: =SUM(Table2[Quantity]) -> 6118
A20: TOTAL DISCOUNT
A21: =SUM(Table2[Discount Amount]) -> 1184202.8
A23: AVERAGE DISCOUNT
A24: =AVERAGE(Table2[Discount %])/100 -> 0.1257
A26: RETURN RATE
A27: =COUNTIF(Table2[Return Status],"Returned")/COUNTA(Table2[Return Status]) -> 0.048666667

Sheet Pivot Table
A3: Row Labels | B3: Sum of Sales Amount
A4: South Zone 1 | B4: 4463451.9
A5: South Zone 2 | B5: 2554815.9
A6: South Zone 3 | B6: 2208912.1
A7: Grand Total | B7: 9227180
A11: #VALUE!
C18: Row Labels | D18: Sum of Sales Amount
C19: TrendMart Kochi High Street | D19: 386337.29
C20: TrendMart Thiruvananthapuram High Street | D20: 310084.63
C21: TrendMart Kochi Standard | D21: 292305.84
C22: TrendMart Vellore Standard | D22: 264364.77
C23: TrendMart Guntur High Street | D23: 223576.78
C24: TrendMart Nizamabad Standard | D24: 219676.14
C25: TrendMart Thoothukudi Mall Kiosk | D25: 194696.05
C26: TrendMart Chennai Standard | D26: 191070.97
C27: TrendMart Warangal High Street | D27: 190549.81
C28: TrendMart Madurai Mall Kiosk | D28: 188618.31
C29: Grand Total | D29: 2461280.6
A32: Row Labels | B32: Sum of Quantity
A33: GRT Jewellers Sling Bag Olive | B33: 156
A34: Indian Terrain Denim Shirt Wine | B34: 74
A35: Reebok Graphic Tee Cream | B35: 69
A36: Sonata Girls Frock Cream | B36: 68
A37: Jack & Jones Maxi Dress Maroon | B37: 68
A38: Global Desi Round Neck Green | B38: 64
A39: Metro Shoes Polo Purple | B39: 62
A40: Nike Shirt Dress Peach | B40: 61
A41: Peter England Crop Top Green | B41: 57
A42: US Polo Assn Casual Top Sky Blue | B42: 56
A43: Spykar Cotton Saree Black | B43: 56
A44: Grand Total | B44: 791
A48: Row Labels | B48: Sum of Sales Amount
A49: 2024 | B49: 7613439.2
A50: Apr | B50: 683356.93
A51: 45383 | B51: 26253.63
A52: 45384 | B52: 21041.18
A53: 45385 | B53: 25887.06
A54: 45386 | B54: 15719.39
A55: 45387 | B55: 12426.68
A56: 45388 | B56: 41836.48
A57: 45389 | B57: 39492.78
A58: 45390 | B58: 21753.61
A59: 45391 | B59: 10892.27
A60: 45392 | B60: 19623.04
A61: 45393 | B61: 15265.4
A62: 45394 | B62: 9965.48
... A80: 45412 | B80: 22213.77
A81: May | B81: 715370.42
A82: 45413 | B82: 35353.19
A83: 45414 | B83: 16996.24
A84: 45415 | B84: 34201.43
A85: 45416 | B85: 39323.46
A86: 45417 | B86: 42159.38
A87: 45418 | B87: 18140.12
A88: 45419 | B88: 12163.63
A89: 45420 | B89: 30602.65
A90: 45421 | B90: 7004.82
A91: 45422 | B91: 14213.36
A92: 45423 | B92: 36373.75
A93: 45424 | B93: 19417.42
... A112: 45443 | B112: 25298.53
A113: Jun | B113: 706442.99
A114: 45444 | B114: 7140.44
A115: 45445 | B115: 18745.02
A116: 45446 | B116: 14635.12
A117: 45447 | B117: 27053.56
A118: 45448 | B118: 13444.8
A119: 45449 | B119: 31792.84
A120: 45450 | B120: 14749.94
A121: 45451 | B121: 47288
A122: 45452 | B122: 13016.99
A123: 45453 | B123: 48668.7
A124: 45454 | B124: 49739.71
A125: 45455 | B125: 20762.9
... A143: 45473 | B143: 36523.03
A144: Jul | B144: 575940.09
A145: 45474 | B145: 11537.94
A146: 45475 | B146: 15022.85
A147: 45476 | B147: 9582.78
A148: 45477 | B148: 15330.83
A149: 45478 | B149: 8850.28
A150: 45479 | B150: 13185.94
A151: 45480 | B151: 14847.79
A152: 45481 | B152: 15057.92
A153: 45482 | B153: 36278.18
A154: 45483 | B154: 36227.41
A155: 45484 | B155: 31932.13
A156: 45485 | B156: 7561.07
... A175: 45504 | B175: 9422.28
A176: Aug | B176: 624765.64
A177: 45505 | B177: 23233.22
A178: 45506 | B178: 17915.34
A179: 45507 | B179: 35496.89
A180: 45508 | B180: 25078.86
A181: 45509 | B181: 15386.6
A182: 45510 | B182: 13861.71
A183: 45511 | B183: 18137.21
A184: 45512 | B184: 12923.87
A185: 45513 | B185: 26521.3
A186: 45514 | B186: 11784.61
...

Sheet PT_3
A3: Row Labels | B3: Sum of Sales Amount | C3: Average of Monthly Target | D3: Achievement %
A4: STR001 | B4: 58182.66 | C4: 2500000 | D4: =B4/C4 -> 0.023273064
A5: STR002 | B5: 42708.59 | C5: 1000000 | D5: =B5/C5 -> 0.04270859
A6: STR003 | B6: 60837.5 | C6: 2500000 | D6: =B6/C6 -> 0.024335
A7: STR004 | B7: 125355.94 | C7: 800000 | D7: =B7/C7 -> 0.15669493
A8: STR005 | B8: 47267.33 | C8: 2000000 | D8: =B8/C8 -> 0.023633665
A9: STR006 | B9: 60517.59 | C9: 2000000 | D9: =B9/C9 -> 0.030258795
A10: STR007 | B10: 109813.92 | C10: 1500000 | D10: =B10/C10 -> 0.07320928
A11: STR008 | B11: 88031.94 | C11: 1500000 | D11: =B11/C11 -> 0.05868796
A12: STR009 | B12: 49358.5 | C12: 2500000 | D12: =B12/C12 -> 0.0197434
A13: STR010 | B13: 67231.87 | C13: 2500000 | D13: =B13/C13 -> 0.026892748
A14: STR011 | B14: 129824.86 | C14: 2000000 | D14: =B14/C14 -> 0.06491243
A15: STR012 | B15: 69910.21 | C15: 2000000 | D15: =B15/C15 -> 0.034955105
... A114: STR111 | B114: 71886.83 | C114: 2500000 | D114: =B114/C114 -> 0.028754732
A115: STR112 | B115: 76199.66 | C115: 1500000 | D115: =B115/C115 -> 0.050799773 | G115: Row Labels | H115: Actual Sales | I115: Monthly Target | J115: Achievement %
A116: STR113 | B116: 107652.66 | C116: 2000000 | D116: =B116/C116 -> 0.05382633 | G116: STR037 | H116: 174307.53 | I116: 1000000 | J116: 0.17430753
A117: STR114 | B117: 45249.64 | C117: 2000000 | D117: =B117/C117 -> 0.02262482 | G117: STR004 | H117: 125355.94 | I117: 800000 | J117: 0.15669493
A118: STR115 | B118: 92669.69 | C118: 1500000 | D118: =B118/C118 -> 0.061779793 | G118: STR047 | H118: 99917.88 | I118: 800000 | J118: 0.12489735
A119: STR116 | B119: 72998.49 | C119: 2000000 | D119: =B119/C119 -> 0.036499245 | G119: STR015 | H119: 96001.61 | I119: 800000 | J119: 0.12000201
A120: STR117 | B120: 72445.64 | C120: 1500000 | D120: =B120/C120 -> 0.048297093 | G120: STR052 | H120: 94918.73 | I120: 800000 | J120: 0.11864841
A121: STR118 | B121: 82219.4 | C121: 1000000 | D121: =B121/C121 -> 0.0822194 | G121: STR017 | H121: 8669.72 | I121: 2500000 | J121: 0.003467888
A122: STR119 | B122: 50368.54 | C122: 1000000 | D122: =B122/C122 -> 0.05036854 | G122: STR095 | H122: 21325.26 | I122: 1500000 | J122: 0.01421684
A123: STR120 | B123: 54856.25 | C123: 1500000 | D123: =B123/C123 -> 0.036570833 | G123: STR009 | H123: 49358.5 | I123: 2500000 | J123: 0.0197434
A124: Grand Total | B124: 9227180 | C124: 1615133.3 | G124: STR033 | H124: 54686.2 | I124: 2500000 | J124: 0.02187448
G125: STR114 | H125: 45249.64 | I125: 2000000 | J125: 0.02262482
A126: Row Labels | B126: Sum of Sales Amount | C126: Average of Monthly Target | D126: Achievement %
A127: STR017 | B127: 8669.72 | C127: 2500000 | D127: 0.003467888 | G127: Row Labels | H127: Sum of Actual Sales | I127: Average of Monthly Target | J127: Sum of Achievement %
A128: STR095 | B128: 21325.26 | C128: 1500000 | D128: 0.01421684 | G128: STR037 | H128: 174307.53 | I128: 1000000 | J128: 0.17430753
A129: STR009 | B129: 49358.5 | C129: 2500000 | D129: 0.0197434 | G129: STR004 | H129: 125355.94 | I129: 800000 | J129: 0.15669493
A130: STR033 | B130: 54686.2 | C130: 2500000 | D130: 0.02187448 | G130: STR047 | H130: 99917.88 | I130: 800000 | J130: 0.12489735
A131: STR114 | B131: 45249.64 | C131: 2000000 | D131: 0.02262482 | G131: STR015 | H131: 96001.61 | I131: 800000 | J131: 0.12000201
A132: STR066 | B132: 56611.06 | C132: 2500000 | D132: 0.022644424 | G132: STR052 | H132: 94918.73 | I132: 800000 | J132: 0.11864841
A133: STR061 | B133: 34153.66 | C133: 1500000 | D133: 0.022769107 | G133: STR114 | H133: 45249.64 | I133: 2000000 | J133: 0.02262482
A134: STR001 | B134: 58182.66 | C134: 2500000 | D134: 0.023273064 | G134: STR033 | H134: 54686.2 | I134: 2500000 | J134: 0.02187448
A135: STR005 | B135: 47267.33 | C135: 2000000 | D135: 0.023633665 | G135: STR009 | H135: 49358.5 | I135: 2500000 | J135: 0.0197434
A136: STR079 | B136: 59737.93 | C136: 2500000 | D136: 0.023895172 | G136: STR095 | H136: 21325.26 | I136: 1500000 | J136: 0.01421684
A137: STR026 | B137: 60502.63 | C137: 2500000 | D137: 0.024201052 | G137: STR017 | H137: 8669.72 | I137: 2500000 | J137: 0.003467888
A138: STR003 | B138: 60837.5 | C138: 2500000 | D138: 0.024335
A139: STR081 | B139: 61362.04 | C139: 2500000 | D139: 0.024544816
A140: STR018 | B140: 49189.91 | C140: 2000000 | D140: 0.024594955
A141: STR067 | B141: 66217.52 | C141: 2500000 | D141: 0.026487008
A142: STR041 | B142: 66459.87 | C142: 2500000 | D142: 0.026583948
A143: STR090 | B143: 66598.76 | C143: 2500000 | D143: 0.026639504
A144: STR077 | B144: 67169.7 | C144: 2500000 | D144: 0.02686788
A145: STR010 | B145: 67231.87 | C145: 2500000 | D145: 0.026892748
A146: STR106 | B146: 70216.83 | C146: 2500000 | D146: 0.028086732
A147: STR111 | B147: 71886.83 | C147: 2500000 | D147: 0.028754732
A148: STR057 | B148: 73724.71 | C148: 2500000 | D148: 0.029489884
A149: STR059 | B149: 44857.36 | C149: 1500000 | D149: 0.029904907
... A246: STR037 | B246: 174307.53 | C246: 1000000 | D246: 0.17430753
A247: Grand Total | B247: 9227180 | C247: 1615133.3

Sheet PT_2
A3: Row Labels | B3: Sum of Sales Amount | C3: Sum of Profit | G3: Row Labels | H3: Sum of Sales Amount | I3: Sum of Profit
A4: CUST0389 | B4: 0 | C4: 0 | G4: CUST0225 | H4: 59564.98 | I4: 14119.32
A5: CUST0413 | B5: 0 | C5: 0 | G5: CUST0356 | H5: 58389.09 | I5: 8465.81
A6: CUST0019 | B6: 0 | C6: 0 | G6: CUST0821 | H6: 47508.67 | I6: 10001.87
A7: CUST0147 | B7: 0 | C7: 0 | G7: CUST0658 | H7: 43755.92 | I7: 9918.94
A8: CUST0094 | B8: 400.6 | C8: -28.85 | G8: CUST0674 | H8: 42712.27 | I8: 7206.77
A9: CUST0423 | B9: 457.3 | C9: 64.4 | G9: CUST0094 | H9: 400.6 | I9: -28.85
A10: CUST0403 | B10: 461.01 | C10: 144.06 | G10: CUST0423 | H10: 457.3 | I10: 64.4
A11: CUST0455 | B11: 533.44 | C11: -39.09 | G11: CUST0403 | H11: 461.01 | I11: 144.06
A12: CUST0744 | B12: 550.9 | C12: 155.67 | G12: CUST0455 | H12: 533.44 | I12: -39.09
A13: CUST0137 | B13: 554.81 | C13: 184.59 | G13: CUST0744 | H13: 550.9 | I13: 155.67
A14: CUST0134 | B14: 606.77 | C14: -52.38
A15: CUST0020 | B15: 654.7 | C15: 55.46 | F15: Row Labels | G15: Sales Amount | H15: Profit
A16: CUST0662 | B16: 682.2 | C16: 235.21 | F16: CUST0225 | G16: 59564.98 | H16: 14119.32
A17: CUST0416 | B17: 777.32 | C17: 312.14 | F17: CUST0356 | G17: 58389.09 | H17: 8465.81
A18: CUST0317 | B18: 801.17 | C18: 132.76 | F18: CUST0821 | G18: 47508.67 | H18: 10001.87
A19: CUST0048 | B19: 869.65 | C19: 130.16 | F19: CUST0658 | G19: 43755.92 | H19: 9918.94
A20: CUST0436 | B20: 882.02 | C20: 142.52 | F20: CUST0674 | G20: 42712.27 | H20: 7206.77
A21: CUST0357 | B21: 906.44 | C21: 189.1 | F21: CUST0744 | G21: 550.9 | H21: 155.67
A22: CUST0496 | B22: 944.27 | C22: 178.77 | F22: CUST0455 | G22: 533.44 | H22: -39.09
A23: CUST0499 | B23: 979.54 | C23: 71.95 | F23: CUST0403 | G23: 461.01 | H23: 144.06
A24: CUST0828 | B24: 1010.53 | C24: 147.53 | F24: CUST0423 | G24: 457.3 | H24: 64.4
A25: CUST0672 | B25: 1021.57 | C25: 145.01 | F25: CUST0094 | G25: 400.6 | H25: -28.85
A26: CUST0441 | B26: 1025.96 | C26: 172.04 | F26: Grand Total | G26: 254334.18 | H26: 50008.9
A27: CUST0544 | B27: 1034.07 | C27: -23.27
A28: CUST0817 | B28: 1062.99 | C28: 195.37
A29: CUST0399 | B29: 1102.43 | C29: 5.17
A30: CUST0053 | B30: 1133.69 | C30: 332.94
A31: CUST0014 | B31: 1201.14 | C31: 401.7
A32: CUST0378 | B32: 1212.61 | C32: 267.24
A33: CUST0484 | B33: 1212.98 | C33: 221.22
A34: CUST0839 | B34: 1221.63 | C34: 164.84
A35: CUST0719 | B35: 1250.47 | C35: 245.23
A36: CUST0302 | B36: 1263.16 | C36: 285.97
A37: CUST0285 | B37: 1270.07 | C37: 292.14
A38: CUST0548 | B38: 1288.31 | C38: 174.92
... A825: Grand Total | B825: 9227180 | C825: 1804518.5

Sheet PT_1
A3: Row Labels | B3: Sum of Sales Amount | C3: Sum of Profit
A4: 2024 | B4: 7613439.2 | C4: 1489359.7
A5: Apr | B5: 683356.93 | C5: 132559.46
A6: May | B6: 715370.42 | C6: 143214.56
A7: Jun | B7: 706442.99 | C7: 126683.88
A8: Jul | B8: 575940.09 | C8: 110065.95
A9: Aug | B9: 624765.64 | C9: 122773.23
A10: Sep | B10: 842808.66 | C10: 177387.37
A11: Oct | B11: 1519147.1 | C11: 301165.34
A12: Nov | B12: 1054251.4 | C12: 194655.84
A13: Dec | B13: 891356.08 | C13: 180854.07
A14: 2025 | B14: 1613740.7 | C14: 315158.84
A15: Jan | B15: 305174.24 | C15: 54860.77
... A18: Grand Total | B18: 9227180 | C18: 1804518.5
A22: Row Labels | B22: Sum of Sales Amount | C22: Sum of Profit
A23: Women Sarees | B23: 1103017.8 | C23: 202347.57
A24: Handbags | B24: 994021.98 | C24: 213991.74
A25: Watches | B25: 937502.18 | C25: 181304.56
A26: Jewellery | B26: 850930.2 | C26: 150422.21
A27: Women Dresses | B27: 648333.43 | C27: 108303.11
A28: Footwear | B28: 521388.97 | C28: 89384.64
A29: Men Ethnic | B29: 508021.06 | C29: 96328.01
A30: Women Jeans | B30: 504452.21 | C30: 92155.45
A31: Women Kurtis | B31: 408431.14 | C31: 82676.47
A32: Winter Wear | B32: 390745.41 | C32: 82000.54
A33: Grand Total | B33: 6866844.4 | C33: 1298914.3
A49: Row Labels | B49: Sum of Sales Amount | C49: Sum of Cost Amount | D49: Sum of Profit | E49: Sum of Quantity
A50: Sling Bag | B50: 852042.14 | C50: 573553.51 | D50: 188653 | E50: 313
A51: Earrings | B51: 624597.34 | C51: 502154.51 | D51: 104250.66 | E51: 105
A52: Georgette Saree | B52: 470927.8 | C52: 334711 | D52: 85760.28 | E52: 154
A53: Digital Watch | B53: 369648.92 | C53: 268382.4 | D53: 61661.26 | E53: 93
A54: Shirt Dress | B54: 268165.83 | C54: 197365.25 | D54: 42068.57 | E54: 178
A55: Analog Watch | B55: 266092.36 | C55: 190371.93 | D55: 47210.54 | E55: 57
A56: Smart Watch | B56: 249297.22 | C56: 162993.29 | D56: 59593.51 | E56: 78
A57: Printed Saree | B57: 233659.75 | C57: 156760.65 | D57: 51864.11 | E57: 58
A58: Skinny Fit | B58: 223050.53 | C58: 158577.38 | D58: 43341.81 | E58: 185
A59: Slippers | B59: 210364.48 | C59: 144004.46 | D59: 43820.98 | E59: 88
A60: Cotton Saree | B60: 202834.9 | C60: 150333.72 | D60: 30768.88 | E60: 95
A61: Bootcut | B61: 197586.18 | C61: 139405.88 | D61: 37744.2 | E61: 148
... A125: Grand Total | B125: 9227180 | C125: 6596441.1 | D125: 1804518.5 | E125: 6118
A129: Row Labels | B129: Sum of Sales Amount | C129: Sum of Cost Amount | D129: Sum of Profit | E129: Sum of Quantity
A130: GRT Jewellers | B130: 550505.3 | C130: 364122.14 | D130: 128132.78 | E130: 189
A131: Aurelia | B131: 477313.21 | C131: 379248.34 | D131: 72324.22 | E131: 246
A132: Max Fashion | B132: 452052.35 | C132: 309780.41 | D132: 94595.74 | E132: 148
A133: Global Desi | B133: 434134.43 | C133: 322467.23 | D133: 86063.96 | E133: 213
A134: Nike | B134: 424816.36 | C134: 328679.08 | D134: 68441.94 | E134: 235
A135: Reebok | B135: 409555.3 | C135: 278005.18 | D135: 93336.85 | E135: 292
A136: Pepe Jeans | B136: 303607.52 | C136: 216436.7 | D136: 57824.58 | E136: 152
A137: Nalli Silks | B137: 285539.03 | C137: 200941.32 | D137: 56648.11 | E137: 221
A138: Westside | B138: 280080.14 | C138: 186521.55 | D138: 64567.05 | E138: 133
A139: Pantaloons | B139: 272553.97 | C139: 180682.76 | D139: 63645.75 | E139: 135
A140: Bata | B140: 265817.38 | C140: 190146 | D140: 47190.96 | E140: 102
A141: US Polo Assn | B141: 260616.38 | C141: 191249.69 | D141: 44235.86 | E141: 171
... A180: Grand Total | B180: 9227180 | C180: 6596441.1 | D180: 1804518.5 | E180: 6118
A184: Row Labels | B184: Sum of Sales Amount
A185: GRT Jewellers Sling Bag Olive | B185: 483225.47
A186: Aurelia Earrings Sky Blue | B186: 243671.75
A187: Global Desi Earrings Green | B187: 207013.85
A188: Max Fashion Printed Saree Brown | B188: 197082.8
A189: Nike Earrings Teal | B189: 173911.74
A190: Westside Straight Fit Charcoal | B190: 147220.91
A191: Max Fashion Georgette Saree Brown | B191: 138420.26
A192: Global Desi Analog Watch Cream | B192: 133863.46
A193: Wrangler Ring White | B193: 121803.88
A194: Aurelia Analog Watch Purple | B194: 111670.81
A195: Grand Total | B195: 1957884.9
A435: Row Labels | B435: Sum of Sales Amount | C435: Sum of Profit | D435: Sum of Quantity
A436: 0 | B436: 2607137.5 | C436: 741818.76 | D436: 1520
A437: 5 | B437: 1168943.3 | C437: 293823.9 | D437: 641
A438: 10 | B438: 1977363.5 | C438: 425600.12 | D438: 1267
A439: 15 | B439: 906361.79 | C439: 152717.32 | D439: 638
A440: 20 | B440: 857622.12 | C440: 109703.73 | D440: 638
A441: 25 | B441: 926949.82 | C441: 67165.7 | D441: 694
A442: 30 | B442: 782801.92 | C442: 13689.01 | D442: 720
A443: Grand Total | B443: 9227180 | C443: 1804518.5 | D443: 6118
A446: Row Labels | B446: Count of Invoice No | C446: Sum of Sales Amount | D446: Sum of Profit | E446: Sum of Quantity
A447: Not Returned | B447: 2854 | C447: 8652296.1 | D447: 1686540 | E447: 5817
A448: Returned | B448: 146 | C448: 574883.86 | D448: 117978.54 | E448: 301
A449: Grand Total | B449: 3000 | C449: 9227180 | D449: 1804518.5 | E449: 6118
A452: Row Labels | B452: Sum of Sales Amount
A453: TrendMart Kochi High Street | B453: 386337.29
A454: TrendMart Thiruvananthapuram High Street | B454: 310084.63
A455: TrendMart Kochi Standard | B455: 292305.84
A456: TrendMart Vellore Standard | B456: 264364.77
A457: TrendMart Guntur High Street | B457: 223576.78
A458: TrendMart Nizamabad Standard | B458: 219676.14
A459: TrendMart Thoothukudi Mall Kiosk | B459: 194696.05
A460: TrendMart Chennai Standard | B460: 191070.97
A461: TrendMart Warangal High Street | B461: 190549.81
A462: TrendMart Madurai Mall Kiosk | B462: 188618.31
A463: Grand Total | B463: 2461280.6
A537: Row Labels | B537: Sum of Sales Amount | C537: Sum of Cost Amount | D537: Sum of Profit | E537: Sum of Quantity
A538: South Zone 1 | B538: 4463451.9 | C538: 3198228.1 | D538: 866892.49 | E538: 3028
A539: South Zone 2 | B539: 2554815.9 | C539: 1833775 | D539: 493806.97 | E539: 1617
A540: South Zone 3 | B540: 2208912.1 | C540: 1564438 | D540: 443819.08 | E540: 1473
A541: Grand Total | B541: 9227180 | C541: 6596441.1 | D541: 1804518.5 | E541: 6118
A544: Row Labels | B544: Sum of Sales Amount | C544: Sum of Cost Amount | D544: Sum of Profit | E544: Sum of Quantity
A545: Offline | B545: 6048775.9 | C545: 4326160.1 | D545: 1181710.4 | E545: 4040
A546: Online | B546: 3178404 | C546: 2270281 | D546: 622808.1 | E546: 2078
A547: Grand Total | B547: 9227180 | C547: 6596441.1 | D547: 1804518.5 | E547: 6118
...

Sheet Sales_Transactions
A1: Invoice No | B1: Invoice Date | C1: Year | D1: Month | E1: Target Key | F1: Customer_ID | G1: Customer Name | H1: Gender | I1: City | J1: State | K1: Membership | L1: Product_ID | M1: Product_Name | N1: Category | O1: Sub Category | P1: Brand | Q1: Store_ID | R1: Store Name | S1: Monthly Target | T1: Region | U1: Employee_ID | V1: Employee Name | W1: Quantity | X1: Unit Price | Y1: Discount % | Z1: Discount Amount | AA1: GST % | AB1: GST Amount | AC1: Sales Amount | AD1: Cost Amount | AE1: Profit | AF1: Payment Modee | AG1: Profit Margin % | AH1: Payment Mode | AI1: Sales Channel | AJ1: Return Status | AK1: Order Time | AL1: Order Period | AM1: Day Type
A2: INV100001 | B2: 45642 | C2: =YEAR(Table2[[#This Row],[Invoice Date]]) -> 2024 | D2: =TEXT(Table2[[#This Row],[Invoice Date]],"mmm") -> Dec | E2: =Table2[[#This Row],[Store_ID]]&"-"&Table2[[#This Row],[Year]]&"-"&Table2[[#This Row],[Month]] -> STR037-2024-Dec | F2: CUST0052 | G2: =_xlfn.XLOOKUP(Table2[[#This Row],[Customer_ID]],Table3[Customer_ID],Table3[Customer Name],"Not Found") -> Dhruv Achari | H2: =_xlfn.XLOOKUP(Table2[[#This Row],[Customer_ID]],Table3[Customer_ID],Table3[Gender],"Female") -> Male | I2: =_xlfn.XLOOKUP(Table2[[#This Row],[Customer_ID]],Table3[Customer_ID],Table3[City],"Missing Memebership") -> Kollam | J2: =_xlfn.XLOOKUP(Table2[[#This Row],[Customer_ID]],Table3[Customer_ID],Table3[State],"Karnataka") -> Kerala | K2: =_xlfn.XLOOKUP(Table2[[#This Row],[Customer_ID]],Table3[Customer_ID],Table3[Membership],"Regular") -> Regular | L2: PRD0200 | M2: =_xlfn.XLOOKUP(Table2[[#This Row],[Product_ID]],Table4[Product_ID],Table4[Product_Name],"Not Found") -> Pepe Jeans A-Line Kurti White | N2: =_xlfn.XLOOKUP(Table2[[#This Row],[Product_ID]],Table4[Product_ID],Table4[Category],"Not Found") -> Women Kurtis | O2: =_xlfn.XLOOKUP(Table2[[#This Row],[Product_ID]],Table4[Product_ID],Table4[Subcategory],"Not Found") -> A-Line Kurti | P2: =_xlfn.XLOOKUP(Table2[[#This Row],[Product_ID]],Table4[Product_ID],Table4[Brand],"Missing Brand") -> Pepe Jeans | Q2: STR037 | R2: =_xlfn.XLOOKUP(Table2[[#This Row],[Store_ID]],Table6[Store_ID],Table6[Store Name],"Not Found") -> TrendMart Vijayawada High Street | S2: =_xlfn.XLOOKUP(Table2[[#This Row],[Store_ID]],Table6[Store_ID],Table6[Monthly Target],"Missing Target") -> 1000000 | T2: =_xlfn.XLOOKUP(Table2[[#This Row],[Store_ID]],Table6[Store_ID],Table6[Region],"Not Found") -> South Zone 3 | U2: EMP0276 | V2: =_xlfn.XLOOKUP(Table2[[#This Row],[Employee_ID]],Table5[Employee_ID],Table5[Employee Name],"Not Found") -> Manoj Ramachandran | W2: 1 | X2: 749.84 | Y2: 10 | Z2: 74.98 | AA2: 5 | AB2: 33.74 | AC2: 708.6 | AD2: 496.67 | AE2: =(AC2-AD2-AB2) -> 178.19 | AF2: UPI | AG2: =IFERROR(Table2[[#This Row],[Profit]]/Table2[[#This Row],[Sales Amount]],0) -> 0.25146768 | AH2: =TRIM(Table2[[#This Row],[Payment Modee]]) -> UPI | AI2: Offline | AJ2: Not Returned | AK2: 18:16 | AL2: =IF(HOUR(Table2[[#This Row],[Order Time]])<12,"Morning",IF(HOUR(Table2[[#This Row],[Order Time]])<17,"Afternoon",IF(HOUR(Table2[[#This Row],[Order Time]])<21,"Evening","Night"))) -> Evening | AM2: Weekday
A3: INV100002 | B3: 45578 | C3: =YEAR(Table2[[#This Row],[Invoice Date]]) -> 2024 | D3: =TEXT(Table2[[#This Row],[Invoice Date]],"mmm") -> Oct | E3: =Table2[[#This Row],[Store_ID]]&"-"&Table2[[#This Row],[Year]]&"-"&Table2[[#This Row],[Month]] -> STR102-2024-Oct | F3: CUST0463 | G3: =_xlfn.XLOOKUP(Table2[[#This Row],[Customer_ID]],Table3[Customer_ID],Table3[Customer Name],"Not Found") -> Ashok Menon | H3: =_xlfn.XLOOKUP(Table2[[#This Row],[Customer_ID]],Table3[Customer_ID],Table3[Gender],"Female") -> Male | I3: =_xlfn.XLOOKUP(Table2[[#This Row],[Customer_ID]],Table3[Customer_ID],Table3[City],"Missing Memebership") -> Tumakuru | J3: =_xlfn.XLOOKUP(Table2[[#This Row],[Customer_ID]],Table3[Customer_ID],Table3[State],"Karnataka") -> Karnataka | K3: =_xlfn.XLOOKUP(Table2[[#This Row],[Customer_ID]],Table3[Customer_ID],Table3[Membership],"Regular") -> Regular | L3: PRD0245 | M3: =_xlfn.XLOOKUP(Table2[[#This Row],[Product_ID]],Table4[Product_ID],Table4[Product_Name],"Not Found") -> Reebok Round Neck Sky Blue | N3: =_xlfn.XLOOKUP(Table2[[#This Row],[Product_ID]],Table4[Product_ID],Table4[Category],"Not Found") -> Men T-Shirts | O3: =_xlfn.XLOOKUP(Table2[[#This Row],[Product_ID]],Table4[Product_ID],Table4[Subcategory],"Not Found") -> Round Neck | P3: =_xlfn.XLOOKUP(Table2[[#This Row],[Product_ID]],Table4[Product_ID],Table4[Brand],"Missing Brand") -> Reebok | Q3: STR102 | R3: =_xlfn.XLOOKUP(Table2[[#This Row],[Store_ID]],Table6[Store_ID],Table6[Store Name],"Not Found") -> TrendMart Tirunelveli High Street | S3: =_xlfn.XLOOKUP(Table2[[#This Row],[Store_ID]],Table6[Store_ID],Table6[Monthly Target],"Missing Target") -> 1000000 | T3: =_xlfn.XLOOKUP(Table2[[#This Row],[Store_ID]],Table6[Store_ID],Table6[Region],"Not Found") -> South Zone 1 | U3: EMP0156 | V3: =_xlfn.XLOOKUP(Table2[[#This Row],[Employee_ID]],Table5[Employee_ID],Table5[Employee Name],"Not Found") -> Deepthi Iyengar | W3: 2 | X3: 909.55 | Y3: 25 | Z3: 454.77 | AA3: 5 | AB3: 68.22 | AC3: 1432.55 | AD3: 984.22 | AE3: =(AC3-AD3-AB3) -> 380.11 | AF3: Debit Card | AG3: =IFERROR(Table2[[#This Row],[Profit]]/Table2[[#This Row],[Sales Amount]],0) -> 0.26533803 | AH3: =TRIM(Table2[[#This Row],[Payment Modee]]) -> Debit Card | AI3: Online | AJ3: Not Returned | AK3: 13:25 | AL3: =IF(HOUR(Table2[[#This Row],[Order Time]])<12,"Morning",IF(HOUR(Table2[[#This Row],[Order Time]])<17,"Afternoon",IF(HOUR(Table2[[#This Row],[Order Time]])<21,"Evening","Night"))) -> Afternoon | AM3: Weekend
A4: INV100003 | B4: 45657 | C4: =YEAR(Table2[[#This Row],[Invoice Date]]) -> 2024 | D4: =TEXT(Table2[[#This Row],[Invoice Date]],"mmm") -> Dec | E4: =Table2[[#This Row],[Store_ID]]&"-"&Table2[[#This Row],[Year]]&"-"&Table2[[#This Row],[Month]] -> STR011-2024-Dec | F4: CUST0711 | G4: =_xlfn.XLOOKUP(Table2[[#This Row],[Customer_ID]],Table3[Customer_ID],Table3[Customer Name],"Not Found") -> Deepthi Sundaram | H4: =_xlfn.XLOOKUP(Table2[[#This Row],[Customer_ID]],Table3[Customer_ID],Table3[Gender],"Female") -> Female | I4: =_xlfn.XLOOKUP(Table2[[#This Row],[Customer_ID]],Table3[Customer_ID],Table3[City],"Missing Memebership") -> Nellore | J4: =_xlfn.XLOOKUP(Table2[[#This Row],[Customer_ID]],Table3[Customer_ID],Table3[State],"Karnataka") -> Andhra Pradesh | K4: =_xlfn.XLOOKUP(Table2[[#This Row],[Customer_ID]],Table3[Customer_ID],Table3[Membership],"Regular") -> Silver | L4: PRD0065 | M4: =_xlfn.XLOOKUP(Table2[[#This Row],[Product_ID]],Table4[Product_ID],Table4[Product_Name],"Not Found") -> Westside Georgette Saree White | N4: =_xlfn.XLOOKUP(Table2[[#This Row],[Product_ID]],Table4[Product_ID],Table4[Category],"Not Found") -> Women Sarees | O4: =_xlfn.XLOOKUP(Table2[[#This Row],[Product_ID]],Table4[Product_ID],Table4[Subcategory],"Not Found") -> Georgette Saree | P4: =_xlfn.XLOOKUP(Table2[[#This Row],[Product_ID]],Table4[Product_ID],Table4[Brand],"Missing Brand") -> Westside | Q4: STR011 | R4: =_xlfn.XLOOKUP(Table2[[#This Row],[Store_ID]],Table6[Store_ID],Table6[Store Name],"Not Found") -> TrendMart Tirupati Standard | S4: =_xlfn.XLOOKUP(Table2[[#This Row],[Store_ID]],Table6[Store_ID],Table6[Monthly Target],"Missing Target") -> 2000000 | T4: =_xlfn.XLOOKUP(Table2[[#This Row],[Store_ID]],Table6[Store_ID],Table6[Region],"Not Found") -> South Zone 3 | U4: EMP0223 | V4: =_xlfn.XLOOKUP(Table2[[#This Row],[Employee_ID]],Table5[Employee_ID],Table5[Employee Name],"Not Found") -> Meena Krishnan | W4: 2 | X4: 3872.21 | Y4: 0 | Z4: 0 | AA4: 12 | AB4: 929.33 | AC4: 8673.75 | AD4: 5267.12 | AE4: =(AC4-AD4-AB4) -> 2477.3 | AF4: Debit Card | AG4: =IFERROR(Table2[[#This Row],[Profit]]/Table2[[#This Row],[Sales Amount]],0) -> 0.28560888 | AH4: =TRIM(Table2[[#This Row],[Payment Modee]]) -> Debit Card | AI4: Online | AJ4: Not Returned | AK4: 21:10 | AL4: =IF(HOUR(Table2[[#This Row],[Order Time]])<12,"Morning",IF(HOUR(Table2[[#This Row],[Order Time]])<17,"Afternoon",IF(HOUR(Table2[[#This Row],[Order Time]])<21,"Evening","Night"))) -> Night | AM4: Weekday
A5: INV100004 | B5: 45437 | C5: =YEAR(Table2[[#This Row],[Invoice Date]]) -> 2024 | D5: =TEXT(Table2[[#This Row],[Invoice Date]],"mmm") -> May | E5: =Table2[[#This Row],[Store_ID]]&"-"&Table2[[#This Row],[Year]]&"-"&Table2[[#This Row],[Month]] -> STR078-2024-May | F5: CUST0466 | G5: =_xlfn.XLOOKUP(Table2[[#This Row],[Customer_ID]],Table3[Customer_ID],Table3[Customer Name],"Not Found") -> Manoj Varma | H5: =_xlfn.XLOOKUP(Table2[[#This Row],[Customer_ID]],Table3[Customer_ID],Table3[Gender],"Female") -> Male | I5: =_xlfn.XLOOKUP(Table2[[#This Row],[Customer_ID]],Table3[Customer_ID],Table3[City],"Missing Memebership") -> Vellore | J5: =_xlfn.XLOOKUP(Table2[[#This Row],[Customer_ID]],Table3[Customer_ID],Table3[State],"Karnataka") -> Tamil Nadu | K5: =_xlfn.XLOOKUP(Table2[[#This Row],[Customer_ID]],Table3[Customer_ID],Table3[Membership],"Regular") -> Regular | L5: PRD0224 | M5: =_xlfn.XLOOKUP(Table2[[#This Row],[Product_ID]],Table4[Product_ID],Table4[Product_Name],"Not Found") -> Max Fashion Printed Saree Brown | N5: =_xlfn.XLOOKUP(Table2[[#This Row],[Product_ID]],Table4[Product_ID],Table4[Category],"Not Found") -> Women Sarees | O5: =_xlfn.XLOOKUP(Table2[[#This Row],[Product_ID]],Table4[Product_ID],Table4[Subcategory],"Not Found") -> Printed Saree | P5: =_xlfn.XLOOKUP(Table2[[#This Row],[Product_ID]],Table4[Product_ID],Table4[Brand],"Missing Brand") -> Max Fashion | Q5: STR078 | R5: =_xlfn.XLOOKUP(Table2[[#This Row],[Store_ID]],Table6[Store_ID],Table6[Store Name],"Not Found") -> TrendMart Vellore Standard | S5: =_xlfn.XLOOKUP(Table2[[#This Row],[Store_ID]],Table6[Store_ID],Table6[Monthly Target],"Missing Target") -> 1200000 | T5: =_xlfn.XLOOKUP(Table2[[#This Row],[Store_ID]],Table6[Store_ID],Table6[Region],"Not Found") -> South Zone 1 | U5: EMP0170 | V5: =_xlfn.XLOOKUP(Table2[[#This Row],[Employee_ID]],Table5[Employee_ID],Table5[Employee Name],"Not Found") -> Jyothi Prasad | W5: 4 | X5: 4857.75 | Y5: 20 | Z5: 3886.2 | AA5: 12 | AB5: 1865.38 | AC5: 17410.18 | AD5: 13483.2 | AE5: =(AC5-AD5-AB5) -> 2061.6 | AF5: UPI | AG5: =IFERROR(Table2[[#This Row],[Profit]]/Table2[[#This Row],[Sales Amount]],0) -> 0.11841348 | AH5: =TRIM(Table2[[#This Row],[Payment Modee]]) -> UPI | AI5: Online | AJ5: Not Returned | AK5: 13:45 | AL5: =IF(HOUR(Table2[[#This Row],[Order Time]])<12,"Morning",IF(HOUR(Table2[[#This Row],[Order Time]])<17,"Afternoon",IF(HOUR(Table2[[#This Row],[Order Time]])<21,"Evening","Night"))) -> Afternoon | AM5: Weekend
A6: INV100005 | B6: 45487 | C6: =YEAR(Table2[[#This Row],[Invoice Date]]) -> 2024 | D6: =TEXT(Table2[[#This Row],[Invoice Date]],"mmm") -> Jul | E6: =Table2[[#This Row],[Store_ID]]&"-"&Table2[[#This Row],[Year]]&"-"&Table2[[#This Row],[Month]] -> STR058-2024-Jul | F6: CUST0406 | G6: =_xlfn.XLOOKUP(Table2[[#This Row],[Customer_ID]],Table3[Customer_ID],Table3[Customer Name],"Not Found") -> Gayathri Srinivasan | H6: =_xlfn.XLOOKUP(Table2[[#This Row],[Customer_ID]],Table3[Customer_ID],Table3[Gender],"Female") -> Female | I6: =_xlfn.XLOOKUP(Table2[[#This Row],[Customer_ID]],Table3[Customer_ID],Table3[City],"Missing Memebership") -> Vijayawada | J6: =_xlfn.XLOOKUP(Table2[[#This Row],[Customer_ID]],Table3[Customer_ID],Table3[State],"Karnataka") -> Andhra Pradesh | K6: =_xlfn.XLOOKUP(Table2[[#This Row],[Customer_ID]],Table3[Customer_ID],Table3[Membership],"Regular") -> Regular | L6: PRD0035 | M6: =_xlfn.XLOOKUP(Table2[[#This Row],[Product_ID]],Table4[Product_ID],Table4[Product_Name],"Not Found") -> Reebok Printed Kurti Wine | N6: =_xlfn.XLOOKUP(Table2[[#This Row],[Product_ID]],Table4[Product_ID],Table4[Category],"Not Found") -> Women Kurtis | O6: =_xlfn.XLOOKUP(Table2[[#This Row],[Product_ID]],Table4[Product_ID],Table4[Subcategory],"Not Found") -> Printed Kurti | P6: =_xlfn.XLOOKUP(Table2[[#This Row],[Product_ID]],Table4[Product_ID],Table4[Brand],"Missing Brand") -> Reebok | Q6: STR058 | R6: =_xlfn.XLOOKUP(Table2[[#This Row],[Store_ID]],Table6[Store_ID],Table6[Store Name],"Not Found") -> TrendMart Thoothukudi Flagship | S6: =_xlfn.XLOOKUP(Table2[[#This Row],[Store_ID]],Table6[Store_ID],Table6[Monthly Target],"Missing Target") -> 1200000 | T6: =_xlfn.XLOOKUP(Table2[[#This Row],[Store_ID]],Table6[Store_ID],Table6[Region],"Not Found") -> South Zone 1 | U6: EMP0090 | V6: =_xlfn.XLOOKUP(Table2[[#This Row],[Employee_ID]],Table5[Employee_ID],Table5[Employee Name],"Not Found") -> Padma Gounder | W6: 1 | X6: 874.25 | Y6: 0 | Z6: 0 | AA6: 5 | AB6: 43.71 | AC6: 917.96 | AD6: 539.76 | AE6: =(AC6-AD6-AB6) -> 334.49 | AF6: Credit Card | AG6: =IFERROR(Table2[[#This Row],[Profit]]/Table2[[#This Row],[Sales Amount]],0) -> 0.36438407 | AH6: =TRIM(Table2[[#This Row],[Payment Modee]]) -> Credit Card | AI6: Offline | AJ6: Not Returned | AK6: 21:11 | AL6: =IF(HOUR(Table2[[#This Row],[Order Time]])<12,"Morning",IF(HOUR(Table2[[#This Row],[Order Time]])<17,"Afternoon",IF(HOUR(Table2[[#This Row],[Order Time]])<21,"Evening","Night"))) -> Night | AM6: Weekend
A7: INV100006 | B7: 45704 | C7: =YEAR(Table2[[#This Row],[Invoice Date]]) -> 2025 | D7: =TEXT(Table2[[#This Row],[Invoice Date]],"mmm") -> Feb | E7: =Table2[[#This Row],[Store_ID]]&"-"&Table2[[#This Row],[Year]]&"-"&Table2[[#This Row],[Month]] -> STR074-2025-Feb | F7: CUST0084 | G7: =_xlfn.XLOOKUP(Table2[[#This Row],[Customer_ID]],Table3[Customer_ID],Table3[Customer Name],"Not Found") -> Hari Kamath | H7: =_xlfn.XLOOKUP(Table2[[#This Row],[Customer_ID]],Table3[Customer_ID],Table3[Gender],"Female") -> Male | I7: =_xlfn.XLOOKUP(Table2[[#This Row],[Customer_ID]],Table3[Customer_ID],Table3[City],"Missing Memebership") -> Tirupati | J7: =_xlfn.XLOOKUP(Table2[[#This Row],[Customer_ID]],Table3[Customer_ID],Table3[State],"Karnataka") -> Andhra Pradesh | K7: =_xlfn.XLOOKUP(Table2[[#This Row],[Customer_ID]],Table3[Customer_ID],Table3[Membership],"Regular") -> Platinum | L7: PRD0199 | M7: =_xlfn.XLOOKUP(Table2[[#This Row],[Product_ID]],Table4[Product_ID],Table4[Product_Name],"Not Found") -> US Polo Assn Formal Shoes Red | N7: =_xlfn.XLOOKUP(Table2[[#This Row],[Product_ID]],Table4[Product_ID],Table4[Category],"Not Found") -> Footwear | O7: =_xlfn.XLOOKUP(Table2[[#This Row],[Product_ID]],Table4[Product_ID],Table4[Subcategory],"Not Found") -> Formal Shoes | P7: =_xlfn.XLOOKUP(Table2[[#This Row],[Product_ID]],Table4[Product_ID],Table4[Brand],"Missing Brand") -> US Polo Assn | Q7: STR074 | R7: =_xlfn.XLOOKUP(Table2[[#This Row],[Store_ID]],Table6[Store_ID],Table6[Store Name],"Not Found") -> TrendMart Kurnool High Street | S7: =_xlfn.XLOOKUP(Table2[[#This Row],[Store_ID]],Table6[Store_ID],Table6[Monthly Target],"Missing Target") -> 1200000 | T7: =_xlfn.XLOOKUP(Table2[[#This Row],[Store_ID]],Table6[Store_ID],Table6[Region],"Not Found") -> South Zone 3 | U7: EMP0204 | V7: =_xlfn.XLOOKUP(Table2[[#This Row],[Employee_ID]],Table5[Employee_ID],Table5[Employee Name],"Not Found") -> Rahul Krishnan | W7: 2 | X7: 3390.61 | Y7: 30 | Z7: 2034.37 | AA7: 12 | AB7: 569.62 | AC7: 5316.47 | AD7: 4849.24 | AE7: =(AC7-AD7-AB7) -> -102.39 | AF7: Credit Card | AG7: =IFERROR(Table2[[#This Row],[Profit]]/Table2[[#This Row],[Sales Amount]],0) -> -0.01925902 | AH7: =TRIM(Table2[[#This Row],[Payment Modee]]) -> Credit Card | AI7: Offline | AJ7: Not Returned | AK7: 10:24 | AL7: =IF(HOUR(Table2[[#This Row],[Order Time]])<12,"Morning",IF(HOUR(Table2[[#This Row],[Order Time]])<17,"Afternoon",IF(HOUR(Table2[[#This Row],[Order Time]])<21,"Evening","Night"))) -> Morning | AM7: Weekend
A8: INV100007 | B8: 45457 | C8: =YEAR(Table2[[#This Row],[Invoice Date]]) -> 2024 | D8: =TEXT(Table2[[#This Row],[Invoice Date]],"mmm") -> Jun | E8: =Table2[[#This Row],[Store_ID]]&"-"&Table2[[#This Row],[Year]]&"-"&Table2[[#This Row],[Month]] -> STR062-2024-Jun | F8: CUST0714 | G8: =_xlfn.XLOOKUP(Table2[[#This Row],[Customer_ID]],Table3[Customer_ID],Table3[Customer Name],"Not Found") -> Yamini Srinivasan | H8: =_xlfn.XLOOKUP(Table2[[#This Row],[Customer_ID]],Table3[Customer_ID],Table3[Gender],"Female") -> Female | I8: =_xlfn.XLOOKUP(Table2[[#This Row],[Customer_ID]],Table3[Customer_ID],Table3[City],"Missing Memebership") -> Alappuzha | J8: =_xlfn.XLOOKUP(Table2[[#This Row],[Customer_ID]],Table3[Customer_ID],Table3[State],"Karnataka") -> Kerala | K8: =_xlfn.XLOOKUP(Table2[[#This Row],[Customer_ID]],Table3[Customer_ID],Table3[Membership],"Regular") -> Silver | L8: PRD0040 | M8: =_xlfn.XLOOKUP(Table2[[#This Row],[Product_ID]],Table4[Product_ID],Table4[Product_Name],"Not Found") -> US Polo Assn Track Suit Maroon | N8: =_xlfn.XLOOKUP(Table2[[#This Row],[Product_ID]],Table4[Product_ID],Table4[Category],"Not Found") -> Sportswear | O8: =_xlfn.XLOOKUP(Table2[[#This Row],[Product_ID]],Table4[Product_ID],Table4[Subcategory],"Not Found") -> Track Suit | P8: =_xlfn.XLOOKUP(Table2[[#This Row],[Product_ID]],Table4[Product_ID],Table4[Brand],"Missing Brand") -> US Polo Assn | Q8: STR062 | R8: =_xlfn.XLOOKUP(Table2[[#This Row],[Store_ID]],Table6[Store_ID],Table6[Store Name],"Not Found") -> TrendMart Vijayawada Standard | S8: =_xlfn.XLOOKUP(Table2[[#This Row],[Store_ID]],Table6[Store_ID],Table6[Monthly Target],"Missing Target") -> 1000000 | T8: =_xlfn.XLOOKUP(Table2[[#This Row],[Store_ID]],Table6[Store_ID],Table6[Region],"Not Found") -> South Zone 3 | U8: EMP0215 | V8: =_xlfn.XLOOKUP(Table2[[#This Row],[Employee_ID]],Table5[Employee_ID],Table5[Employee Name],"Not Found") -> Praveen Gupta | W8: 4 | X8: 1474.99 | Y8: 0 | Z8: 0 | AA8: 12 | AB8: 708 | AC8: 6607.96 | AD8: 4594.64 | AE8: =(AC8-AD8-AB8) -> 1305.32 | AF8: Cash | AG8: =IFERROR(Table2[[#This Row],[Profit]]/Table2[[#This Row],[Sales Amount]],0) -> 0.19753752 | AH8: =TRIM(Table2[[#This Row],[Payment Modee]]) -> Cash | AI8: Offline | AJ8: Not Returned | AK8: 20:20 | AL8: =IF(HOUR(Table2[[#This Row],[Order Time]])<12,"Morning",IF(HOUR(Table2[[#This Row],[Order Time]])<17,"Afternoon",IF(HOUR(Table2[[#This Row],[Order Time]])<21,"Evening","Night"))) -> Evening | AM8: Weekday
A9: INV100008 | B9: 45678 | C9: =YEAR(Table2[[#This Row],[Invoice Date]]) -> 2025 | D9: =TEXT(Table2[[#This Row],[Invoice Date]],"mmm") -> Jan | E9: =Table2[[#This Row],[Store_ID]]&"-"&Table2[[#This Row],[Year]]&"-"&Table2[[#This Row],[Month]] -> STR084-2025-Jan | F9: CUST0121 | G9: =_xlfn.XLOOKUP(Table2[[#This Row],[Customer_ID]],Table3[Customer_ID],Table3[Customer Name],"Not Found") -> Srinivas Prasad | H9: =_xlfn.XLOOKUP(Table2[[#This Row],[Customer_ID]],Table3[Customer_ID],Table3[Gender],"Female") -> Male | I9: =_xlfn.XLOOKUP(Table2[[#This Row],[Customer_ID]],Table3[Customer_ID],Table3[City],"Missing Memebership") -> Kannur | J9: =_xlfn.XLOOKUP(Table2[[#This Row],[Customer_ID]],Table3[Customer_ID],Table3[State],"Karnataka") -> Kerala | K9: =_xlfn.XLOOKUP(Table2[[#This Row],[Customer_ID]],Table3[Customer_ID],Table3[Membership],"Regular") -> Silver | L9: PRD0196 | M9: =_xlfn.XLOOKUP(Table2[[#This Row],[Product_ID]],Table4[Product_ID],Table4[Product_Name],"Not Found") -> Metro Shoes Slim Fit Wine | N9: =_xlfn.XLOOKUP(Table2[[#This Row],[Product_ID]],Table4[Product_ID],Table4[Category],"Not Found") -> Men Jeans | O9: =_xlfn.XLOOKUP(Table2[[#This Row],[Product_ID]],Table4[Product_ID],Table4[Subcategory],"Not Found") -> Slim Fit | P9: =_xlfn.XLOOKUP(Table2[[#This Row],[Product_ID]],Table4[Product_ID],Table4[Brand],"Missing Brand") -> Metro Shoes | Q9: STR084 | R9: =_xlfn.XLOOKUP(Table2[[#This Row],[Store_ID]],Table6[Store_ID],Table6[Store Name],"Not Found") -> TrendMart Tirupati High Street | S9: =_xlfn.XLOOKUP(Table2[[#This Row],[Store_ID]],Table6[Store_ID],Table6[Monthly Target],"Missing Target") -> 2000000 | T9: =_xlfn.XLOOKUP(Table2[[#This Row],[Store_ID]],Table6[Store_ID],Table6[Region],"Not Found") -> South Zone 3 | U9: EMP0285 | V9: =_xlfn.XLOOKUP(Table2[[#This Row],[Employee_ID]],Table5[Employee_ID],Table5[Employee Name],"Not Found") -> Chandran Krishnan | W9: 1 | X9: 1407.12 | Y9: 0 | Z9: 0 | AA9: 12 | AB9: 168.85 | AC9: 1575.97 | AD9: 1067.72 | AE9: =(AC9-AD9-AB9) -> 339.4 | AF9: UPI | AG9: =IFERROR(Table2[[#This Row],[Profit]]/Table2[[#This Row],[Sales Amount]],0) -> 0.21535943 | AH9: =TRIM(Table2[[#This Row],[Payment Modee]]) -> UPI | AI9: Offline | AJ9: Not Returned | AK9: 21:28 | AL9: =IF(HOUR(Table2[[#This Row],[Order Time]])<12,"Morning",IF(HOUR(Table2[[#This Row],[Order Time]])<17,"Afternoon",IF(HOUR(Table2[[#This Row],[Order Time]])<21,"Evening","Night"))) -> Night | AM9: Weekday
A10: INV100009 | B10: 45541 | C10: =YEAR(Table2[[#This Row],[Invoice Date]]) -> 2024 | D10: =TEXT(Table2[[#This Row],[Invoice Date]],"mmm") -> Sep | E10: =Table2[[#This Row],[Store_ID]]&"-"&Table2[[#This Row],[Year]]&"-"&Table2[[#This Row],[Month]] -> STR021-2024-Sep | F10: CUST0782 | G10: =_xlfn.XLOOKUP(Table2[[#This Row],[Customer_ID]],Table3[Customer_ID],Table3[Customer Name],"Not Found") -> Rahul Yadav | H10: =_xlfn.XLOOKUP(Table2[[#This Row],[Customer_ID]],Table3[Customer_ID],Table3[Gender],"Female") -> Male | I10: =_xlfn.XLOOKUP(Table2[[#This Row],[Customer_ID]],Table3[Customer_ID],Table3[City],"Missing Memebership") -> Alappuzha | J10: =_xlfn.XLOOKUP(Table2[[#This Row],[Customer_ID]],Table3[Customer_ID],Table3[State],"Karnataka") -> Kerala | K10: =_xlfn.XLOOKUP(Table2[[#This Row],[Customer_ID]],Table3[Customer_ID],Table3[Membership],"Regular") -> Gold | L10: PRD0114 | M10: =_xlfn.XLOOKUP(Table2[[#This Row],[Product_ID]],Table4[Product_ID],Table4[Product_Name],"Not Found") -> Arrow Sunglasses Red | N10: =_xlfn.XLOOKUP(Table2[[#This Row],[Product_ID]],Table4[Product_ID],Table4[Category],"Not Found") -> Accessories | O10: =_xlfn.XLOOKUP(Table2[[#This Row],[Product_ID]],Table4[Product_ID],Table4[Subcategory],"Not Found") -> Sunglasses | P10: =_xlfn.XLOOKUP(Table2[[#This Row],[Product_ID]],Table4[Product_ID],Table4[Brand],"Missing Brand") -> Arrow | Q10: STR021 | R10: =_xlfn.XLOOKUP(Table2[[#This Row],[Store_ID]],Table6[Store_ID],Table6[Store Name],"Not Found") -> TrendMart Kozhikode Standard | S10: =_xlfn.XLOOKUP(Table2[[#This Row],[Store_ID]],Table6[Store_ID],Table6[Monthly Target],"Missing Target") -> 2000000 | T10: =_xlfn.XLOOKUP(Table2[[#This Row],[Store_ID]],Table6[Store_ID],Table6[Region],"Not Found") -> South Zone 1 | U10: EMP0001 | V10: =_xlfn.XLOOKUP(Table2[[#This Row],[Employee_ID]],Table5[Employee_ID],Table5[Employee Name],"Not Found") -> Charulatha Kumar | W10: 5 | X10: 851.61 | Y10: 5 | Z10: 212.9 | AA10: 5 | AB10: 202.26 | AC10: 4247.41 | AD10: 2443 | AE10: =(AC10-AD10-AB10) -> 1602.15 | AF10: Debit Card | AG10: =IFERROR(Table2[[#This Row],[Profit]]/Table2[[#This Row],[Sales Amount]],0) -> 0.37720634 | AH10: =TRIM(Table2[[#This Row],[Payment Modee]]) -> Debit Card | AI10: Offline | AJ10: Not Returned | AK10: 19:05 | AL10: =IF(HOUR(Table2[[#This Row],[Order Time]])<12,"Morning",IF(HOUR(Table2[[#This Row],[Order Time]])<17,"Afternoon",IF(HOUR(Table2[[#This Row],[Order Time]])<21,"Evening","Night"))) -> Evening | AM10: Weekday
A11: INV100010 | B11: 45583 | C11: =YEAR(Table2[[#This Row],[Invoice Date]]) -> 2024 | D11: =TEXT(Table2[[#This Row],[Invoice Date]],"mmm") -> Oct | E11: =Table2[[#This Row],[Store_ID]]&"-"&Table2[[#This Row],[Year]]&"-"&Table2[[#This Row],[Month]] -> STR085-2024-Oct | F11: CUST0429 | G11: =_xlfn.XLOOKUP(Table2[[#This Row],[Customer_ID]],Table3[Customer_ID],Table3[Customer Name],"Not Found") -> Nandini Gopalakrishnan | H11: =_xlfn.XLOOKUP(Table2[[#This Row],[Customer_ID]],Table3[Customer_ID],Table3[Gender],"Female") -> Female | I11: =_xlfn.XLOOKUP(Table2[[#This Row],[Customer_ID]],Table3[Customer_ID],Table3[City],"Missing Memebership") -> Vellore | J11: =_xlfn.XLOOKUP(Table2[[#This Row],[Customer_ID]],Table3[Customer_ID],Table3[State],"Karnataka") -> Tamil Nadu | K11: =_xlfn.XLOOKUP(Table2[[#This Row],[Customer_ID]],Table3[Customer_ID],Table3[Membership],"Regular") -> Regular | L11: PRD0075 | M11: =_xlfn.XLOOKUP(Table2[[#This Row],[Product_ID]],Table4[Product_ID],Table4[Product_Name],"Not Found") -> Sonata Bootcut Navy Blue | N11: =_xlfn.XLOOKUP(Table2[[#This Row],[Product_ID]],Table4[Product_ID],Table4[Category],"Not Found") -> Women Jeans | O11: =_xlfn.XLOOKUP(Table2[[#This Row],[Product_ID]],Table4[Product_ID],Table4[Subcategory],"Not Found") -> Bootcut | P11: =_xlfn.XLOOKUP(Table2[[#This Row],[Product_ID]],Table4[Product_ID],Table4[Brand],"Missing Brand") -> Sonata | Q11: STR085 | R11: =_xlfn.XLOOKUP(Table2[[#This Row],[Store_ID]],Table6[Store_ID],Table6[Store Name],"Not Found") -> TrendMart Nizamabad Outlet | S11: =_xlfn.XLOOKUP(Table2[[#This Row],[Store_ID]],Table6[Store_ID],Table6[Monthly Target],"Missing Target") -> 1500000 | T11: =_xlfn.XLOOKUP(Table2[[#This Row],[Store_ID]],Table6[Store_ID],Table6[Region],"Not Found") -> South Zone 2 | U11: EMP0090 | V11: =_xlfn.XLOOKUP(Table2[[#This Row],[Employee_ID]],Table5[Employee_ID],Table5[Employee Name],"Not Found") -> Padma Gounder | W11: 1 | X11: 1041.15 | Y11: 0 | Z11: 0 | AA11: 12 | AB11: 124.94 | AC11: 1166.09 | AD11: 692.53 | AE11: =(AC11-AD11-AB11) -> 348.62 | AF11: Credit Card | AG11: =IFERROR(Table2[[#This Row],[Profit]]/Table2[[#This Row],[Sales Amount]],0) -> 0.29896492 | AH11: =TRIM(Table2[[#This Row],[Payment Modee]]) -> Credit Card | AI11: Offline | AJ11: Not Returned | AK11: 10:34 | AL11: =IF(HOUR(Table2[[#This Row],[Order Time]])<12,"Morning",IF(HOUR(Table2[[#This Row],[Order Time]])<17,"Afternoon",IF(HOUR(Table2[[#This Row],[Order Time]])<21,"Evening","Night"))) -> Morning | AM11: Weekday
A12: INV100011 | B12: 45677 | C12: =YEAR(Table2[[#This Row],[Invoice Date]]) -> 2025 | D12: =TEXT(Table2[[#This Row],[Invoice Date]],"mmm") -> Jan | E12: =Table2[[#This Row],[Store_ID]]&"-"&Table2[[#This Row],[Year]]&"-"&Table2[[#This Row],[Month]] -> STR004-2025-Jan | F12: CUST0162 | G12: =_xlfn.XLOOKUP(Table2[[#This Row],[Customer_ID]],Table3[Customer_ID],Table3[Customer Name],"Not Found") -> Tanvi Balasubramaniam | H12: =_xlfn.XLOOKUP(Table2[[#This Row],[Customer_ID]],Table3[Customer_ID],Table3[Gender],"Female") -> Female | I12: =_xlfn.XLOOKUP(Table2[[#This Row],[Customer_ID]],Table3[Customer_ID],Table3[City],"Missing Memebership") -> Kannur | J12: =_xlfn.XLOOKUP(Table2[[#This Row],[Customer_ID]],Table3[Customer_ID],Table3[State],"Karnataka") -> Kerala | K12: =_xlfn.XLOOKUP(Table2[[#This Row],[Customer_ID]],Table3[Customer_ID],Table3[Membership],"Regular") -> Silver | L12: PRD0117 | M12: =_xlfn.XLOOKUP(Table2[[#This Row],[Product_ID]],Table4[Product_ID],Table4[Product_Name],"Not Found") -> Nike Shirt Dress Peach | N12: =_xlfn.XLOOKUP(Table2[[#This Row],[Product_ID]],Table4[Product_ID],Table4[Category],"Not Found") -> Women Dresses | O12: =_xlfn.XLOOKUP(Table2[[#This Row],[Product_ID]],Table4[Product_ID],Table4[Subcategory],"Not Found") -> Shirt Dress | P12: =_xlfn.XLOOKUP(Table2[[#This Row],[Product_ID]],Table4[Product_ID],Table4[Brand],"Missing Brand") -> Nike | Q12: STR004 | R12: =_xlfn.XLOOKUP(Table2[[#This Row],[Store_ID]],Table6[Store_ID],Table6[Store Name],"Not Found") -> TrendMart Kalaburagi Mall Kiosk | S12: =_xlfn.XLOOKUP(Table2[[#This Row],[Store_ID]],Table6[Store_ID],Table6[Monthly Target],"Missing Target") -> 800000 | T12: =_xlfn.XLOOKUP(Table2[[#This Row],[Store_ID]],Table6[Store_ID],Table6[Region],"Not Found") -> South Zone 2 | U12: EMP0258 | V12: =_xlfn.XLOOKUP(Table2[[#This Row],[Employee_ID]],Table5[Employee_ID],Table5[Employee Name],"Not Found") -> Preethi Singh | W12: 4 | X12: 1761.12 | Y12: 10 | Z12: 704.45 | AA12: 12 | AB12: 760.8 | AC12: 7100.83 | AD12: 5599.4 | AE12: =(AC12-AD12-AB12) -> 740.63 | AF12: Credit Card | AG12: =IFERROR(Table2[[#This Row],[Profit]]/Table2[[#This Row],[Sales Amount]],0) -> 0.10430189 | AH12: =TRIM(Table2[[#This Row],[Payment Modee]]) -> Credit Card | AI12: Offline | AJ12: Not Returned | AK12: 13:20 | AL12: =IF(HOUR(Table2[[#This Row],[Order Time]])<12,"Morning",IF(HOUR(Table2[[#This Row],[Order Time]])<17,"Afternoon",IF(HOUR(Table2[[#This Row],[Order Time]])<21,"Evening","Night"))) -> Afternoon | AM12: Weekday
A13: INV100012 | B13: 45736 | C13: =YEAR(Table2[[#This Row],[Invoice Date]]) -> 2025 | D13: =TEXT(Table2[[#This Row],[Invoice Date]],"mmm") -> Mar | E13: =Table2[[#This Row],[Store_ID]]&"-"&Table2[[#This Row],[Year]]&"-"&Table2[[#This Row],[Month]] -> STR068-2025-Mar | F13: CUST0794 | G13: =_xlfn.XLOOKUP(Table2[[#This Row],[Customer_ID]],Table3[Customer_ID],Table3[Customer Name],"Not Found") -> Rahul Gupta | H13: =_xlfn.XLOOKUP(Table2[[#This Row],[Customer_ID]],Table3[Customer_ID],Table3[Gender],"Female") -> Male | I13: =_xlfn.XLOOKUP(Table2[[#This Row],[Customer_ID]],Table3[Customer_ID],Table3[City],"Missing Memebership") -> Chennai | J13: =_xlfn.XLOOKUP(Table2[[#This Row],[Customer_ID]],Table3[Customer_ID],Table3[State],"Karnataka") -> Tamil Nadu | K13: =_xlfn.XLOOKUP(Table2[[#This Row],[Customer_ID]],Table3[Customer_ID],Table3[Membership],"Regular") -> Silver | L13: PRD0078 | M13: =_xlfn.XLOOKUP(Table2[[#This Row],[Product_ID]],Table4[Product_ID],Table4[Product_Name],"Not Found") -> Metro Shoes Regular Fit Charcoal | N13: =_xlfn.XLOOKUP(Table2[[#This Row],[Product_ID]],Table4[Product_ID],Table4[Category],"Not Found") -> Men Jeans | O13: =_xlfn.XLOOKUP(Table2[[#This Row],[Product_ID]],Table4[Product_ID],Table4[Subcategory],"Not Found") -> Regular Fit | P13: =_xlfn.XLOOKUP(Table2[[#This Row],[Product_ID]],Table4[Product_ID],Table4[Brand],"Missing Brand") -> Metro Shoes | Q13: STR068 | R13: =_xlfn.XLOOKUP(Table2[[#This Row],[Store_ID]],Table6[Store_ID],Table6[Store Name],"Not Found") -> TrendMart Madurai Mall Kiosk | S13: =_xlfn.XLOOKUP(Table2[[#This Row],[Store_ID]],Table6[Store_ID],Table6[Monthly Target],"Missing Target") -> 2000000 | T13: =_xlfn.XLOOKUP(Table2[[#This Row],[Store_ID]],Table6[Store_ID],Table6[Region],"Not Found") -> South Zone 1 | U13: EMP0204 | V13: =_xlfn.XLOOKUP(Table2[[#This Row],[Employee_ID]],Table5[Employee_ID],Table5[Employee Name],"Not Found") -> Rahul Krishnan | W13: 1 | X13: 1019.42 | Y13: 5 | Z13: 50.97 | AA13: 12 | AB13: 116.21 | AC13: 1084.66 | AD13: 828.44 | AE13: =(AC13-AD13-AB13) -> 140.01 | AF13: UPI | AG13: =IFERROR(Table2[[#This Row],[Profit]]/Table2[[#This Row],[Sales Amount]],0) -> 0.12908192 | AH13: =TRIM(Table2[[#This Row],[Payment Modee]]) -> UPI | AI13: Online | AJ13: Not Returned | AK13: 18:28 | AL13: =IF(HOUR(Table2[[#This Row],[Order Time]])<12,"Morning",IF(HOUR(Table2[[#This Row],[Order Time]])<17,"Afternoon",IF(HOUR(Table2[[#This Row],[Order Time]])<21,"Evening","Night"))) -> Evening | AM13: Weekday
... A68: INV100067 | B68: 45622 | C68: =YEAR(Table2[[#This Row],[Invoice Date]]) -> 2024 | D68: =TEXT(Table2[[#This Row],[Invoice Date]],"mmm") -> Nov | E68: =Table2[[#This Row],[Store_ID]]&"-"&Table2[[#This Row],[Year]]&"-"&Table2[[#This Row],[Month]] -> STR100-2024-Nov | F68: CUST0746 | G68: =_xlfn.XLOOKUP(Table2[[#This Row],[Customer_ID]],Table3[Customer_ID],Table3[Customer Name],"Not Found") -> Pandian Venkatesan | H68: =_xlfn.XLOOKUP(Table2[[#This Row],[Customer_ID]],Table3[Customer_ID],Table3[Gender],"Female") -> Male | I68: =_xlfn.XLOOKUP(Table2[[#This Row],[Customer_ID]],Table3[Customer_ID],Table3[City],"Missing Memebership") -> Kalaburagi | J68: =_xlfn.XLOOKUP(Table2[[#This Row],[Customer_ID]],Table3[Customer_ID],Table3[State],"Karnataka") -> Karnataka | K68: =_xlfn.XLOOKUP(Table2[[#This Row],[Customer_ID]],Table3[Customer_ID],Table3[Membership],"Regular") -> Silver | L68: PRD0019 | M68: =_xlfn.XLOOKUP(Table2[[#This Row],[Product_ID]],Table4[Product_ID],Table4[Product_Name],"Not Found") -> Sonata Girls Frock Cream | N68: =_xlfn.XLOOKUP(Table2[[#This Row],[Product_ID]],Table4[Product_ID],Table4[Category],"Not Found") -> Kids Wear | O68: =_xlfn.XLOOKUP(Table2[[#This Row],[Product_ID]],Table4[Product_ID],Table4[Subcategory],"Not Found") -> Kids T-Shirt | P68: =_xlfn.XLOOKUP(Table2[[#This Row],[Product_ID]],Table4[Product_ID],Table4[Brand],"Missing Brand") -> Jack & Jones | Q68: STR100 | R68: =_xlfn.XLOOKUP(Table2[[#This Row],[Store_ID]],Table6[Store_ID],Table6[Store Name],"Not Found") -> TrendMart Hubballi Standard | S68: =_xlfn.XLOOKUP(Table2[[#This Row],[Store_ID]],Table6[Store_ID],Table6[Monthly Target],"Missing Target") -> 2500000 | T68: =_xlfn.XLOOKUP(Table2[[#This Row],[Store_ID]],Table6[Store_ID],Table6[Region],"Not Found") -> South Zone 2 | U68: EMP0141 | V68: =_xlfn.XLOOKUP(Table2[[#This Row],[Employee_ID]],Table5[Employee_ID],Table5[Employee Name],"Not Found") -> Dhruv Mishra | W68: 1 | X68: 640.02 | Y68: 25 | Z68: 160 | AA68: 5 | AB68: 24 | AC68: 504.02 | AD68: 413.39 | AE68: =(AC68-AD68-AB68) -> 66.63 | AF68: Cash | AG68: =IFERROR(Table2[[#This Row],[Profit]]/Table2[[#This Row],[Sales Amount]],0) -> 0.13219714 | AH68: =TRIM(Table2[[#This Row],[Payment Modee]]) -> Cash | AI68: Online | AJ68: Not Returned | AK68: 16:30 | AL68: =IF(HOUR(Table2[[#This Row],[Order Time]])<12,"Morning",IF(HOUR(Table2[[#This Row],[Order Time]])<17,"Afternoon",IF(HOUR(Table2[[#This Row],[Order Time]])<21,"Evening","Night"))) -> Afternoon | AM68: Weekday
A69: INV100068 | B69: 45541 | C69: =YEAR(Table2[[#This Row],[Invoice Date]]) -> 2024 | D69: =TEXT(Table2[[#This Row],[Invoice Date]],"mmm") -> Sep | E69: =Table2[[#This Row],[Store_ID]]&"-"&Table2[[#This Row],[Year]]&"-"&Table2[[#This Row],[Month]] -> STR112-2024-Sep | F69: CUST0583 | G69: =_xlfn.XLOOKUP(Table2[[#This Row],[Customer_ID]],Table3[Customer_ID],Table3[Customer Name],"Not Found") -> Feroz Naicker | H69: =_xlfn.XLOOKUP(Table2[[#This Row],[Customer_ID]],Table3[Customer_ID],Table3[Gender],"Female") -> Male | I69: =_xlfn.XLOOKUP(Table2[[#This Row],[Customer_ID]],Table3[Customer_ID],Table3[City],"Missing Memebership") -> Guntur | J69: =_xlfn.XLOOKUP(Table2[[#This Row],[Customer_ID]],Table3[Customer_ID],Table3[State],"Karnataka") -> Andhra Pradesh | K69: =_xlfn.XLOOKUP(Table2[[#This Row],[Customer_ID]],Table3[Customer_ID],Table3[Membership],"Regular") -> Silver | L69: PRD0134 | M69: =_xlfn.XLOOKUP(Table2[[#This Row],[Product_ID]],Table4[Product_ID],Table4[Product_Name],"Not Found") -> Jack & Jones Maxi Dress Maroon | N69: =_xlfn.XLOOKUP(Table2[[#This Row],[Product_ID]],Table4[Product_ID],Table4[Category],"Not Found") -> Women Dresses | O69: =_xlfn.XLOOKUP(Table2[[#This Row],[Product_ID]],Table4[Product_ID],Table4[Subcategory],"Not Found") -> Maxi Dress | P69: =_xlfn.XLOOKUP(Table2[[#This Row],[Product_ID]],Table4[Product_ID],Table4[Brand],"Missing Brand") -> Jack & Jones | Q69: STR112 | R69: =_xlfn.XLOOKUP(Table2[[#This Row],[Store_ID]],Table6[Store_ID],Table6[Store Name],"Not Found") -> TrendMart Guntur Outlet | S69: =_xlfn.XLOOKUP(Table2[[#This Row],[Store_ID]],Table6[Store_ID],Table6[Monthly Target],"Missing Target") -> 1500000 | T69: =_xlfn.XLOOKUP(Table2[[#This Row],[Store_ID]],Table6[Store_ID],Table6[Region],"Not Found") -> South Zone 3 | U69: EMP0203 | V69: =_xlfn.XLOOKUP(Table2[[#This Row],[Employee_ID]],Table5[Employee_ID],Table5[Employee Name],"Not Found") -> Rani Mishra | W69: 0 | X69: 924.29 | Y69: 0 | Z69: 0 | AA69: 5 | AB69: 0 | AC69: 0 | AD69: 0 | AE69: 0 | AF69: EMI | AG69: =IFERROR(Table2[[#This Row],[Profit]]/Table2[[#This Row],[Sales Amount]],0) -> 0 | AH69: =TRIM(Table2[[#This Row],[Payment Modee]]) -> EMI | AI69: Online | AJ69: Not Returned | AK69: 18:42 | AL69: =IF(HOUR(Table2[[#This Row],[Order Time]])<12,"Morning",IF(HOUR(Table2[[#This Row],[Order Time]])<17,"Afternoon",IF(HOUR(Table2[[#This Row],[Order Time]])<21,"Evening","Night"))) -> Evening | AM69: Weekday
A70: INV100069 | B70: 45622 | C70: =YEAR(Table2[[#This Row],[Invoice Date]]) -> 2024 | D70: =TEXT(Table2[[#This Row],[Invoice Date]],"mmm") -> Nov | E70: =Table2[[#This Row],[Store_ID]]&"-"&Table2[[#This Row],[Year]]&"-"&Table2[[#This Row],[Month]] -> STR088-2024-Nov | F70: CUST0422 | G70: =_xlfn.XLOOKUP(Table2[[#This Row],[Customer_ID]],Table3[Customer_ID],Table3[Customer Name],"Not Found") -> Malathi Shetty | H70: =_xlfn.XLOOKUP(Table2[[#This Row],[Customer_ID]],Table3[Customer_ID],Table3[Gender],"Female") -> Female | I70: =_xlfn.XLOOKUP(Table2[[#This Row],[Customer_ID]],Table3[Customer_ID],Table3[City],"Missing Memebership") -> Nellore | J70: =_xlfn.XLOOKUP(Table2[[#This Row],[Customer_ID]],Table3[Customer_ID],Table3[State],"Karnataka") -> Andhra Pradesh | K70: =_xlfn.XLOOKUP(Table2[[#This Row],[Customer_ID]],Table3[Customer_ID],Table3[Membership],"Regular") -> Silver | L70: PRD0117 | M70: =_xlfn.XLOOKUP(Table2[[#This Row],[Product_ID]],Table4[Product_ID],Table4[Product_Name],"Not Found") -> Nike Shirt Dress Peach | N70: =_xlfn.XLOOKUP(Table2[[#This Row],[Product_ID]],Table4[Product_ID],Table4[Category],"Not Found") -> Women Dresses | O70: =_xlfn.XLOOKUP(Table2[[#This Row],[Product_ID]],Table4[Product_ID],Table4[Subcategory],"Not Found") -> Shirt Dress | P70: =_xlfn.XLOOKUP(Table2[[#This Row],[Product_ID]],Table4[Product_ID],Table4[Brand],"Missing Brand") -> Nike | Q70: STR088 | R70: =_xlfn.XLOOKUP(Table2[[#This Row],[Store_ID]],Table6[Store_ID],Table6[Store Name],"Not Found") -> TrendMart Warangal High Street | S70: =_xlfn.XLOOKUP(Table2[[#This Row],[Store_ID]],Table6[Store_ID],Table6[Monthly Target],"Missing Target") -> 2000000 | T70: =_xlfn.XLOOKUP(Table2[[#This Row],[Store_ID]],Table6[Store_ID],Table6[Region],"Not Found") -> South Zone 2 | U70: EMP0204 | V70: =_xlfn.XLOOKUP(Table2[[#This Row],[Employee_ID]],Table5[Employee_ID],Table5[Employee Name],"Not Found") -> Rahul Krishnan | W70: 2 | X70: 1714.04 | Y70: 10 | Z70: 342.81 | AA70: 12 | AB70: 370.23 | AC70: 3455.5 | AD70: 2799.7 | AE70: =(AC70-AD70-AB70) -> 285.57 | AF70: Cash | AG70: =IFERROR(Table2[[#This Row],[Profit]]/Table2[[#This Row],[Sales Amount]],0) -> 0.082642165 | AH70: =TRIM(Table2[[#This Row],[Payment Modee]]) -> Cash | AI70: Online | AJ70: Not Returned | AK70: 19:44 | AL70: =IF(HOUR(Table2[[#This Row],[Order Time]])<12,"Morning",IF(HOUR(Table2[[#This Row],[Order Time]])<17,"Afternoon",IF(HOUR(Table2[[#This Row],[Order Time]])<21,"Evening","Night"))) -> Evening | AM70: Weekday
A71: INV100070 | B71: 45620 | C71: =YEAR(Table2[[#This Row],[Invoice Date]]) -> 2024 | D71: =TEXT(Table2[[#This Row],[Invoice Date]],"mmm") -> Nov | E71: =Table2[[#This Row],[Store_ID]]&"-"&Table2[[#This Row],[Year]]&"-"&Table2[[#This Row],[Month]] -> STR096-2024-Nov | F71: CUST0613 | G71: =_xlfn.XLOOKUP(Table2[[#This Row],[Customer_ID]],Table3[Customer_ID],Table3[Customer Name],"Not Found") -> Usha Krishnan | H71: =_xlfn.XLOOKUP(Table2[[#This Row],[Customer_ID]],Table3[Customer_ID],Table3[Gender],"Female") -> Female | I71: =_xlfn.XLOOKUP(Table2[[#This Row],[Customer_ID]],Table3[Customer_ID],Table3[City],"Missing Memebership") -> Kalaburagi | J71: =_xlfn.XLOOKUP(Table2[[#This Row],[Customer_ID]],Table3[Customer_ID],Table3[State],"Karnataka") -> Karnataka | K71: =_xlfn.XLOOKUP(Table2[[#This Row],[Customer_ID]],Table3[Customer_ID],Table3[Membership],"Regular") -> Gold | L71: PRD0116 | M71: =_xlfn.XLOOKUP(Table2[[#This Row],[Product_ID]],Table4[Product_ID],Table4[Product_Name],"Not Found") -> Woodland Bootcut Peach | N71: =_xlfn.XLOOKUP(Table2[[#This Row],[Product_ID]],Table4[Product_ID],Table4[Category],"Not Found") -> Women Jeans | O71: =_xlfn.XLOOKUP(Table2[[#This Row],[Product_ID]],Table4[Product_ID],Table4[Subcategory],"Not Found") -> Bootcut | P71: =_xlfn.XLOOKUP(Table2[[#This Row],[Product_ID]],Table4[Product_ID],Table4[Brand],"Missing Brand") -> Woodland | Q71: STR096 | R71: =_xlfn.XLOOKUP(Table2[[#This Row],[Store_ID]],Table6[Store_ID],Table6[Store Name],"Not Found") -> TrendMart Mangaluru Mall Kiosk | S71: =_xlfn.XLOOKUP(Table2[[#This Row],[Store_ID]],Table6[Store_ID],Table6[Monthly Target],"Missing Target") -> 1500000 | T71: =_xlfn.XLOOKUP(Table2[[#This Row],[Store_ID]],Table6[Store_ID],Table6[Region],"Not Found") -> South Zone 2 | U71: EMP0215 | V71: =_xlfn.XLOOKUP(Table2[[#This Row],[Employee_ID]],Table5[Employee_ID],Table5[Employee Name],"Not Found") -> Praveen Gupta | W71: 3 | X71: 1579.45 | Y71: 15 | Z71: 710.75 | AA71: 12 | AB71: 483.31 | AC71: 4510.91 | AD71: 3146.13 | AE71: =(AC71-AD71-AB71) -> 881.47 | AF71: Debit Card | AG71: =IFERROR(Table2[[#This Row],[Profit]]/Table2[[#This Row],[Sales Amount]],0) -> 0.19540847 | AH71: =TRIM(Table2[[#This Row],[Payment Modee]]) -> Debit Card | AI71: Online | AJ71: Not Returned | AK71: 21:51 | AL71: =IF(HOUR(Table2[[#This Row],[Order Time]])<12,"Morning",IF(HOUR(Table2[[#This Row],[Order Time]])<17,"Afternoon",IF(HOUR(Table2[[#This Row],[Order Time]])<21,"Evening","Night"))) -> Night | AM71: Weekend
A72: INV100071 | B72: 45426 | C72: =YEAR(Table2[[#This Row],[Invoice Date]]) -> 2024 | D72: =TEXT(Table2[[#This Row],[Invoice Date]],"mmm") -> May | E72: =Table2[[#This Row],[Store_ID]]&"-"&Table2[[#This Row],[Year]]&"-"&Table2[[#This Row],[Month]] -> STR016-2024-May | F72: CUST0131 | G72: =_xlfn.XLOOKUP(Table2[[#This Row],[Customer_ID]],Table3[Customer_ID],Table3[Customer Name],"Not Found") -> Jyothi Achari | H72: =_xlfn.XLOOKUP(Table2[[#This Row],[Customer_ID]],Table3[Customer_ID],Table3[Gender],"Female") -> Female | I72: =_xlfn.XLOOKUP(Table2[[#This Row],[Customer_ID]],Table3[Customer_ID],Table3[City],"Missing Memebership") -> Tiruchirappalli | J72: =_xlfn.XLOOKUP(Table2[[#This Row],[Customer_ID]],Table3[Customer_ID],Table3[State],"Karnataka") -> Tamil Nadu | K72: =_xlfn.XLOOKUP(Table2[[#This Row],[Customer_ID]],Table3[Customer_ID],Table3[Membership],"Regular") -> Regular | L72: PRD0115 | M72: =_xlfn.XLOOKUP(Table2[[#This Row],[Product_ID]],Table4[Product_ID],Table4[Product_Name],"Not Found") -> Reebok Bodycon Dress Navy Blue | N72: =_xlfn.XLOOKUP(Table2[[#This Row],[Product_ID]],Table4[Product_ID],Table4[Category],"Not Found") -> Women Dresses | O72: =_xlfn.XLOOKUP(Table2[[#This Row],[Product_ID]],Table4[Product_ID],Table4[Subcategory],"Not Found") -> Bodycon Dress | P72: =_xlfn.XLOOKUP(Table2[[#This Row],[Product_ID]],Table4[Product_ID],Table4[Brand],"Missing Brand") -> Reebok | Q72: STR016 | R72: =_xlfn.XLOOKUP(Table2[[#This Row],[Store_ID]],Table6[Store_ID],Table6[Store Name],"Not Found") -> TrendMart Visakhapatnam Flagship | S72: =_xlfn.XLOOKUP(Table2[[#This Row],[Store_ID]],Table6[Store_ID],Table6[Monthly Target],"Missing Target") -> 1200000 | T72: =_xlfn.XLOOKUP(Table2[[#This Row],[Store_ID]],Table6[Store_ID],Table6[Region],"Not Found") -> South Zone 3 | U72: EMP0258 | V72: =_xlfn.XLOOKUP(Table2[[#This Row],[Employee_ID]],Table5[Employee_ID],Table5[Employee Name],"Not Found") -> Preethi Singh | W72: 1 | X72: 1632.35 | Y72: 5 | Z72: 81.62 | AA72: 12 | AB72: 186.09 | AC72: 1736.82 | AD72: 1140.9 | AE72: =(AC72-AD72-AB72) -> 409.83 | AF72: Net Banking | AG72: =IFERROR(Table2[[#This Row],[Profit]]/Table2[[#This Row],[Sales Amount]],0) -> 0.23596573 | AH72: =TRIM(Table2[[#This Row],[Payment Modee]]) -> Net Banking | AI72: Online | AJ72: Not Returned | AK72: 19:45 | AL72: =IF(HOUR(Table2[[#This Row],[Order Time]])<12,"Morning",IF(HOUR(Table2[[#This Row],[Order Time]])<17,"Afternoon",IF(HOUR(Table2[[#This Row],[Order Time]])<21,"Evening","Night"))) -> Evening | AM72: Weekday
A73: INV100072 | B73: 45586 | C73: =YEAR(Table2[[#This Row],[Invoice Date]]) -> 2024 | D73: =TEXT(Table2[[#This Row],[Invoice Date]],"mmm") -> Oct | E73: =Table2[[#This Row],[Store_ID]]&"-"&Table2[[#This Row],[Year]]&"-"&Table2[[#This Row],[Month]] -> STR074-2024-Oct | F73: CUST0338 | G73: =_xlfn.XLOOKUP(Table2[[#This Row],[Customer_ID]],Table3[Customer_ID],Table3[Customer Name],"Not Found") -> Vijay Prasad | H73: =_xlfn.XLOOKUP(Table2[[#This Row],[Customer_ID]],Table3[Customer_ID],Table3[Gender],"Female") -> Male | I73: =_xlfn.XLOOKUP(Table2[[#This Row],[Customer_ID]],Table3[Customer_ID],Table3[City],"Missing Memebership") -> Karimnagar | J73: =_xlfn.XLOOKUP(Table2[[#This Row],[Customer_ID]],Table3[Customer_ID],Table3[State],"Karnataka") -> Telangana | K73: =_xlfn.XLOOKUP(Table2[[#This Row],[Customer_ID]],Table3[Customer_ID],Table3[Membership],"Regular") -> Silver | L73: PRD0034 | M73: =_xlfn.XLOOKUP(Table2[[#This Row],[Product_ID]],Table4[Product_ID],Table4[Product_Name],"Not Found") -> Nike Casual Belt Olive | N73: =_xlfn.XLOOKUP(Table2[[#This Row],[Product_ID]],Table4[Product_ID],Table4[Category],"Not Found") -> Belts | O73: =_xlfn.XLOOKUP(Table2[[#This Row],[Product_ID]],Table4[Product_ID],Table4[Subcategory],"Not Found") -> Casual Belt | P73: =_xlfn.XLOOKUP(Table2[[#This Row],[Product_ID]],Table4[Product_ID],Table4[Brand],"Missing Brand") -> Nike | Q73: STR074 | R73: =_xlfn.XLOOKUP(Table2[[#This Row],[Store_ID]],Table6[Store_ID],Table6[Store Name],"Not Found") -> TrendMart Kurnool High Street | S73: =_xlfn.XLOOKUP(Table2[[#This Row],[Store_ID]],Table6[Store_ID],Table6[Monthly Target],"Missing Target") -> 1200000 | T73: =_xlfn.XLOOKUP(Table2[[#This Row],[Store_ID]],Table6[Store_ID],Table6[Region],"Not Found") -> South Zone 3 | U73: EMP0149 | V73: =_xlfn.XLOOKUP(Table2[[#This Row],[Employee_ID]],Table5[Employee_ID],Table5[Employee Name],"Not Found") -> Vasanthi Kamath | W73: 0 | X73: 413.58 | Y73: 0 | Z73: 0 | AA73: 5 | AB73: 0 | AC73: 0 | AD73: 0 | AE73: 0 | AF73: EMI | AG73: =IFERROR(Table2[[#This Row],[Profit]]/Table2[[#This Row],[Sales Amount]],0) -> 0 | AH73: =TRIM(Table2[[#This Row],[Payment Modee]]) -> EMI | AI73: Online | AJ73: Not Returned | AK73: 21:44 | AL73: =IF(HOUR(Table2[[#This Row],[Order Time]])<12,"Morning",IF(HOUR(Table2[[#This Row],[Order Time]])<17,"Afternoon",IF(HOUR(Table2[[#This Row],[Order Time]])<21,"Evening","Night"))) -> Night | AM73: Weekday
A74: INV100073 | B74: 45693 | C74: =YEAR(Table2[[#This Row],[Invoice Date]]) -> 2025 | D74: =TEXT(Table2[[#This Row],[Invoice Date]],"mmm") -> Feb | E74: =Table2[[#This Row],[Store_ID]]&"-"&Table2[[#This Row],[Year]]&"-"&Table2[[#This Row],[Month]] -> STR110-2025-Feb | F74: CUST0721 | G74: =_xlfn.XLOOKUP(Table2[[#This Row],[Customer_ID]],Table3[Customer_ID],Table3[Customer Name],"Not Found") -> Kavya Singh | H74: =_xlfn.XLOOKUP(Table2[[#This Row],[Customer_ID]],Table3[Customer_ID],Table3[Gender],"Female") -> Female | I74: =_xlfn.XLOOKUP(Table2[[#This Row],[Customer_ID]],Table3[Customer_ID],Table3[City],"Missing Memebership") -> Khammam | J74: =_xlfn.XLOOKUP(Table2[[#This Row],[Customer_ID]],Table3[Customer_ID],Table3[State],"Karnataka") -> Telangana | K74: =_xlfn.XLOOKUP(Table2[[#This Row],[Customer_ID]],Table3[Customer_ID],Table3[Membership],"Regular") -> Regular | L74: PRD0082 | M74: =_xlfn.XLOOKUP(Table2[[#This Row],[Product_ID]],Table4[Product_ID],Table4[Product_Name],"Not Found") -> Libas Sling Bag Green | N74: =_xlfn.XLOOKUP(Table2[[#This Row],[Product_ID]],Table4[Product_ID],Table4[Category],"Not Found") -> Handbags | O74: =_xlfn.XLOOKUP(Table2[[#This Row],[Product_ID]],Table4[Product_ID],Table4[Subcategory],"Not Found") -> Sling Bag | P74: =_xlfn.XLOOKUP(Table2[[#This Row],[Product_ID]],Table4[Product_ID],Table4[Brand],"Missing Brand") -> Libas | Q74: STR110 | R74: =_xlfn.XLOOKUP(Table2[[#This Row],[Store_ID]],Table6[Store_ID],Table6[Store Name],"Not Found") -> TrendMart Thoothukudi Outlet | S74: =_xlfn.XLOOKUP(Table2[[#This Row],[Store_ID]],Table6[Store_ID],Table6[Monthly Target],"Missing Target") -> 1000000 | T74: =_xlfn.XLOOKUP(Table2[[#This Row],[Store_ID]],Table6[Store_ID],Table6[Region],"Not Found") -> South Zone 1 | U74: EMP0141 | V74: =_xlfn.XLOOKUP(Table2[[#This Row],[Employee_ID]],Table5[Employee_ID],Table5[Employee Name],"Not Found") -> Dhruv Mishra | W74: 3 | X74: 2846.44 | Y74: 5 | Z74: 426.97 | AA74: 12 | AB74: 973.48 | AC74: 9085.83 | AD74: 6454.02 | AE74: =(AC74-AD74-AB74) -> 1658.33 | AF74: Debit Card | AG74: =IFERROR(Table2[[#This Row],[Profit]]/Table2[[#This Row],[Sales Amount]],0) -> 0.18251827 | AH74: =TRIM(Table2[[#This Row],[Payment Modee]]) -> Debit Card | AI74: Online | AJ74: Not Returned | AK74: 21:32 | AL74: =IF(HOUR(Table2[[#This Row],[Order Time]])<12,"Morning",IF(HOUR(Table2[[#This Row],[Order Time]])<17,"Afternoon",IF(HOUR(Table2[[#This Row],[Order Time]])<21,"Evening","Night"))) -> Night | AM74: Weekday
A75: INV100074 | B75: 45399 | C75: =YEAR(Table2[[#This Row],[Invoice Date]]) -> 2024 | D75: =TEXT(Table2[[#This Row],[Invoice Date]],"mmm") -> Apr | E75: =Table2[[#This Row],[Store_ID]]&"-"&Table2[[#This Row],[Year]]&"-"&Table2[[#This Row],[Month]] -> STR055-2024-Apr | F75: CUST0210 | G75: =_xlfn.XLOOKUP(Table2[[#This Row],[Customer_ID]],Table3[Customer_ID],Table3[Customer Name],"Not Found") -> Priya Pandian | H75: =_xlfn.XLOOKUP(Table2[[#This Row],[Customer_ID]],Table3[Customer_ID],Table3[Gender],"Female") -> Female | I75: =_xlfn.XLOOKUP(Table2[[#This Row],[Customer_ID]],Table3[Customer_ID],Table3[City],"Missing Memebership") -> Hubballi | J75: =_xlfn.XLOOKUP(Table2[[#This Row],[Customer_ID]],Table3[Customer_ID],Table3[State],"Karnataka") -> Karnataka | K75: =_xlfn.XLOOKUP(Table2[[#This Row],[Customer_ID]],Table3[Customer_ID],Table3[Membership],"Regular") -> Regular | L75: PRD0075 | M75: =_xlfn.XLOOKUP(Table2[[#This Row],[Product_ID]],Table4[Product_ID],Table4[Product_Name],"Not Found") -> Sonata Bootcut Navy Blue | N75: =_xlfn.XLOOKUP(Table2[[#This Row],[Product_ID]],Table4[Product_ID],Table4[Category],"Not Found") -> Women Jeans | O75: =_xlfn.XLOOKUP(Table2[[#This Row],[Product_ID]],Table4[Product_ID],Table4[Subcategory],"Not Found") -> Bootcut | P75: =_xlfn.XLOOKUP(Table2[[#This Row],[Product_ID]],Table4[Product_ID],Table4[Brand],"Missing Brand") -> Sonata | Q75: STR055 | R75: =_xlfn.XLOOKUP(Table2[[#This Row],[Store_ID]],Table6[Store_ID],Table6[Store Name],"Not Found") -> TrendMart Nellore High Street | S75: =_xlfn.XLOOKUP(Table2[[#This Row],[Store_ID]],Table6[Store_ID],Table6[Monthly Target],"Missing Target") -> 1500000 | T75: =_xlfn.XLOOKUP(Table2[[#This Row],[Store_ID]],Table6[Store_ID],Table6[Region],"Not Found") -> South Zone 3 | U75: EMP0285 | V75: =_xlfn.XLOOKUP(Table2[[#This Row],[Employee_ID]],Table5[Employee_ID],Table5[Employee Name],"Not Found") -> Chandran Krishnan | W75: 1 | X75: 1011.81 | Y75: 30 | Z75: 303.54 | AA75: 12 | AB75: 84.99 | AC75: 793.26 | AD75: 692.53 | AE75: =(AC75-AD75-AB75) -> 15.74 | AF75: UPI | AG75: =IFERROR(Table2[[#This Row],[Profit]]/Table2[[#This Row],[Sales Amount]],0) -> 0.01984217 | AH75: =TRIM(Table2[[#This Row],[Payment Modee]]) -> UPI | AI75: Offline | AJ75: Not Returned | AK75: 16:33 | AL75: =IF(HOUR(Table2[[#This Row],[Order Time]])<12,"Morning",IF(HOUR(Table2[[#This Row],[Order Time]])<17,"Afternoon",IF(HOUR(Table2[[#This Row],[Order Time]])<21,"Evening","Night"))) -> Afternoon | AM75: Weekday
A76: INV100075 | B76: 45620 | C76: =YEAR(Table2[[#This Row],[Invoice Date]]) -> 2024 | D76: =TEXT(Table2[[#This Row],[Invoice Date]],"mmm") -> Nov | E76: =Table2[[#This Row],[Store_ID]]&"-"&Table2[[#This Row],[Year]]&"-"&Table2[[#This Row],[Month]] -> STR045-2024-Nov | F76: CUST0658 | G76: =_xlfn.XLOOKUP(Table2[[#This Row],[Customer_ID]],Table3[Customer_ID],Table3[Customer Name],"Not Found") -> Kiran Gupta | H76: =_xlfn.XLOOKUP(Table2[[#This Row],[Customer_ID]],Table3[Customer_ID],Table3[Gender],"Female") -> Male | I76: =_xlfn.XLOOKUP(Table2[[#This Row],[Customer_ID]],Table3[Customer_ID],Table3[City],"Missing Memebership") -> Vellore | J76: =_xlfn.XLOOKUP(Table2[[#This Row],[Customer_ID]],Table3[Customer_ID],Table3[State],"Karnataka") -> Tamil Nadu | K76: =_xlfn.XLOOKUP(Table2[[#This Row],[Customer_ID]],Table3[Customer_ID],Table3[Membership],"Regular") -> Gold | L76: PRD0203 | M76: =_xlfn.XLOOKUP(Table2[[#This Row],[Product_ID]],Table4[Product_ID],Table4[Product_Name],"Not Found") -> Liberty Sports T-Shirt Peach | N76: =_xlfn.XLOOKUP(Table2[[#This Row],[Product_ID]],Table4[Product_ID],Table4[Category],"Not Found") -> Sportswear | O76: =_xlfn.XLOOKUP(Table2[[#This Row],[Product_ID]],Table4[Product_ID],Table4[Subcategory],"Not Found") -> Sports T-Shirt | P76: =_xlfn.XLOOKUP(Table2[[#This Row],[Product_ID]],Table4[Product_ID],Table4[Brand],"Missing Brand") -> Liberty | Q76: STR045 | R76: =_xlfn.XLOOKUP(Table2[[#This Row],[Store_ID]],Table6[Store_ID],Table6[Store Name],"Not Found") -> TrendMart Khammam Standard | S76: =_xlfn.XLOOKUP(Table2[[#This Row],[Store_ID]],Table6[Store_ID],Table6[Monthly Target],"Missing Target") -> 1500000 | T76: =_xlfn.XLOOKUP(Table2[[#This Row],[Store_ID]],Table6[Store_ID],Table6[Region],"Not Found") -> South Zone 2 | U76: EMP0255 | V76: =_xlfn.XLOOKUP(Table2[[#This Row],[Employee_ID]],Table5[Employee_ID],Table5[Employee Name],"Not Found") -> Venkat Sharma | W76: 5 | X76: 1268.61 | Y76: 15 | Z76: 951.46 | AA76: 12 | AB76: 646.99 | AC76: 6038.58 | AD76: 4573.6 | AE76: =(AC76-AD76-AB76) -> 817.99 | AF76: Debit Card | AG76: =IFERROR(Table2[[#This Row],[Profit]]/Table2[[#This Row],[Sales Amount]],0) -> 0.13546065 | AH76: =TRIM(Table2[[#This Row],[Payment Modee]]) -> Debit Card | AI76: Offline | AJ76: Not Returned | AK76: 19:17 | AL76: =IF(HOUR(Table2[[#This Row],[Order Time]])<12,"Morning",IF(HOUR(Table2[[#This Row],[Order Time]])<17,"Afternoon",IF(HOUR(Table2[[#This Row],[Order Time]])<21,"Evening","Night"))) -> Evening | AM76: Weekend
A77: INV100076 | B77: 45633 | C77: =YEAR(Table2[[#This Row],[Invoice Date]]) -> 2024 | D77: =TEXT(Table2[[#This Row],[Invoice Date]],"mmm") -> Dec | E77: =Table2[[#This Row],[Store_ID]]&"-"&Table2[[#This Row],[Year]]&"-"&Table2[[#This Row],[Month]] -> STR104-2024-Dec | F77: CUST0636 | G77: =_xlfn.XLOOKUP(Table2[[#This Row],[Customer_ID]],Table3[Customer_ID],Table3[Customer Name],"Not Found") -> Gayathri Gowda | H77: =_xlfn.XLOOKUP(Table2[[#This Row],[Customer_ID]],Table3[Customer_ID],Table3[Gender],"Female") -> Female | I77: =_xlfn.XLOOKUP(Table2[[#This Row],[Customer_ID]],Table3[Customer_ID],Table3[City],"Missing Memebership") -> Mangaluru | J77: =_xlfn.XLOOKUP(Table2[[#This Row],[Customer_ID]],Table3[Customer_ID],Table3[State],"Karnataka") -> Karnataka | K77: =_xlfn.XLOOKUP(Table2[[#This Row],[Customer_ID]],Table3[Customer_ID],Table3[Membership],"Regular") -> Regular | L77: PRD0022 | M77: =_xlfn.XLOOKUP(Table2[[#This Row],[Product_ID]],Table4[Product_ID],Table4[Product_Name],"Not Found") -> Being Human Skinny Fit Charcoal | N77: =_xlfn.XLOOKUP(Table2[[#This Row],[Product_ID]],Table4[Product_ID],Table4[Category],"Not Found") -> Women Jeans | O77: =_xlfn.XLOOKUP(Table2[[#This Row],[Product_ID]],Table4[Product_ID],Table4[Subcategory],"Not Found") -> Skinny Fit | P77: =_xlfn.XLOOKUP(Table2[[#This Row],[Product_ID]],Table4[Product_ID],Table4[Brand],"Missing Brand") -> Being Human | Q77: STR104 | R77: =_xlfn.XLOOKUP(Table2[[#This Row],[Store_ID]],Table6[Store_ID],Table6[Store Name],"Not Found") -> TrendMart Kochi High Street | S77: =_xlfn.XLOOKUP(Table2[[#This Row],[Store_ID]],Table6[Store_ID],Table6[Monthly Target],"Missing Target") -> 1200000 | T77: =_xlfn.XLOOKUP(Table2[[#This Row],[Store_ID]],Table6[Store_ID],Table6[Region],"Not Found") -> South Zone 1 | U77: EMP0086 | V77: =_xlfn.XLOOKUP(Table2[[#This Row],[Employee_ID]],Table5[Employee_ID],Table5[Employee Name],"Not Found") -> Anil Reddy | W77: 1 | X77: 1323.12 | Y77: 0 | Z77: 0 | AA77: 12 | AB77: 158.77 | AC77: 1481.89 | AD77: 767.83 | AE77: =(AC77-AD77-AB77) -> 555.29 | AF77: Credit Card | AG77: =IFERROR(Table2[[#This Row],[Profit]]/Table2[[#This Row],[Sales Amount]],0) -> 0.37471742 | AH77: =TRIM(Table2[[#This Row],[Payment Modee]]) -> Credit Card | AI77: Offline | AJ77: Not Returned | AK77: 11:24 | AL77: =IF(HOUR(Table2[[#This Row],[Order Time]])<12,"Morning",IF(HOUR(Table2[[#This Row],[Order Time]])<17,"Afternoon",IF(HOUR(Table2[[#This Row],[Order Time]])<21,"Evening","Night"))) -> Morning | AM77: Weekend
A78: INV100077 | B78: 45396 | C78: =YEAR(Table2[[#This Row],[Invoice Date]]) -> 2024 | D78: =TEXT(Table2[[#This Row],[Invoice Date]],"mmm") -> Apr | E78: =Table2[[#This Row],[Store_ID]]&"-"&Table2[[#This Row],[Year]]&"-"&Table2[[#This Row],[Month]] -> STR082-2024-Apr | F78: CUST0461 | G78: =_xlfn.XLOOKUP(Table2[[#This Row],[Customer_ID]],Table3[Customer_ID],Table3[Customer Name],"Not Found") -> Bindu Mishra | H78: =_xlfn.XLOOKUP(Table2[[#This Row],[Customer_ID]],Table3[Customer_ID],Table3[Gender],"Female") -> Female | I78: =_xlfn.XLOOKUP(Table2[[#This Row],[Customer_ID]],Table3[Customer_ID],Table3[City],"Missing Memebership") -> Kozhikode | J78: =_xlfn.XLOOKUP(Table2[[#This Row],[Customer_ID]],Table3[Customer_ID],Table3[State],"Karnataka") -> Kerala | K78: =_xlfn.XLOOKUP(Table2[[#This Row],[Customer_ID]],Table3[Customer_ID],Table3[Membership],"Regular") -> Regular | L78: PRD0228 | M78: =_xlfn.XLOOKUP(Table2[[#This Row],[Product_ID]],Table4[Product_ID],Table4[Product_Name],"Not Found") -> Nike Bifold Wallet Navy Blue | N78: =_xlfn.XLOOKUP(Table2[[#This Row],[Product_ID]],Table4[Product_ID],Table4[Category],"Not Found") -> Wallets | O78: =_xlfn.XLOOKUP(Table2[[#This Row],[Product_ID]],Table4[Product_ID],Table4[Subcategory],"Not Found") -> Bifold Wallet | P78: =_xlfn.XLOOKUP(Table2[[#This Row],[Product_ID]],Table4[Product_ID],Table4[Brand],"Missing Brand") -> Nike | Q78: STR082 | R78: =_xlfn.XLOOKUP(Table2[[#This Row],[Store_ID]],Table6[Store_ID],Table6[Store Name],"Not Found") -> TrendMart Tirupati Standard | S78: =_xlfn.XLOOKUP(Table2[[#This Row],[Store_ID]],Table6[Store_ID],Table6[Monthly Target],"Missing Target") -> 1000000 | T78: =_xlfn.XLOOKUP(Table2[[#This Row],[Store_ID]],Table6[Store_ID],Table6[Region],"Not Found") -> South Zone 3 | U78: EMP0127 | V78: =_xlfn.XLOOKUP(Table2[[#This Row],[Employee_ID]],Table5[Employee_ID],Table5[Employee Name],"Not Found") -> Chandra Reddy | W78: 2 | X78: 1419.26 | Y78: 20 | Z78: 567.7 | AA78: 12 | AB78: 272.5 | AC78: 2543.32 | AD78: 1806.6 | AE78: =(AC78-AD78-AB78) -> 464.22 | AF78: Credit Card | AG78: =IFERROR(Table2[[#This Row],[Profit]]/Table2[[#This Row],[Sales Amount]],0) -> 0.1825252 | AH78: =TRIM(Table2[[#This Row],[Payment Modee]]) -> Credit Card | AI78: Online | AJ78: Not Returned | AK78: 15:56 | AL78: =IF(HOUR(Table2[[#This Row],[Order Time]])<12,"Morning",IF(HOUR(Table2[[#This Row],[Order Time]])<17,"Afternoon",IF(HOUR(Table2[[#This Row],[Order Time]])<21,"Evening","Night"))) -> Afternoon | AM78: Weekend
A79: INV100078 | B79: 45443 | C79: =YEAR(Table2[[#This Row],[Invoice Date]]) -> 2024 | D79: =TEXT(Table2[[#This Row],[Invoice Date]],"mmm") -> May | E79: =Table2[[#This Row],[Store_ID]]&"-"&Table2[[#This Row],[Year]]&"-"&Table2[[#This Row],[Month]] -> STR001-2024-May | F79: CUST0006 | G79: =_xlfn.XLOOKUP(Table2[[#This Row],[Customer_ID]],Table3[Customer_ID],Table3[Customer Name],"Not Found") -> Rajesh Gopalakrishnan | H79: =_xlfn.XLOOKUP(Table2[[#This Row],[Customer_ID]],Table3[Customer_ID],Table3[Gender],"Female") -> Male | I79: =_xlfn.XLOOKUP(Table2[[#This Row],[Customer_ID]],Table3[Customer_ID],Table3[City],"Missing Memebership") -> Karimnagar | J79: =_xlfn.XLOOKUP(Table2[[#This Row],[Customer_ID]],Table3[Customer_ID],Table3[State],"Karnataka") -> Telangana | K79: =_xlfn.XLOOKUP(Table2[[#This Row],[Customer_ID]],Table3[Customer_ID],Table3[Membership],"Regular") -> Gold | L79: PRD0141 | M79: =_xlfn.XLOOKUP(Table2[[#This Row],[Product_ID]],Table4[Product_ID],Table4[Product_Name],"Not Found") -> Indian Terrain Formal Top Maroon | N79: =_xlfn.XLOOKUP(Table2[[#This Row],[Product_ID]],Table4[Product_ID],Table4[Category],"Not Found") -> Women Tops | O79: =_xlfn.XLOOKUP(Table2[[#This Row],[Product_ID]],Table4[Product_ID],Table4[Subcategory],"Not Found") -> Formal Top | P79: =_xlfn.XLOOKUP(Table2[[#This Row],[Product_ID]],Table4[Product_ID],Table4[Brand],"Missing Brand") -> Indian Terrain | Q79: STR001 | R79: =_xlfn.XLOOKUP(Table2[[#This Row],[Store_ID]],Table6[Store_ID],Table6[Store Name],"Not Found") -> TrendMart Kollam Standard | S79: =_xlfn.XLOOKUP(Table2[[#This Row],[Store_ID]],Table6[Store_ID],Table6[Monthly Target],"Missing Target") -> 2500000 | T79: =_xlfn.XLOOKUP(Table2[[#This Row],[Store_ID]],Table6[Store_ID],Table6[Region],"Not Found") -> South Zone 1 | U79: EMP0204 | V79: =_xlfn.XLOOKUP(Table2[[#This Row],[Employee_ID]],Table5[Employee_ID],Table5[Employee Name],"Not Found") -> Rahul Krishnan | W79: 4 | X79: 713.19 | Y79: 30 | Z79: 855.83 | AA79: 5 | AB79: 99.85 | AC79: 2096.78 | AD79: 2190.68 | AE79: =(AC79-AD79-AB79) -> -193.75 | AF79: UPI | AG79: =IFERROR(Table2[[#This Row],[Profit]]/Table2[[#This Row],[Sales Amount]],0) -> -0.09240359 | AH79: =TRIM(Table2[[#This Row],[Payment Modee]]) -> UPI | AI79: Offline | AJ79: Not Returned | AK79: 10:22 | AL79: =IF(HOUR(Table2[[#This Row],[Order Time]])<12,"Morning",IF(HOUR(Table2[[#This Row],[Order Time]])<17,"Afternoon",IF(HOUR(Table2[[#This Row],[Order Time]])<21,"Evening","Night"))) -> Morning | AM79: Weekday
A80: INV100079 | B80: 45544 | C80: =YEAR(Table2[[#This Row],[Invoice Date]]) -> 2024 | D80: =TEXT(Table2[[#This Row],[Invoice Date]],"mmm") -> Sep | E80: =Table2[[#This Row],[Store_ID]]&"-"&Table2[[#This Row],[Year]]&"-"&Table2[[#This Row],[Month]] -> STR032-2024-Sep | F80: CUST0310 | G80: =_xlfn.XLOOKUP(Table2[[#This Row],[Customer_ID]],Table3[Customer_ID],Table3[Customer Name],"Not Found") -> Nithya Yadav | H80: =_xlfn.XLOOKUP(Table2[[#This Row],[Customer_ID]],Table3[Customer_ID],Table3[Gender],"Female") -> Female | I80: =_xlfn.XLOOKUP(Table2[[#This Row],[Customer_ID]],Table3[Customer_ID],Table3[City],"Missing Memebership") -> Hyderabad | J80: =_xlfn.XLOOKUP(Table2[[#This Row],[Customer_ID]],Table3[Customer_ID],Table3[State],"Karnataka") -> Telangana | K80: =_xlfn.XLOOKUP(Table2[[#This Row],[Customer_ID]],Table3[Customer_ID],Table3[Membership],"Regular") -> Silver | L80: PRD0138 | M80: =_xlfn.XLOOKUP(Table2[[#This Row],[Product_ID]],Table4[Product_ID],Table4[Product_Name],"Not Found") -> Louis Philippe Formal Trouser Olive | N80: =_xlfn.XLOOKUP(Table2[[#This Row],[Product_ID]],Table4[Product_ID],Table4[Category],"Not Found") -> Men Trousers | O80: =_xlfn.XLOOKUP(Table2[[#This Row],[Product_ID]],Table4[Product_ID],Table4[Subcategory],"Not Found") -> Formal Trouser | P80: =_xlfn.XLOOKUP(Table2[[#This Row],[Product_ID]],Table4[Product_ID],Table4[Brand],"Missing Brand") -> Louis Philippe | Q80: STR032 | R80: =_xlfn.XLOOKUP(Table2[[#This Row],[Store_ID]],Table6[Store_ID],Table6[Store Name],"Not Found") -> TrendMart Kochi Standard | S80: =_xlfn.XLOOKUP(Table2[[#This Row],[Store_ID]],Table6[Store_ID],Table6[Monthly Target],"Missing Target") -> 2500000 | T80: =_xlfn.XLOOKUP(Table2[[#This Row],[Store_ID]],Table6[Store_ID],Table6[Region],"Not Found") -> South Zone 1 | U80: EMP0258 | V80: =_xlfn.XLOOKUP(Table2[[#This Row],[Employee_ID]],Table5[Employee_ID],Table5[Employee Name],"Not Found") -> Preethi Singh | W80: 4 | X80: 1255.49 | Y80: 0 | Z80: 0 | AA80: 12 | AB80: 602.64 | AC80: 5624.6 | AD80: 3647.36 | AE80: =(AC80-AD80-AB80) -> 1374.6 | AF80: Debit Card | AG80: =IFERROR(Table2[[#This Row],[Profit]]/Table2[[#This Row],[Sales Amount]],0) -> 0.24439071 | AH80: =TRIM(Table2[[#This Row],[Payment Modee]]) -> Debit Card | AI80: Online | AJ80: Not Returned | AK80: 13:12 | AL80: =IF(HOUR(Table2[[#This Row],[Order Time]])<12,"Morning",IF(HOUR(Table2[[#This Row],[Order Time]])<17,"Afternoon",IF(HOUR(Table2[[#This Row],[Order Time]])<21,"Evening","Night"))) -> Afternoon | AM80: Weekday
A81: INV100080 | B81: 45702 | C81: =YEAR(Table2[[#This Row],[Invoice Date]]) -> 2025 | D81: =TEXT(Table2[[#This Row],[Invoice Date]],"mmm") -> Feb | E81: =Table2[[#This Row],[Store_ID]]&"-"&Table2[[#This Row],[Year]]&"-"&Table2[[#This Row],[Month]] -> STR029-2025-Feb | F81: CUST0795 | G81: =_xlfn.XLOOKUP(Table2[[#This Row],[Customer_ID]],Table3[Customer_ID],Table3[Customer Name],"Not Found") -> Deepa Iyer | H81: =_xlfn.XLOOKUP(Table2[[#This Row],[Customer_ID]],Table3[Customer_ID],Table3[Gender],"Female") -> Female | I81: =_xlfn.XLOOKUP(Table2[[#This Row],[Customer_ID]],Table3[Customer_ID],Table3[City],"Missing Memebership") -> Karimnagar | J81: =_xlfn.XLOOKUP(Table2[[#This Row],[Customer_ID]],Table3[Customer_ID],Table3[State],"Karnataka") -> Telangana | K81: =_xlfn.XLOOKUP(Table2[[#This Row],[Customer_ID]],Table3[Customer_ID],Table3[Membership],"Regular") -> Regular | L81: PRD0043 | M81: =_xlfn.XLOOKUP(Table2[[#This Row],[Product_ID]],Table4[Product_ID],Table4[Product_Name],"Not Found") -> GRT Jewellers Sling Bag Olive | N81: =_xlfn.XLOOKUP(Table2[[#This Row],[Product_ID]],Table4[Product_ID],Table4[Category],"Not Found") -> Handbags | O81: =_xlfn.XLOOKUP(Table2[[#This Row],[Product_ID]],Table4[Product_ID],Table4[Subcategory],"Not Found") -> Sling Bag | P81: =_xlfn.XLOOKUP(Table2[[#This Row],[Product_ID]],Table4[Product_ID],Table4[Brand],"Missing Brand") -> GRT Jewellers | Q81: STR029 | R81: =_xlfn.XLOOKUP(Table2[[#This Row],[Store_ID]],Table6[Store_ID],Table6[Store Name],"Not Found") -> TrendMart Davanagere High Street | S81: =_xlfn.XLOOKUP(Table2[[#This Row],[Store_ID]],Table6[Store_ID],Table6[Monthly Target],"Missing Target") -> 800000 | T81: =_xlfn.XLOOKUP(Table2[[#This Row],[Store_ID]],Table6[Store_ID],Table6[Region],"Not Found") -> South Zone 2 | U81: EMP0206 | V81: =_xlfn.XLOOKUP(Table2[[#This Row],[Employee_ID]],Table5[Employee_ID],Table5[Employee Name],"Not Found") -> Arjun Krishnan | W81: 2 | X81: 3188.24 | Y81: 25 | Z81: 1594.12 | AA81: 12 | AB81: 573.88 | AC81: 5356.24 | AD81: 4068.02 | AE81: =(AC81-AD81-AB81) -> 714.34 | AF81: Cash | AG81: =IFERROR(Table2[[#This Row],[Profit]]/Table2[[#This Row],[Sales Amount]],0) -> 0.13336594 | AH81: =TRIM(Table2[[#This Row],[Payment Modee]]) -> Cash | AI81: Online | AJ81: Returned | AK81: 13:02 | AL81: =IF(HOUR(Table2[[#This Row],[Order Time]])<12,"Morning",IF(HOUR(Table2[[#This Row],[Order Time]])<17,"Afternoon",IF(HOUR(Table2[[#This Row],[Order Time]])<21,"Evening","Night"))) -> Afternoon | AM81: Weekday
A82: INV100081 | B82: 45534 | C82: =YEAR(Table2[[#This Row],[Invoice Date]]) -> 2024 | D82: =TEXT(Table2[[#This Row],[Invoice Date]],"mmm") -> Aug | E82: =Table2[[#This Row],[Store_ID]]&"-"&Table2[[#This Row],[Year]]&"-"&Table2[[#This Row],[Month]] -> STR050-2024-Aug | F82: CUST0659 | G82: =_xlfn.XLOOKUP(Table2[[#This Row],[Customer_ID]],Table3[Customer_ID],Table3[Customer Name],"Not Found") -> Nandini Natarajan | H82: =_xlfn.XLOOKUP(Table2[[#This Row],[Customer_ID]],Table3[Customer_ID],Table3[Gender],"Female") -> Female | I82: =_xlfn.XLOOKUP(Table2[[#This Row],[Customer_ID]],Table3[Customer_ID],Table3[City],"Missing Memebership") -> Chennai | J82: =_xlfn.XLOOKUP(Table2[[#This Row],[Customer_ID]],Table3[Customer_ID],Table3[State],"Karnataka") -> Tamil Nadu | K82: =_xlfn.XLOOKUP(Table2[[#This Row],[Customer_ID]],Table3[Customer_ID],Table3[Membership],"Regular") -> Gold | L82: PRD0178 | M82: =_xlfn.XLOOKUP(Table2[[#This Row],[Product_ID]],Table4[Product_ID],Table4[Product_Name],"Not Found") -> Aurelia Zip Wallet Red | N82: =_xlfn.XLOOKUP(Table2[[#This Row],[Product_ID]],Table4[Product_ID],Table4[Category],"Not Found") -> Wallets | O82: =_xlfn.XLOOKUP(Table2[[#This Row],[Product_ID]],Table4[Product_ID],Table4[Subcategory],"Not Found") -> Zip Wallet | P82: =_xlfn.XLOOKUP(Table2[[#This Row],[Product_ID]],Table4[Product_ID],Table4[Brand],"Missing Brand") -> Aurelia | Q82: STR050 | R82: =_xlfn.XLOOKUP(Table2[[#This Row],[Store_ID]],Table6[Store_ID],Table6[Store Name],"Not Found") -> TrendMart Thrissur High Street | S82: =_xlfn.XLOOKUP(Table2[[#This Row],[Store_ID]],Table6[Store_ID],Table6[Monthly Target],"Missing Target") -> 2000000 | T82: =_xlfn.XLOOKUP(Table2[[#This Row],[Store_ID]],Table6[Store_ID],Table6[Region],"Not Found") -> South Zone 1 | U82: EMP0149 | V82: =_xlfn.XLOOKUP(Table2[[#This Row],[Employee_ID]],Table5[Employee_ID],Table5[Employee Name],"Not Found") -> Vasanthi Kamath | W82: 3 | X82: 565.59 | Y82: 30 | Z82: 509.03 | AA82: 5 | AB82: 59.39 | AC82: 1247.13 | AD82: 1072.35 | AE82: =(AC82-AD82-AB82) -> 115.39 | AF82: UPI | AG82: =IFERROR(Table2[[#This Row],[Profit]]/Table2[[#This Row],[Sales Amount]],0) -> 0.092524436 | AH82: =TRIM(Table2[[#This Row],[Payment Modee]]) -> UPI | AI82: Online | AJ82: Not Returned | AK82: 14:47 | AL82: =IF(HOUR(Table2[[#This Row],[Order Time]])<12,"Morning",IF(HOUR(Table2[[#This Row],[Order Time]])<17,"Afternoon",IF(HOUR(Table2[[#This Row],[Order Time]])<21,"Evening","Night"))) -> Afternoon | AM82: Weekday
A83: INV100082 | B83: 45492 | C83: =YEAR(Table2[[#This Row],[Invoice Date]]) -> 2024 | D83: =TEXT(Table2[[#This Row],[Invoice Date]],"mmm") -> Jul | E83: =Table2[[#This Row],[Store_ID]]&"-"&Table2[[#This Row],[Year]]&"-"&Table2[[#This Row],[Month]] -> STR053-2024-Jul | F83: CUST0789 | G83: =_xlfn.XLOOKUP(Table2[[#This Row],[Customer_ID]],Table3[Customer_ID],Table3[Customer Name],"Not Found") -> Rohit Gupta | H83: =_xlfn.XLOOKUP(Table2[[#This Row],[Customer_ID]],Table3[Customer_ID],Table3[Gender],"Female") -> Male | I83: =_xlfn.XLOOKUP(Table2[[#This Row],[Customer_ID]],Table3[Customer_ID],Table3[City],"Missing Memebership") -> Kollam | J83: =_xlfn.XLOOKUP(Table2[[#This Row],[Customer_ID]],Table3[Customer_ID],Table3[State],"Karnataka") -> Kerala | K83: =_xlfn.XLOOKUP(Table2[[#This Row],[Customer_ID]],Table3[Customer_ID],Table3[Membership],"Regular") -> Gold | L83: PRD0043 | M83: =_xlfn.XLOOKUP(Table2[[#This Row],[Product_ID]],Table4[Product_ID],Table4[Product_Name],"Not Found") -> GRT Jewellers Sling Bag Olive | N83: =_xlfn.XLOOKUP(Table2[[#This Row],[Product_ID]],Table4[Product_ID],Table4[Category],"Not Found") -> Handbags | O83: =_xlfn.XLOOKUP(Table2[[#This Row],[Product_ID]],Table4[Product_ID],Table4[Subcategory],"Not Found") -> Sling Bag | P83: =_xlfn.XLOOKUP(Table2[[#This Row],[Product_ID]],Table4[Product_ID],Table4[Brand],"Missing Brand") -> GRT Jewellers | Q83: STR053 | R83: =_xlfn.XLOOKUP(Table2[[#This Row],[Store_ID]],Table6[Store_ID],Table6[Store Name],"Not Found") -> TrendMart Kochi Standard | S83: =_xlfn.XLOOKUP(Table2[[#This Row],[Store_ID]],Table6[Store_ID],Table6[Monthly Target],"Missing Target") -> 1500000 | T83: =_xlfn.XLOOKUP(Table2[[#This Row],[Store_ID]],Table6[Store_ID],Table6[Region],"Not Found") -> South Zone 1 | U83: EMP0260 | V83: =_xlfn.XLOOKUP(Table2[[#This Row],[Employee_ID]],Table5[Employee_ID],Table5[Employee Name],"Not Found") -> Malathi Varma | W83: 3 | X83: 3067.81 | Y83: 25 | Z83: 2300.86 | AA83: 12 | AB83: 828.31 | AC83: 7730.88 | AD83: 6102.03 | AE83: =(AC83-AD83-AB83) -> 800.54 | AF83: UPI | AG83: =IFERROR(Table2[[#This Row],[Profit]]/Table2[[#This Row],[Sales Amount]],0) -> 0.10355095 | AH83: =TRIM(Table2[[#This Row],[Payment Modee]]) -> UPI | AI83: Online | AJ83: Returned | AK83: 12:35 | AL83: =IF(HOUR(Table2[[#This Row],[Order Time]])<12,"Morning",IF(HOUR(Table2[[#This Row],[Order Time]])<17,"Afternoon",IF(HOUR(Table2[[#This Row],[Order Time]])<21,"Evening","Night"))) -> Afternoon | AM83: Weekday
A84: INV100083 | B84: 45456 | C84: =YEAR(Table2[[#This Row],[Invoice Date]]) -> 2024 | D84: =TEXT(Table2[[#This Row],[Invoice Date]],"mmm") -> Jun | E84: =Table2[[#This Row],[Store_ID]]&"-"&Table2[[#This Row],[Year]]&"-"&Table2[[#This Row],[Month]] -> STR110-2024-Jun | F84: CUST0326 | G84: =_xlfn.XLOOKUP(Table2[[#This Row],[Customer_ID]],Table3[Customer_ID],Table3[Customer Name],"Not Found") -> Deepa Prasad | H84: =_xlfn.XLOOKUP(Table2[[#This Row],[Customer_ID]],Table3[Customer_ID],Table3[Gender],"Female") -> Female | I84: =_xlfn.XLOOKUP(Table2[[#This Row],[Customer_ID]],Table3[Customer_ID],Table3[City],"Missing Memebership") -> Chennai | J84: =_xlfn.XLOOKUP(Table2[[#This Row],[Customer_ID]],Table3[Customer_ID],Table3[State],"Karnataka") -> Tamil Nadu | K84: =_xlfn.XLOOKUP(Table2[[#This Row],[Customer_ID]],Table3[Customer_ID],Table3[Membership],"Regular") -> Platinum | L84: PRD0151 | M84: =_xlfn.XLOOKUP(Table2[[#This Row],[Product_ID]],Table4[Product_ID],Table4[Product_Name],"Not Found") -> US Polo Assn Bootcut Black | N84: =_xlfn.XLOOKUP(Table2[[#This Row],[Product_ID]],Table4[Product_ID],Table4[Category],"Not Found") -> Women Jeans | O84: =_xlfn.XLOOKUP(Table2[[#This Row],[Product_ID]],Table4[Product_ID],Table4[Subcategory],"Not Found") -> Bootcut | P84: =_xlfn.XLOOKUP(Table2[[#This Row],[Product_ID]],Table4[Product_ID],Table4[Brand],"Missing Brand") -> US Polo Assn | Q84: STR110 | R84: =_xlfn.XLOOKUP(Table2[[#This Row],[Store_ID]],Table6[Store_ID],Table6[Store Name],"Not Found") -> TrendMart Thoothukudi Outlet | S84: =_xlfn.XLOOKUP(Table2[[#This Row],[Store_ID]],Table6[Store_ID],Table6[Monthly Target],"Missing Target") -> 1000000 | T84: =_xlfn.XLOOKUP(Table2[[#This Row],[Store_ID]],Table6[Store_ID],Table6[Region],"Not Found") -> South Zone 1 | U84: EMP0156 | V84: =_xlfn.XLOOKUP(Table2[[#This Row],[Employee_ID]],Table5[Employee_ID],Table5[Employee Name],"Not Found") -> Deepthi Iyengar | W84: 1 | X84: 1325.53 | Y84: 25 | Z84: 331.38 | AA84: 12 | AB84: 119.3 | AC84: 1113.45 | AD84: 834.96 | AE84: =(AC84-AD84-AB84) -> 159.19 | AF84: Credit Card | AG84: =IFERROR(Table2[[#This Row],[Profit]]/Table2[[#This Row],[Sales Amount]],0) -> 0.14297005 | AH84: =TRIM(Table2[[#This Row],[Payment Modee]]) -> Credit Card | AI84: Online | AJ84: Not Returned | AK84: 10:36 | AL84: =IF(HOUR(Table2[[#This Row],[Order Time]])<12,"Morning",IF(HOUR(Table2[[#This Row],[Order Time]])<17,"Afternoon",IF(HOUR(Table2[[#This Row],[Order Time]])<21,"Evening","Night"))) -> Morning | AM84: Weekday
A85: INV100084 | B85: 45604 | C85: =YEAR(Table2[[#This Row],[Invoice Date]]) -> 2024 | D85: =TEXT(Table2[[#This Row],[Invoice Date]],"mmm") -> Nov | E85: =Table2[[#This Row],[Store_ID]]&"-"&Table2[[#This Row],[Year]]&"-"&Table2[[#This Row],[Month]] -> STR071-2024-Nov | F85: CUST0345 | G85: =_xlfn.XLOOKUP(Table2[[#This Row],[Customer_ID]],Table3[Customer_ID],Table3[Customer Name],"Not Found") -> Sunita Subramaniam | H85: =_xlfn.XLOOKUP(Table2[[#This Row],[Customer_ID]],Table3[Customer_ID],Table3[Gender],"Female") -> Female | I85: =_xlfn.XLOOKUP(Table2[[#This Row],[Customer_ID]],Table3[Customer_ID],Table3[City],"Missing Memebership") -> Khammam | J85: =_xlfn.XLOOKUP(Table2[[#This Row],[Customer_ID]],Table3[Customer_ID],Table3[State],"Karnataka") -> Telangana | K85: =_xlfn.XLOOKUP(Table2[[#This Row],[Customer_ID]],Table3[Customer_ID],Table3[Membership],"Regular") -> Regular | L85: PRD0220 | M85: =_xlfn.XLOOKUP(Table2[[#This Row],[Product_ID]],Table4[Product_ID],Table4[Product_Name],"Not Found") -> Joyalukkas Sandals Beige | N85: =_xlfn.XLOOKUP(Table2[[#This Row],[Product_ID]],Table4[Product_ID],Table4[Category],"Not Found") -> Footwear | O85: =_xlfn.XLOOKUP(Table2[[#This Row],[Product_ID]],Table4[Product_ID],Table4[Subcategory],"Not Found") -> Sandals | P85: =_xlfn.XLOOKUP(Table2[[#This Row],[Product_ID]],Table4[Product_ID],Table4[Brand],"Missing Brand") -> Joyalukkas | Q85: STR071 | R85: =_xlfn.XLOOKUP(Table2[[#This Row],[Store_ID]],Table6[Store_ID],Table6[Store Name],"Not Found") -> TrendMart Kannur Standard | S85: =_xlfn.XLOOKUP(Table2[[#This Row],[Store_ID]],Table6[Store_ID],Table6[Monthly Target],"Missing Target") -> 2000000 | T85: =_xlfn.XLOOKUP(Table2[[#This Row],[Store_ID]],Table6[Store_ID],Table6[Region],"Not Found") -> South Zone 1 | U85: EMP0240 | V85: =_xlfn.XLOOKUP(Table2[[#This Row],[Employee_ID]],Table5[Employee_ID],Table5[Employee Name],"Not Found") -> Gopal Prasad | W85: 2 | X85: 1187.06 | Y85: 20 | Z85: 474.82 | AA85: 12 | AB85: 227.92 | AC85: 2127.22 | AD85: 1709.7 | AE85: =(AC85-AD85-AB85) -> 189.6 | AF85: UPI | AG85: =IFERROR(Table2[[#This Row],[Profit]]/Table2[[#This Row],[Sales Amount]],0) -> 0.089130414 | AH85: =TRIM(Table2[[#This Row],[Payment Modee]]) -> UPI | AI85: Online | AJ85: Not Returned | AK85: 14:17 | AL85: =IF(HOUR(Table2[[#This Row],[Order Time]])<12,"Morning",IF(HOUR(Table2[[#This Row],[Order Time]])<17,"Afternoon",IF(HOUR(Table2[[#This Row],[Order Time]])<21,"Evening","Night"))) -> Afternoon | AM85: Weekday
... A143: INV100142 | B143: 45615 | C143: =YEAR(Table2[[#This Row],[Invoice Date]]) -> 2024 | D143: =TEXT(Table2[[#This Row],[Invoice Date]],"mmm") -> Nov | E143: =Table2[[#This Row],[Store_ID]]&"-"&Table2[[#This Row],[Year]]&"-"&Table2[[#This Row],[Month]] -> STR026-2024-Nov | F143: CUST0103 | G143: =_xlfn.XLOOKUP(Table2[[#This Row],[Customer_ID]],Table3[Customer_ID],Table3[Customer Name],"Not Found") -> Yogesh Venkatesan | H143: =_xlfn.XLOOKUP(Table2[[#This Row],[Customer_ID]],Table3[Customer_ID],Table3[Gender],"Female") -> Male | I143: =_xlfn.XLOOKUP(Table2[[#This Row],[Customer_ID]],Table3[Customer_ID],Table3[City],"Missing Memebership") -> Madurai | J143: =_xlfn.XLOOKUP(Table2[[#This Row],[Customer_ID]],Table3[Customer_ID],Table3[State],"Karnataka") -> Tamil Nadu | K143: =_xlfn.XLOOKUP(Table2[[#This Row],[Customer_ID]],Table3[Customer_ID],Table3[Membership],"Regular") -> Regular | L143: PRD0192 | M143: =_xlfn.XLOOKUP(Table2[[#This Row],[Product_ID]],Table4[Product_ID],Table4[Product_Name],"Not Found") -> Skechers Round Neck Red | N143: =_xlfn.XLOOKUP(Table2[[#This Row],[Product_ID]],Table4[Product_ID],Table4[Category],"Not Found") -> Men T-Shirts | O143: =_xlfn.XLOOKUP(Table2[[#This Row],[Product_ID]],Table4[Product_ID],Table4[Subcategory],"Not Found") -> Round Neck | P143: =_xlfn.XLOOKUP(Table2[[#This Row],[Product_ID]],Table4[Product_ID],Table4[Brand],"Missing Brand") -> Skechers | Q143: STR026 | R143: =_xlfn.XLOOKUP(Table2[[#This Row],[Store_ID]],Table6[Store_ID],Table6[Store Name],"Not Found") -> TrendMart Guntur Standard | S143: =_xlfn.XLOOKUP(Table2[[#This Row],[Store_ID]],Table6[Store_ID],Table6[Monthly Target],"Missing Target") -> 2500000 | T143: =_xlfn.XLOOKUP(Table2[[#This Row],[Store_ID]],Table6[Store_ID],Table6[Region],"Not Found") -> South Zone 3 | U143: EMP0009 | V143: =_xlfn.XLOOKUP(Table2[[#This Row],[Employee_ID]],Table5[Employee_ID],Table5[Employee Name],"Not Found") -> Vinod Hegde | W143: 4 | X143: 394.94 | Y143: 0 | Z143: 0 | AA143: 5 | AB143: 78.99 | AC143: 1658.75 | AD143: 1048.24 | AE143: =(AC143-AD143-AB143) -> 531.52 | AF143: UPI | AG143: =IFERROR(Table2[[#This Row],[Profit]]/Table2[[#This Row],[Sales Amount]],0) -> 0.32043406 | AH143: =TRIM(Table2[[#This Row],[Payment Modee]]) -> UPI | AI143: Offline | AJ143: Not Returned | AK143: 17:07 | AL143: =IF(HOUR(Table2[[#This Row],[Order Time]])<12,"Morning",IF(HOUR(Table2[[#This Row],[Order Time]])<17,"Afternoon",IF(HOUR(Table2[[#This Row],[Order Time]])<21,"Evening","Night"))) -> Evening | AM143: Weekday
A144: INV100143 | B144: 45435 | C144: =YEAR(Table2[[#This Row],[Invoice Date]]) -> 2024 | D144: =TEXT(Table2[[#This Row],[Invoice Date]],"mmm") -> May | E144: =Table2[[#This Row],[Store_ID]]&"-"&Table2[[#This Row],[Year]]&"-"&Table2[[#This Row],[Month]] -> STR002-2024-May | F144: CUST0837 | G144: =_xlfn.XLOOKUP(Table2[[#This Row],[Customer_ID]],Table3[Customer_ID],Table3[Customer Name],"Not Found") -> Deepthi Shetty | H144: =_xlfn.XLOOKUP(Table2[[#This Row],[Customer_ID]],Table3[Customer_ID],Table3[Gender],"Female") -> Female | I144: =_xlfn.XLOOKUP(Table2[[#This Row],[Customer_ID]],Table3[Customer_ID],Table3[City],"Missing Memebership") -> Karimnagar | J144: =_xlfn.XLOOKUP(Table2[[#This Row],[Customer_ID]],Table3[Customer_ID],Table3[State],"Karnataka") -> Telangana | K144: =_xlfn.XLOOKUP(Table2[[#This Row],[Customer_ID]],Table3[Customer_ID],Table3[Membership],"Regular") -> Regular | L144: PRD0241 | M144: =_xlfn.XLOOKUP(Table2[[#This Row],[Product_ID]],Table4[Product_ID],Table4[Product_Name],"Not Found") -> Allen Solly Sports T-Shirt Cream | N144: =_xlfn.XLOOKUP(Table2[[#This Row],[Product_ID]],Table4[Product_ID],Table4[Category],"Not Found") -> Sportswear | O144: =_xlfn.XLOOKUP(Table2[[#This Row],[Product_ID]],Table4[Product_ID],Table4[Subcategory],"Not Found") -> Sports T-Shirt | P144: =_xlfn.XLOOKUP(Table2[[#This Row],[Product_ID]],Table4[Product_ID],Table4[Brand],"Missing Brand") -> Allen Solly | Q144: STR002 | R144: =_xlfn.XLOOKUP(Table2[[#This Row],[Store_ID]],Table6[Store_ID],Table6[Store Name],"Not Found") -> TrendMart Thrissur Standard | S144: =_xlfn.XLOOKUP(Table2[[#This Row],[Store_ID]],Table6[Store_ID],Table6[Monthly Target],"Missing Target") -> 1000000 | T144: =_xlfn.XLOOKUP(Table2[[#This Row],[Store_ID]],Table6[Store_ID],Table6[Region],"Not Found") -> South Zone 1 | U144: EMP0205 | V144: =_xlfn.XLOOKUP(Table2[[#This Row],[Employee_ID]],Table5[Employee_ID],Table5[Employee Name],"Not Found") -> Malini Gowda | W144: 0 | X144: 1601.15 | Y144: 30 | Z144: 0 | AA144: 12 | AB144: 0 | AC144: 0 | AD144: 0 | AE144: 0 | AF144: UPI | AG144: =IFERROR(Table2[[#This Row],[Profit]]/Table2[[#This Row],[Sales Amount]],0) -> 0 | AH144: =TRIM(Table2[[#This Row],[Payment Modee]]) -> UPI | AI144: Offline | AJ144: Not Returned | AK144: 14:05 | AL144: =IF(HOUR(Table2[[#This Row],[Order Time]])<12,"Morning",IF(HOUR(Table2[[#This Row],[Order Time]])<17,"Afternoon",IF(HOUR(Table2[[#This Row],[Order Time]])<21,"Evening","Night"))) -> Afternoon | AM144: Weekday
A145: INV100144 | B145: 45672 | C145: =YEAR(Table2[[#This Row],[Invoice Date]]) -> 2025 | D145: =TEXT(Table2[[#This Row],[Invoice Date]],"mmm") -> Jan | E145: =Table2[[#This Row],[Store_ID]]&"-"&Table2[[#This Row],[Year]]&"-"&Table2[[#This Row],[Month]] -> STR113-2025-Jan | F145: CUST0497 | G145: =_xlfn.XLOOKUP(Table2[[#This Row],[Customer_ID]],Table3[Customer_ID],Table3[Customer Name],"Not Found") -> Naveen Subramaniam | H145: =_xlfn.XLOOKUP(Table2[[#This Row],[Customer_ID]],Table3[Customer_ID],Table3[Gender],"Female") -> Male | I145: =_xlfn.XLOOKUP(Table2[[#This Row],[Customer_ID]],Table3[Customer_ID],Table3[City],"Missing Memebership") -> Nellore | J145: =_xlfn.XLOOKUP(Table2[[#This Row],[Customer_ID]],Table3[Customer_ID],Table3[State],"Karnataka") -> Andhra Pradesh | K145: =_xlfn.XLOOKUP(Table2[[#This Row],[Customer_ID]],Table3[Customer_ID],Table3[Membership],"Regular") -> Regular | L145: PRD0033 | M145: =_xlfn.XLOOKUP(Table2[[#This Row],[Product_ID]],Table4[Product_ID],Table4[Product_Name],"Not Found") -> Bata Cotton Saree Mustard | N145: =_xlfn.XLOOKUP(Table2[[#This Row],[Product_ID]],Table4[Product_ID],Table4[Category],"Not Found") -> Women Sarees | O145: =_xlfn.XLOOKUP(Table2[[#This Row],[Product_ID]],Table4[Product_ID],Table4[Subcategory],"Not Found") -> Cotton Saree | P145: =_xlfn.XLOOKUP(Table2[[#This Row],[Product_ID]],Table4[Product_ID],Table4[Brand],"Missing Brand") -> Bata | Q145: STR113 | R145: =_xlfn.XLOOKUP(Table2[[#This Row],[Store_ID]],Table6[Store_ID],Table6[Store Name],"Not Found") -> TrendMart Mangaluru High Street | S145: =_xlfn.XLOOKUP(Table2[[#This Row],[Store_ID]],Table6[Store_ID],Table6[Monthly Target],"Missing Target") -> 2000000 | T145: =_xlfn.XLOOKUP(Table2[[#This Row],[Store_ID]],Table6[Store_ID],Table6[Region],"Not Found") -> South Zone 2 | U145: EMP0260 | V145: =_xlfn.XLOOKUP(Table2[[#This Row],[Employee_ID]],Table5[Employee_ID],Table5[Employee Name],"Not Found") -> Malathi Varma | W145: 1 | X145: 3398.79 | Y145: 30 | Z145: 1019.64 | AA145: 12 | AB145: 285.5 | AC145: 2664.65 | AD145: 2710.05 | AE145: =(AC145-AD145-AB145) -> -330.9 | AF145: Debit Card | AG145: =IFERROR(Table2[[#This Row],[Profit]]/Table2[[#This Row],[Sales Amount]],0) -> -0.12418141 | AH145: =TRIM(Table2[[#This Row],[Payment Modee]]) -> Debit Card | AI145: Offline | AJ145: Not Returned | AK145: 16:12 | AL145: =IF(HOUR(Table2[[#This Row],[Order Time]])<12,"Morning",IF(HOUR(Table2[[#This Row],[Order Time]])<17,"Afternoon",IF(HOUR(Table2[[#This Row],[Order Time]])<21,"Evening","Night"))) -> Afternoon | AM145: Weekday
A146: INV100145 | B146: 45499 | C146: =YEAR(Table2[[#This Row],[Invoice Date]]) -> 2024 | D146: =TEXT(Table2[[#This Row],[Invoice Date]],"mmm") -> Jul | E146: =Table2[[#This Row],[Store_ID]]&"-"&Table2[[#This Row],[Year]]&"-"&Table2[[#This Row],[Month]] -> STR074-2024-Jul | F146: CUST0309 | G146: =_xlfn.XLOOKUP(Table2[[#This Row],[Customer_ID]],Table3[Customer_ID],Table3[Customer Name],"Not Found") -> Srinivas Gopalakrishnan | H146: =_xlfn.XLOOKUP(Table2[[#This Row],[Customer_ID]],Table3[Customer_ID],Table3[Gender],"Female") -> Male | I146: =_xlfn.XLOOKUP(Table2[[#This Row],[Customer_ID]],Table3[Customer_ID],Table3[City],"Missing Memebership") -> Karimnagar | J146: =_xlfn.XLOOKUP(Table2[[#This Row],[Customer_ID]],Table3[Customer_ID],Table3[State],"Karnataka") -> Telangana | K146: =_xlfn.XLOOKUP(Table2[[#This Row],[Customer_ID]],Table3[Customer_ID],Table3[Membership],"Regular") -> Silver | L146: PRD0126 | M146: =_xlfn.XLOOKUP(Table2[[#This Row],[Product_ID]],Table4[Product_ID],Table4[Product_Name],"Not Found") -> Van Heusen Formal Shirt Olive | N146: =_xlfn.XLOOKUP(Table2[[#This Row],[Product_ID]],Table4[Product_ID],Table4[Category],"Not Found") -> Men Shirts | O146: =_xlfn.XLOOKUP(Table2[[#This Row],[Product_ID]],Table4[Product_ID],Table4[Subcategory],"Not Found") -> Formal Shirt | P146: =_xlfn.XLOOKUP(Table2[[#This Row],[Product_ID]],Table4[Product_ID],Table4[Brand],"Missing Brand") -> Van Heusen | Q146: STR074 | R146: =_xlfn.XLOOKUP(Table2[[#This Row],[Store_ID]],Table6[Store_ID],Table6[Store Name],"Not Found") -> TrendMart Kurnool High Street | S146: =_xlfn.XLOOKUP(Table2[[#This Row],[Store_ID]],Table6[Store_ID],Table6[Monthly Target],"Missing Target") -> 1200000 | T146: =_xlfn.XLOOKUP(Table2[[#This Row],[Store_ID]],Table6[Store_ID],Table6[Region],"Not Found") -> South Zone 3 | U146: EMP0170 | V146: =_xlfn.XLOOKUP(Table2[[#This Row],[Employee_ID]],Table5[Employee_ID],Table5[Employee Name],"Not Found") -> Jyothi Prasad | W146: 2 | X146: 947.98 | Y146: 10 | Z146: 189.6 | AA146: 5 | AB146: 85.32 | AC146: 1791.68 | AD146: 1291.18 | AE146: =(AC146-AD146-AB146) -> 415.18 | AF146: UPI | AG146: =IFERROR(Table2[[#This Row],[Profit]]/Table2[[#This Row],[Sales Amount]],0) -> 0.23172665 | AH146: =TRIM(Table2[[#This Row],[Payment Modee]]) -> UPI | AI146: Online | AJ146: Not Returned | AK146: 11:22 | AL146: =IF(HOUR(Table2[[#This Row],[Order Time]])<12,"Morning",IF(HOUR(Table2[[#This Row],[Order Time]])<17,"Afternoon",IF(HOUR(Table2[[#This Row],[Order Time]])<21,"Evening","Night"))) -> Morning | AM146: Weekday
A147: INV100146 | B147: 45405 | C147: =YEAR(Table2[[#This Row],[Invoice Date]]) -> 2024 | D147: =TEXT(Table2[[#This Row],[Invoice Date]],"mmm") -> Apr | E147: =Table2[[#This Row],[Store_ID]]&"-"&Table2[[#This Row],[Year]]&"-"&Table2[[#This Row],[Month]] -> STR007-2024-Apr | F147: CUST0340 | G147: =_xlfn.XLOOKUP(Table2[[#This Row],[Customer_ID]],Table3[Customer_ID],Table3[Customer Name],"Not Found") -> Gopal Prasad | H147: =_xlfn.XLOOKUP(Table2[[#This Row],[Customer_ID]],Table3[Customer_ID],Table3[Gender],"Female") -> Male | I147: =_xlfn.XLOOKUP(Table2[[#This Row],[Customer_ID]],Table3[Customer_ID],Table3[City],"Missing Memebership") -> Mysuru | J147: =_xlfn.XLOOKUP(Table2[[#This Row],[Customer_ID]],Table3[Customer_ID],Table3[State],"Karnataka") -> Karnataka | K147: =_xlfn.XLOOKUP(Table2[[#This Row],[Customer_ID]],Table3[Customer_ID],Table3[Membership],"Regular") -> Regular | L147: PRD0096 | M147: =_xlfn.XLOOKUP(Table2[[#This Row],[Product_ID]],Table4[Product_ID],Table4[Product_Name],"Not Found") -> Mufti Chronograph Grey | N147: =_xlfn.XLOOKUP(Table2[[#This Row],[Product_ID]],Table4[Product_ID],Table4[Category],"Not Found") -> Watches | O147: =_xlfn.XLOOKUP(Table2[[#This Row],[Product_ID]],Table4[Product_ID],Table4[Subcategory],"Not Found") -> Chronograph | P147: =_xlfn.XLOOKUP(Table2[[#This Row],[Product_ID]],Table4[Product_ID],Table4[Brand],"Missing Brand") -> Mufti | Q147: STR007 | R147: =_xlfn.XLOOKUP(Table2[[#This Row],[Store_ID]],Table6[Store_ID],Table6[Store Name],"Not Found") -> TrendMart Thoothukudi Mall Kiosk | S147: =_xlfn.XLOOKUP(Table2[[#This Row],[Store_ID]],Table6[Store_ID],Table6[Monthly Target],"Missing Target") -> 1500000 | T147: =_xlfn.XLOOKUP(Table2[[#This Row],[Store_ID]],Table6[Store_ID],Table6[Region],"Not Found") -> South Zone 1 | U147: EMP0203 | V147: =_xlfn.XLOOKUP(Table2[[#This Row],[Employee_ID]],Table5[Employee_ID],Table5[Employee Name],"Not Found") -> Rani Mishra | W147: 1 | X147: 4323.94 | Y147: 0 | Z147: 0 | AA147: 12 | AB147: 518.87 | AC147: 4842.81 | AD147: 2833.61 | AE147: =(AC147-AD147-AB147) -> 1490.33 | AF147: UPI | AG147: =IFERROR(Table2[[#This Row],[Profit]]/Table2[[#This Row],[Sales Amount]],0) -> 0.30774075 | AH147: =TRIM(Table2[[#This Row],[Payment Modee]]) -> UPI | AI147: Offline | AJ147: Not Returned | AK147: 15:21 | AL147: =IF(HOUR(Table2[[#This Row],[Order Time]])<12,"Morning",IF(HOUR(Table2[[#This Row],[Order Time]])<17,"Afternoon",IF(HOUR(Table2[[#This Row],[Order Time]])<21,"Evening","Night"))) -> Afternoon | AM147: Weekday
A148: INV100147 | B148: 45529 | C148: =YEAR(Table2[[#This Row],[Invoice Date]]) -> 2024 | D148: =TEXT(Table2[[#This Row],[Invoice Date]],"mmm") -> Aug | E148: =Table2[[#This Row],[Store_ID]]&"-"&Table2[[#This Row],[Year]]&"-"&Table2[[#This Row],[Month]] -> STR018-2024-Aug | F148: CUST0003 | G148: =_xlfn.XLOOKUP(Table2[[#This Row],[Customer_ID]],Table3[Customer_ID],Table3[Customer Name],"Not Found") -> Swathi Bhat | H148: =_xlfn.XLOOKUP(Table2[[#This Row],[Customer_ID]],Table3[Customer_ID],Table3[Gender],"Female") -> Female | I148: =_xlfn.XLOOKUP(Table2[[#This Row],[Customer_ID]],Table3[Customer_ID],Table3[City],"Missing Memebership") -> Vellore | J148: =_xlfn.XLOOKUP(Table2[[#This Row],[Customer_ID]],Table3[Customer_ID],Table3[State],"Karnataka") -> Tamil Nadu | K148: =_xlfn.XLOOKUP(Table2[[#This Row],[Customer_ID]],Table3[Customer_ID],Table3[Membership],"Regular") -> Regular | L148: PRD0002 | M148: =_xlfn.XLOOKUP(Table2[[#This Row],[Product_ID]],Table4[Product_ID],Table4[Product_Name],"Not Found") -> Fastrack Jacket Orange | N148: =_xlfn.XLOOKUP(Table2[[#This Row],[Product_ID]],Table4[Product_ID],Table4[Category],"Not Found") -> Winter Wear | O148: =_xlfn.XLOOKUP(Table2[[#This Row],[Product_ID]],Table4[Product_ID],Table4[Subcategory],"Not Found") -> Jacket | P148: =_xlfn.XLOOKUP(Table2[[#This Row],[Product_ID]],Table4[Product_ID],Table4[Brand],"Missing Brand") -> Fastrack | Q148: STR018 | R148: =_xlfn.XLOOKUP(Table2[[#This Row],[Store_ID]],Table6[Store_ID],Table6[Store Name],"Not Found") -> TrendMart Visakhapatnam High Street | S148: =_xlfn.XLOOKUP(Table2[[#This Row],[Store_ID]],Table6[Store_ID],Table6[Monthly Target],"Missing Target") -> 2000000 | T148: =_xlfn.XLOOKUP(Table2[[#This Row],[Store_ID]],Table6[Store_ID],Table6[Region],"Not Found") -> South Zone 3 | U148: EMP0207 | V148: =_xlfn.XLOOKUP(Table2[[#This Row],[Employee_ID]],Table5[Employee_ID],Table5[Employee Name],"Not Found") -> Chitra Bhat | W148: 1 | X148: 1289.85 | Y148: 30 | Z148: 386.95 | AA148: 12 | AB148: 108.35 | AC148: 1011.25 | AD148: 755.06 | AE148: =(AC148-AD148-AB148) -> 147.84 | AF148: Net Banking | AG148: =IFERROR(Table2[[#This Row],[Profit]]/Table2[[#This Row],[Sales Amount]],0) -> 0.1461953 | AH148: =TRIM(Table2[[#This Row],[Payment Modee]]) -> Net Banking | AI148: Offline | AJ148: Not Returned | AK148: 18:33 | AL148: =IF(HOUR(Table2[[#This Row],[Order Time]])<12,"Morning",IF(HOUR(Table2[[#This Row],[Order Time]])<17,"Afternoon",IF(HOUR(Table2[[#This Row],[Order Time]])<21,"Evening","Night"))) -> Evening | AM148: Weekend
A149: INV100148 | B149: 45517 | C149: =YEAR(Table2[[#This Row],[Invoice Date]]) -> 2024 | D149: =TEXT(Table2[[#This Row],[Invoice Date]],"mmm") -> Aug | E149: =Table2[[#This Row],[Store_ID]]&"-"&Table2[[#This Row],[Year]]&"-"&Table2[[#This Row],[Month]] -> STR004-2024-Aug | F149: CUST0060 | G149: =_xlfn.XLOOKUP(Table2[[#This Row],[Customer_ID]],Table3[Customer_ID],Table3[Customer Name],"Not Found") -> Karunakaran Yadav | H149: =_xlfn.XLOOKUP(Table2[[#This Row],[Customer_ID]],Table3[Customer_ID],Table3[Gender],"Female") -> Male | I149: =_xlfn.XLOOKUP(Table2[[#This Row],[Customer_ID]],Table3[Customer_ID],Table3[City],"Missing Memebership") -> Kochi | J149: =_xlfn.XLOOKUP(Table2[[#This Row],[Customer_ID]],Table3[Customer_ID],Table3[State],"Karnataka") -> Kerala | K149: =_xlfn.XLOOKUP(Table2[[#This Row],[Customer_ID]],Table3[Customer_ID],Table3[Membership],"Regular") -> Regular | L149: PRD0137 | M149: =_xlfn.XLOOKUP(Table2[[#This Row],[Product_ID]],Table4[Product_ID],Table4[Product_Name],"Not Found") -> Peter England Crop Top Green | N149: =_xlfn.XLOOKUP(Table2[[#This Row],[Product_ID]],Table4[Product_ID],Table4[Category],"Not Found") -> Women Tops | O149: =_xlfn.XLOOKUP(Table2[[#This Row],[Product_ID]],Table4[Product_ID],Table4[Subcategory],"Not Found") -> Crop Top | P149: =_xlfn.XLOOKUP(Table2[[#This Row],[Product_ID]],Table4[Product_ID],Table4[Brand],"Missing Brand") -> Peter England | Q149: STR004 | R149: =_xlfn.XLOOKUP(Table2[[#This Row],[Store_ID]],Table6[Store_ID],Table6[Store Name],"Not Found") -> TrendMart Kalaburagi Mall Kiosk | S149: =_xlfn.XLOOKUP(Table2[[#This Row],[Store_ID]],Table6[Store_ID],Table6[Monthly Target],"Missing Target") -> 800000 | T149: =_xlfn.XLOOKUP(Table2[[#This Row],[Store_ID]],Table6[Store_ID],Table6[Region],"Not Found") -> South Zone 2 | U149: EMP0276 | V149: =_xlfn.XLOOKUP(Table2[[#This Row],[Employee_ID]],Table5[Employee_ID],Table5[Employee Name],"Not Found") -> Manoj Ramachandran | W149: 1 | X149: 754.03 | Y149: 25 | Z149: 188.51 | AA149: 5 | AB149: 28.28 | AC149: 593.8 | AD149: 522.38 | AE149: =(AC149-AD149-AB149) -> 43.14 | AF149: Credit Card | AG149: =IFERROR(Table2[[#This Row],[Profit]]/Table2[[#This Row],[Sales Amount]],0) -> 0.072650724 | AH149: =TRIM(Table2[[#This Row],[Payment Modee]]) -> Credit Card | AI149: Online | AJ149: Not Returned | AK149: 16:13 | AL149: =IF(HOUR(Table2[[#This Row],[Order Time]])<12,"Morning",IF(HOUR(Table2[[#This Row],[Order Time]])<17,"Afternoon",IF(HOUR(Table2[[#This Row],[Order Time]])<21,"Evening","Night"))) -> Afternoon | AM149: Weekday
A150: INV100149 | B150: 45636 | C150: =YEAR(Table2[[#This Row],[Invoice Date]]) -> 2024 | D150: =TEXT(Table2[[#This Row],[Invoice Date]],"mmm") -> Dec | E150: =Table2[[#This Row],[Store_ID]]&"-"&Table2[[#This Row],[Year]]&"-"&Table2[[#This Row],[Month]] -> STR077-2024-Dec | F150: CUST0460 | G150: =_xlfn.XLOOKUP(Table2[[#This Row],[Customer_ID]],Table3[Customer_ID],Table3[Customer Name],"Not Found") -> Ramesh Singh | H150: =_xlfn.XLOOKUP(Table2[[#This Row],[Customer_ID]],Table3[Customer_ID],Table3[Gender],"Female") -> Male | I150: =_xlfn.XLOOKUP(Table2[[#This Row],[Customer_ID]],Table3[Customer_ID],Table3[City],"Missing Memebership") -> Visakhapatnam | J150: =_xlfn.XLOOKUP(Table2[[#This Row],[Customer_ID]],Table3[Customer_ID],Table3[State],"Karnataka") -> Andhra Pradesh | K150: =_xlfn.XLOOKUP(Table2[[#This Row],[Customer_ID]],Table3[Customer_ID],Table3[Membership],"Regular") -> Silver | L150: PRD0064 | M150: =_xlfn.XLOOKUP(Table2[[#This Row],[Product_ID]],Table4[Product_ID],Table4[Product_Name],"Not Found") -> Raymond Leather Belt White | N150: =_xlfn.XLOOKUP(Table2[[#This Row],[Product_ID]],Table4[Product_ID],Table4[Category],"Not Found") -> Belts | O150: =_xlfn.XLOOKUP(Table2[[#This Row],[Product_ID]],Table4[Product_ID],Table4[Subcategory],"Not Found") -> Leather Belt | P150: =_xlfn.XLOOKUP(Table2[[#This Row],[Product_ID]],Table4[Product_ID],Table4[Brand],"Missing Brand") -> Raymond | Q150: STR077 | R150: =_xlfn.XLOOKUP(Table2[[#This Row],[Store_ID]],Table6[Store_ID],Table6[Store Name],"Not Found") -> TrendMart Hyderabad Mall Kiosk | S150: =_xlfn.XLOOKUP(Table2[[#This Row],[Store_ID]],Table6[Store_ID],Table6[Monthly Target],"Missing Target") -> 2500000 | T150: =_xlfn.XLOOKUP(Table2[[#This Row],[Store_ID]],Table6[Store_ID],Table6[Region],"Not Found") -> South Zone 2 | U150: EMP0063 | V150: =_xlfn.XLOOKUP(Table2[[#This Row],[Employee_ID]],Table5[Employee_ID],Table5[Employee Name],"Not Found") -> Anusuya Subramaniam | W150: 1 | X150: 324.55 | Y150: 15 | Z150: 48.68 | AA150: 5 | AB150: 13.79 | AC150: 289.66 | AD150: 254.15 | AE150: =(AC150-AD150-AB150) -> 21.72 | AF150: UPI | AG150: =IFERROR(Table2[[#This Row],[Profit]]/Table2[[#This Row],[Sales Amount]],0) -> 0.074984465 | AH150: =TRIM(Table2[[#This Row],[Payment Modee]]) -> UPI | AI150: Offline | AJ150: Returned | AK150: 16:55 | AL150: =IF(HOUR(Table2[[#This Row],[Order Time]])<12,"Morning",IF(HOUR(Table2[[#This Row],[Order Time]])<17,"Afternoon",IF(HOUR(Table2[[#This Row],[Order Time]])<21,"Evening","Night"))) -> Afternoon | AM150: Weekday
A151: INV100150 | B151: 45384 | C151: =YEAR(Table2[[#This Row],[Invoice Date]]) -> 2024 | D151: =TEXT(Table2[[#This Row],[Invoice Date]],"mmm") -> Apr | E151: =Table2[[#This Row],[Store_ID]]&"-"&Table2[[#This Row],[Year]]&"-"&Table2[[#This Row],[Month]] -> STR101-2024-Apr | F151: CUST0114 | G151: =_xlfn.XLOOKUP(Table2[[#This Row],[Customer_ID]],Table3[Customer_ID],Table3[Customer Name],"Not Found") -> Manikandan Gupta | H151: =_xlfn.XLOOKUP(Table2[[#This Row],[Customer_ID]],Table3[Customer_ID],Table3[Gender],"Female") -> Male | I151: =_xlfn.XLOOKUP(Table2[[#This Row],[Customer_ID]],Table3[Customer_ID],Table3[City],"Missing Memebership") -> Salem | J151: =_xlfn.XLOOKUP(Table2[[#This Row],[Customer_ID]],Table3[Customer_ID],Table3[State],"Karnataka") -> Tamil Nadu | K151: =_xlfn.XLOOKUP(Table2[[#This Row],[Customer_ID]],Table3[Customer_ID],Table3[Membership],"Regular") -> Regular | L151: PRD0123 | M151: =_xlfn.XLOOKUP(Table2[[#This Row],[Product_ID]],Table4[Product_ID],Table4[Product_Name],"Not Found") -> Wrangler Formal Belt Brown | N151: =_xlfn.XLOOKUP(Table2[[#This Row],[Product_ID]],Table4[Product_ID],Table4[Category],"Not Found") -> Belts | O151: =_xlfn.XLOOKUP(Table2[[#This Row],[Product_ID]],Table4[Product_ID],Table4[Subcategory],"Not Found") -> Formal Belt | P151: =_xlfn.XLOOKUP(Table2[[#This Row],[Product_ID]],Table4[Product_ID],Table4[Brand],"Missing Brand") -> Wrangler | Q151: STR101 | R151: =_xlfn.XLOOKUP(Table2[[#This Row],[Store_ID]],Table6[Store_ID],Table6[Store Name],"Not Found") -> TrendMart Thiruvananthapuram Standard | S151: =_xlfn.XLOOKUP(Table2[[#This Row],[Store_ID]],Table6[Store_ID],Table6[Monthly Target],"Missing Target") -> 1200000 | T151: =_xlfn.XLOOKUP(Table2[[#This Row],[Store_ID]],Table6[Store_ID],Table6[Region],"Not Found") -> South Zone 1 | U151: EMP0206 | V151: =_xlfn.XLOOKUP(Table2[[#This Row],[Employee_ID]],Table5[Employee_ID],Table5[Employee Name],"Not Found") -> Arjun Krishnan | W151: 2 | X151: 1150.4 | Y151: 20 | Z151: 460.16 | AA151: 12 | AB151: 220.88 | AC151: 2061.52 | AD151: 1474.7 | AE151: =(AC151-AD151-AB151) -> 365.94 | AF151: Credit Card | AG151: =IFERROR(Table2[[#This Row],[Profit]]/Table2[[#This Row],[Sales Amount]],0) -> 0.1775098 | AH151: =TRIM(Table2[[#This Row],[Payment Modee]]) -> Credit Card | AI151: Offline | AJ151: Not Returned | AK151: 21:32 | AL151: =IF(HOUR(Table2[[#This Row],[Order Time]])<12,"Morning",IF(HOUR(Table2[[#This Row],[Order Time]])<17,"Afternoon",IF(HOUR(Table2[[#This Row],[Order Time]])<21,"Evening","Night"))) -> Night | AM151: Weekday
A152: INV100151 | B152: 45655 | C152: =YEAR(Table2[[#This Row],[Invoice Date]]) -> 2024 | D152: =TEXT(Table2[[#This Row],[Invoice Date]],"mmm") -> Dec | E152: =Table2[[#This Row],[Store_ID]]&"-"&Table2[[#This Row],[Year]]&"-"&Table2[[#This Row],[Month]] -> STR118-2024-Dec | F152: CUST0654 | G152: =_xlfn.XLOOKUP(Table2[[#This Row],[Customer_ID]],Table3[Customer_ID],Table3[Customer Name],"Not Found") -> Lakshmi Nair | H152: =_xlfn.XLOOKUP(Table2[[#This Row],[Customer_ID]],Table3[Customer_ID],Table3[Gender],"Female") -> Female | I152: =_xlfn.XLOOKUP(Table2[[#This Row],[Customer_ID]],Table3[Customer_ID],Table3[City],"Missing Memebership") -> Shivamogga | J152: =_xlfn.XLOOKUP(Table2[[#This Row],[Customer_ID]],Table3[Customer_ID],Table3[State],"Karnataka") -> Karnataka | K152: =_xlfn.XLOOKUP(Table2[[#This Row],[Customer_ID]],Table3[Customer_ID],Table3[Membership],"Regular") -> Regular | L152: PRD0043 | M152: =_xlfn.XLOOKUP(Table2[[#This Row],[Product_ID]],Table4[Product_ID],Table4[Product_Name],"Not Found") -> GRT Jewellers Sling Bag Olive | N152: =_xlfn.XLOOKUP(Table2[[#This Row],[Product_ID]],Table4[Product_ID],Table4[Category],"Not Found") -> Handbags | O152: =_xlfn.XLOOKUP(Table2[[#This Row],[Product_ID]],Table4[Product_ID],Table4[Subcategory],"Not Found") -> Sling Bag | P152: =_xlfn.XLOOKUP(Table2[[#This Row],[Product_ID]],Table4[Product_ID],Table4[Brand],"Missing Brand") -> GRT Jewellers | Q152: STR118 | R152: =_xlfn.XLOOKUP(Table2[[#This Row],[Store_ID]],Table6[Store_ID],Table6[Store Name],"Not Found") -> TrendMart Nellore Mall Kiosk | S152: =_xlfn.XLOOKUP(Table2[[#This Row],[Store_ID]],Table6[Store_ID],Table6[Monthly Target],"Missing Target") -> 1000000 | T152: =_xlfn.XLOOKUP(Table2[[#This Row],[Store_ID]],Table6[Store_ID],Table6[Region],"Not Found") -> South Zone 3 | U152: EMP0225 | V152: =_xlfn.XLOOKUP(Table2[[#This Row],[Employee_ID]],Table5[Employee_ID],Table5[Employee Name],"Not Found") -> Swathi Achari | W152: 2 | X152: 3566.32 | Y152: 0 | Z152: 0 | AA152: 12 | AB152: 855.92 | AC152: 7988.56 | AD152: 4068.02 | AE152: =(AC152-AD152-AB152) -> 3064.62 | AF152: Credit Card | AG152: =IFERROR(Table2[[#This Row],[Profit]]/Table2[[#This Row],[Sales Amount]],0) -> 0.38362609 | AH152: =TRIM(Table2[[#This Row],[Payment Modee]]) -> Credit Card | AI152: Offline | AJ152: Returned | AK152: 10:30 | AL152: =IF(HOUR(Table2[[#This Row],[Order Time]])<12,"Morning",IF(HOUR(Table2[[#This Row],[Order Time]])<17,"Afternoon",IF(HOUR(Table2[[#This Row],[Order Time]])<21,"Evening","Night"))) -> Morning | AM152: Weekend
A153: INV100152 | B153: 45467 | C153: =YEAR(Table2[[#This Row],[Invoice Date]]) -> 2024 | D153: =TEXT(Table2[[#This Row],[Invoice Date]],"mmm") -> Jun | E153: =Table2[[#This Row],[Store_ID]]&"-"&Table2[[#This Row],[Year]]&"-"&Table2[[#This Row],[Month]] -> STR020-2024-Jun | F153: CUST0676 | G153: =_xlfn.XLOOKUP(Table2[[#This Row],[Customer_ID]],Table3[Customer_ID],Table3[Customer Name],"Not Found") -> Dinesh Chandran | H153: =_xlfn.XLOOKUP(Table2[[#This Row],[Customer_ID]],Table3[Customer_ID],Table3[Gender],"Female") -> Male | I153: =_xlfn.XLOOKUP(Table2[[#This Row],[Customer_ID]],Table3[Customer_ID],Table3[City],"Missing Memebership") -> Nizamabad | J153: =_xlfn.XLOOKUP(Table2[[#This Row],[Customer_ID]],Table3[Customer_ID],Table3[State],"Karnataka") -> Telangana | K153: =_xlfn.XLOOKUP(Table2[[#This Row],[Customer_ID]],Table3[Customer_ID],Table3[Membership],"Regular") -> Platinum | L153: PRD0235 | M153: =_xlfn.XLOOKUP(Table2[[#This Row],[Product_ID]],Table4[Product_ID],Table4[Product_Name],"Not Found") -> Reebok Georgette Saree Charcoal | N153: =_xlfn.XLOOKUP(Table2[[#This Row],[Product_ID]],Table4[Product_ID],Table4[Category],"Not Found") -> Women Sarees | O153: =_xlfn.XLOOKUP(Table2[[#This Row],[Product_ID]],Table4[Product_ID],Table4[Subcategory],"Not Found") -> Georgette Saree | P153: =_xlfn.XLOOKUP(Table2[[#This Row],[Product_ID]],Table4[Product_ID],Table4[Brand],"Missing Brand") -> Reebok | Q153: STR020 | R153: =_xlfn.XLOOKUP(Table2[[#This Row],[Store_ID]],Table6[Store_ID],Table6[Store Name],"Not Found") -> TrendMart Guntur Standard | S153: =_xlfn.XLOOKUP(Table2[[#This Row],[Store_ID]],Table6[Store_ID],Table6[Monthly Target],"Missing Target") -> 2000000 | T153: =_xlfn.XLOOKUP(Table2[[#This Row],[Store_ID]],Table6[Store_ID],Table6[Region],"Not Found") -> South Zone 3 | U153: EMP0240 | V153: =_xlfn.XLOOKUP(Table2[[#This Row],[Employee_ID]],Table5[Employee_ID],Table5[Employee Name],"Not Found") -> Gopal Prasad | W153: 1 | X153: 1908.46 | Y153: 5 | Z153: 95.42 | AA153: 12 | AB153: 217.56 | AC153: 2030.6 | AD153: 1378.38 | AE153: =(AC153-AD153-AB153) -> 434.66 | AF153: Cash | AG153: =IFERROR(Table2[[#This Row],[Profit]]/Table2[[#This Row],[Sales Amount]],0) -> 0.21405496 | AH153: =TRIM(Table2[[#This Row],[Payment Modee]]) -> Cash | AI153: Online | AJ153: Not Returned | AK153: 17:20 | AL153: =IF(HOUR(Table2[[#This Row],[Order Time]])<12,"Morning",IF(HOUR(Table2[[#This Row],[Order Time]])<17,"Afternoon",IF(HOUR(Table2[[#This Row],[Order Time]])<21,"Evening","Night"))) -> Evening | AM153: Weekday
A154: INV100153 | B154: 45577 | C154: =YEAR(Table2[[#This Row],[Invoice Date]]) -> 2024 | D154: =TEXT(Table2[[#This Row],[Invoice Date]],"mmm") -> Oct | E154: =Table2[[#This Row],[Store_ID]]&"-"&Table2[[#This Row],[Year]]&"-"&Table2[[#This Row],[Month]] -> STR001-2024-Oct | F154: CUST0033 | G154: =_xlfn.XLOOKUP(Table2[[#This Row],[Customer_ID]],Table3[Customer_ID],Table3[Customer Name],"Not Found") -> Vidya Varma | H154: =_xlfn.XLOOKUP(Table2[[#This Row],[Customer_ID]],Table3[Customer_ID],Table3[Gender],"Female") -> Female | I154: =_xlfn.XLOOKUP(Table2[[#This Row],[Customer_ID]],Table3[Customer_ID],Table3[City],"Missing Memebership") -> Hyderabad | J154: =_xlfn.XLOOKUP(Table2[[#This Row],[Customer_ID]],Table3[Customer_ID],Table3[State],"Karnataka") -> Telangana | K154: =_xlfn.XLOOKUP(Table2[[#This Row],[Customer_ID]],Table3[Customer_ID],Table3[Membership],"Regular") -> Regular | L154: PRD0062 | M154: =_xlfn.XLOOKUP(Table2[[#This Row],[Product_ID]],Table4[Product_ID],Table4[Product_Name],"Not Found") -> Being Human Girls Frock Teal | N154: =_xlfn.XLOOKUP(Table2[[#This Row],[Product_ID]],Table4[Product_ID],Table4[Category],"Not Found") -> Kids Wear | O154: =_xlfn.XLOOKUP(Table2[[#This Row],[Product_ID]],Table4[Product_ID],Table4[Subcategory],"Not Found") -> Girls Frock | P154: =_xlfn.XLOOKUP(Table2[[#This Row],[Product_ID]],Table4[Product_ID],Table4[Brand],"Missing Brand") -> Being Human | Q154: STR001 | R154: =_xlfn.XLOOKUP(Table2[[#This Row],[Store_ID]],Table6[Store_ID],Table6[Store Name],"Not Found") -> TrendMart Kollam Standard | S154: =_xlfn.XLOOKUP(Table2[[#This Row],[Store_ID]],Table6[Store_ID],Table6[Monthly Target],"Missing Target") -> 2500000 | T154: =_xlfn.XLOOKUP(Table2[[#This Row],[Store_ID]],Table6[Store_ID],Table6[Region],"Not Found") -> South Zone 1 | U154: EMP0240 | V154: =_xlfn.XLOOKUP(Table2[[#This Row],[Employee_ID]],Table5[Employee_ID],Table5[Employee Name],"Not Found") -> Gopal Prasad | W154: 2 | X154: 610.55 | Y154: 15 | Z154: 183.16 | AA154: 5 | AB154: 51.9 | AC154: 1089.84 | AD154: 849.52 | AE154: =(AC154-AD154-AB154) -> 188.42 | AF154: UPI | AG154: =IFERROR(Table2[[#This Row],[Profit]]/Table2[[#This Row],[Sales Amount]],0) -> 0.17288776 | AH154: =TRIM(Table2[[#This Row],[Payment Modee]]) -> UPI | AI154: Offline | AJ154: Not Returned | AK154: 11:59 | AL154: =IF(HOUR(Table2[[#This Row],[Order Time]])<12,"Morning",IF(HOUR(Table2[[#This Row],[Order Time]])<17,"Afternoon",IF(HOUR(Table2[[#This Row],[Order Time]])<21,"Evening","Night"))) -> Morning | AM154: Weekend
A155: INV100154 | B155: 45623 | C155: =YEAR(Table2[[#This Row],[Invoice Date]]) -> 2024 | D155: =TEXT(Table2[[#This Row],[Invoice Date]],"mmm") -> Nov | E155: =Table2[[#This Row],[Store_ID]]&"-"&Table2[[#This Row],[Year]]&"-"&Table2[[#This Row],[Month]] -> STR117-2024-Nov | F155: CUST0327 | G155: =_xlfn.XLOOKUP(Table2[[#This Row],[Customer_ID]],Table3[Customer_ID],Table3[Customer Name],"Not Found") -> Manju Varma | H155: =_xlfn.XLOOKUP(Table2[[#This Row],[Customer_ID]],Table3[Customer_ID],Table3[Gender],"Female") -> Female | I155: =_xlfn.XLOOKUP(Table2[[#This Row],[Customer_ID]],Table3[Customer_ID],Table3[City],"Missing Memebership") -> Shivamogga | J155: =_xlfn.XLOOKUP(Table2[[#This Row],[Customer_ID]],Table3[Customer_ID],Table3[State],"Karnataka") -> Karnataka | K155: =_xlfn.XLOOKUP(Table2[[#This Row],[Customer_ID]],Table3[Customer_ID],Table3[Membership],"Regular") -> Gold | L155: PRD0048 | M155: =_xlfn.XLOOKUP(Table2[[#This Row],[Product_ID]],Table4[Product_ID],Table4[Product_Name],"Not Found") -> Indian Terrain Denim Shirt Wine | N155: =_xlfn.XLOOKUP(Table2[[#This Row],[Product_ID]],Table4[Product_ID],Table4[Category],"Not Found") -> Accessories | O155: =_xlfn.XLOOKUP(Table2[[#This Row],[Product_ID]],Table4[Product_ID],Table4[Subcategory],"Not Found") -> Tie | P155: =_xlfn.XLOOKUP(Table2[[#This Row],[Product_ID]],Table4[Product_ID],Table4[Brand],"Missing Brand") -> Being Human | Q155: STR117 | R155: =_xlfn.XLOOKUP(Table2[[#This Row],[Store_ID]],Table6[Store_ID],Table6[Store Name],"Not Found") -> TrendMart Tirunelveli Flagship | S155: =_xlfn.XLOOKUP(Table2[[#This Row],[Store_ID]],Table6[Store_ID],Table6[Monthly Target],"Missing Target") -> 1500000 | T155: =_xlfn.XLOOKUP(Table2[[#This Row],[Store_ID]],Table6[Store_ID],Table6[Region],"Not Found") -> South Zone 1 | U155: EMP0063 | V155: =_xlfn.XLOOKUP(Table2[[#This Row],[Employee_ID]],Table5[Employee_ID],Table5[Employee Name],"Not Found") -> Anusuya Subramaniam | W155: 3 | X155: 1026.23 | Y155: 5 | Z155: 153.93 | AA155: 12 | AB155: 350.97 | AC155: 3275.73 | AD155: 1751.58 | AE155: =(AC155-AD155-AB155) -> 1173.18 | AF155: UPI | AG155: =IFERROR(Table2[[#This Row],[Profit]]/Table2[[#This Row],[Sales Amount]],0) -> 0.35814307 | AH155: =TRIM(Table2[[#This Row],[Payment Modee]]) -> UPI | AI155: Offline | AJ155: Returned | AK155: 16:18 | AL155: =IF(HOUR(Table2[[#This Row],[Order Time]])<12,"Morning",IF(HOUR(Table2[[#This Row],[Order Time]])<17,"Afternoon",IF(HOUR(Table2[[#This Row],[Order Time]])<21,"Evening","Night"))) -> Afternoon | AM155: Weekday
A156: INV100155 | B156: 45618 | C156: =YEAR(Table2[[#This Row],[Invoice Date]]) -> 2024 | D156: =TEXT(Table2[[#This Row],[Invoice Date]],"mmm") -> Nov | E156: =Table2[[#This Row],[Store_ID]]&"-"&Table2[[#This Row],[Year]]&"-"&Table2[[#This Row],[Month]] -> STR091-2024-Nov | F156: CUST0614 | G156: =_xlfn.XLOOKUP(Table2[[#This Row],[Customer_ID]],Table3[Customer_ID],Table3[Customer Name],"Not Found") -> Deepthi Gupta | H156: =_xlfn.XLOOKUP(Table2[[#This Row],[Customer_ID]],Table3[Customer_ID],Table3[Gender],"Female") -> Female | I156: =_xlfn.XLOOKUP(Table2[[#This Row],[Customer_ID]],Table3[Customer_ID],Table3[City],"Missing Memebership") -> Kozhikode | J156: =_xlfn.XLOOKUP(Table2[[#This Row],[Customer_ID]],Table3[Customer_ID],Table3[State],"Karnataka") -> Kerala | K156: =_xlfn.XLOOKUP(Table2[[#This Row],[Customer_ID]],Table3[Customer_ID],Table3[Membership],"Regular") -> Regular | L156: PRD0025 | M156: =_xlfn.XLOOKUP(Table2[[#This Row],[Product_ID]],Table4[Product_ID],Table4[Product_Name],"Not Found") -> Pothys Straight Fit Charcoal | N156: =_xlfn.XLOOKUP(Table2[[#This Row],[Product_ID]],Table4[Product_ID],Table4[Category],"Not Found") -> Women Jeans | O156: =_xlfn.XLOOKUP(Table2[[#This Row],[Product_ID]],Table4[Product_ID],Table4[Subcategory],"Not Found") -> Straight Fit | P156: =_xlfn.XLOOKUP(Table2[[#This Row],[Product_ID]],Table4[Product_ID],Table4[Brand],"Missing Brand") -> Pothys | Q156: STR091 | R156: =_xlfn.XLOOKUP(Table2[[#This Row],[Store_ID]],Table6[Store_ID],Table6[Store Name],"Not Found") -> TrendMart Nizamabad Standard | S156: =_xlfn.XLOOKUP(Table2[[#This Row],[Store_ID]],Table6[Store_ID],Table6[Monthly Target],"Missing Target") -> 1500000 | T156: =_xlfn.XLOOKUP(Table2[[#This Row],[Store_ID]],Table6[Store_ID],Table6[Region],"Not Found") -> South Zone 2 | U156: EMP0002 | V156: =_xlfn.XLOOKUP(Table2[[#This Row],[Employee_ID]],Table5[Employee_ID],Table5[Employee Name],"Not Found") -> Girish Sundaram | W156: 2 | X156: 1322.6 | Y156: 0 | Z156: 0 | AA156: 12 | AB156: 317.42 | AC156: 2962.62 | AD156: 2050.48 | AE156: =(AC156-AD156-AB156) -> 594.72 | AF156: Net Banking | AG156: =IFERROR(Table2[[#This Row],[Profit]]/Table2[[#This Row],[Sales Amount]],0) -> 0.20074124 | AH156: =TRIM(Table2[[#This Row],[Payment Modee]]) -> Net Banking | AI156: Online | AJ156: Not Returned | AK156: 19:18 | AL156: =IF(HOUR(Table2[[#This Row],[Order Time]])<12,"Morning",IF(HOUR(Table2[[#This Row],[Order Time]])<17,"Afternoon",IF(HOUR(Table2[[#This Row],[Order Time]])<21,"Evening","Night"))) -> Evening | AM156: Weekday
... A356: INV100355 | B356: 45604 | C356: =YEAR(Table2[[#This Row],[Invoice Date]]) -> 2024 | D356: =TEXT(Table2[[#This Row],[Invoice Date]],"mmm") -> Nov | E356: =Table2[[#This Row],[Store_ID]]&"-"&Table2[[#This Row],[Year]]&"-"&Table2[[#This Row],[Month]] -> STR094-2024-Nov | F356: CUST0725 | G356: =_xlfn.XLOOKUP(Table2[[#This Row],[Customer_ID]],Table3[Customer_ID],Table3[Customer Name],"Not Found") -> Padma Gopalakrishnan | H356: =_xlfn.XLOOKUP(Table2[[#This Row],[Customer_ID]],Table3[Customer_ID],Table3[Gender],"Female") -> Female | I356: =_xlfn.XLOOKUP(Table2[[#This Row],[Customer_ID]],Table3[Customer_ID],Table3[City],"Missing Memebership") -> Chennai | J356: =_xlfn.XLOOKUP(Table2[[#This Row],[Customer_ID]],Table3[Customer_ID],Table3[State],"Karnataka") -> Tamil Nadu | K356: =_xlfn.XLOOKUP(Table2[[#This Row],[Customer_ID]],Table3[Customer_ID],Table3[Membership],"Regular") -> Silver | L356: PRD0141 | M356: =_xlfn.XLOOKUP(Table2[[#This Row],[Product_ID]],Table4[Product_ID],Table4[Product_Name],"Not Found") -> Indian Terrain Formal Top Maroon | N356: =_xlfn.XLOOKUP(Table2[[#This Row],[Product_ID]],Table4[Product_ID],Table4[Category],"Not Found") -> Women Tops | O356: =_xlfn.XLOOKUP(Table2[[#This Row],[Product_ID]],Table4[Product_ID],Table4[Subcategory],"Not Found") -> Formal Top | P356: =_xlfn.XLOOKUP(Table2[[#This Row],[Product_ID]],Table4[Product_ID],Table4[Brand],"Missing Brand") -> Indian Terrain | Q356: STR094 | R356: =_xlfn.XLOOKUP(Table2[[#This Row],[Store_ID]],Table6[Store_ID],Table6[Store Name],"Not Found") -> TrendMart Kollam Flagship | S356: =_xlfn.XLOOKUP(Table2[[#This Row],[Store_ID]],Table6[Store_ID],Table6[Monthly Target],"Missing Target") -> 1200000 | T356: =_xlfn.XLOOKUP(Table2[[#This Row],[Store_ID]],Table6[Store_ID],Table6[Region],"Not Found") -> South Zone 1 | U356: EMP0215 | V356: =_xlfn.XLOOKUP(Table2[[#This Row],[Employee_ID]],Table5[Employee_ID],Table5[Employee Name],"Not Found") -> Praveen Gupta | W356: 2 | X356: 751.36 | Y356: 20 | Z356: 300.54 | AA356: 5 | AB356: 60.11 | AC356: 1262.29 | AD356: 1095.34 | AE356: =(AC356-AD356-AB356) -> 106.84 | AF356: UPI | AG356: =IFERROR(Table2[[#This Row],[Profit]]/Table2[[#This Row],[Sales Amount]],0) -> 0.084639821 | AH356: =TRIM(Table2[[#This Row],[Payment Modee]]) -> UPI | AI356: Offline | AJ356: Not Returned | AK356: 12:43 | AL356: =IF(HOUR(Table2[[#This Row],[Order Time]])<12,"Morning",IF(HOUR(Table2[[#This Row],[Order Time]])<17,"Afternoon",IF(HOUR(Table2[[#This Row],[Order Time]])<21,"Evening","Night"))) -> Afternoon | AM356: Weekday
A357: INV100355 | B357: 45447 | C357: =YEAR(Table2[[#This Row],[Invoice Date]]) -> 2024 | D357: =TEXT(Table2[[#This Row],[Invoice Date]],"mmm") -> Jun | E357: =Table2[[#This Row],[Store_ID]]&"-"&Table2[[#This Row],[Year]]&"-"&Table2[[#This Row],[Month]] -> STR047-2024-Jun | F357: CUST0084 | G357: =_xlfn.XLOOKUP(Table2[[#This Row],[Customer_ID]],Table3[Customer_ID],Table3[Customer Name],"Not Found") -> Hari Kamath | H357: =_xlfn.XLOOKUP(Table2[[#This Row],[Customer_ID]],Table3[Customer_ID],Table3[Gender],"Female") -> Male | I357: =_xlfn.XLOOKUP(Table2[[#This Row],[Customer_ID]],Table3[Customer_ID],Table3[City],"Missing Memebership") -> Tirupati | J357: =_xlfn.XLOOKUP(Table2[[#This Row],[Customer_ID]],Table3[Customer_ID],Table3[State],"Karnataka") -> Andhra Pradesh | K357: =_xlfn.XLOOKUP(Table2[[#This Row],[Customer_ID]],Table3[Customer_ID],Table3[Membership],"Regular") -> Platinum | L357: PRD0055 | M357: =_xlfn.XLOOKUP(Table2[[#This Row],[Product_ID]],Table4[Product_ID],Table4[Product_Name],"Not Found") -> GRT Jewellers Sports T-Shirt Cream | N357: =_xlfn.XLOOKUP(Table2[[#This Row],[Product_ID]],Table4[Product_ID],Table4[Category],"Not Found") -> Sportswear | O357: =_xlfn.XLOOKUP(Table2[[#This Row],[Product_ID]],Table4[Product_ID],Table4[Subcategory],"Not Found") -> Sports T-Shirt | P357: =_xlfn.XLOOKUP(Table2[[#This Row],[Product_ID]],Table4[Product_ID],Table4[Brand],"Missing Brand") -> GRT Jewellers | Q357: STR047 | R357: =_xlfn.XLOOKUP(Table2[[#This Row],[Store_ID]],Table6[Store_ID],Table6[Store Name],"Not Found") -> TrendMart Kurnool Standard | S357: =_xlfn.XLOOKUP(Table2[[#This Row],[Store_ID]],Table6[Store_ID],Table6[Monthly Target],"Missing Target") -> 800000 | T357: =_xlfn.XLOOKUP(Table2[[#This Row],[Store_ID]],Table6[Store_ID],Table6[Region],"Not Found") -> South Zone 3 | U357: EMP0026 | V357: =_xlfn.XLOOKUP(Table2[[#This Row],[Employee_ID]],Table5[Employee_ID],Table5[Employee Name],"Not Found") -> Sunita Ramachandran | W357: 0 | X357: 1453.56 | Y357: 15 | Z357: 0 | AA357: 12 | AB357: 0 | AC357: 0 | AD357: 0 | AE357: 0 | AF357: Cash | AG357: =IFERROR(Table2[[#This Row],[Profit]]/Table2[[#This Row],[Sales Amount]],0) -> 0 | AH357: =TRIM(Table2[[#This Row],[Payment Modee]]) -> Cash | AI357: Online | AJ357: Returned | AK357: 18:20 | AL357: =IF(HOUR(Table2[[#This Row],[Order Time]])<12,"Morning",IF(HOUR(Table2[[#This Row],[Order Time]])<17,"Afternoon",IF(HOUR(Table2[[#This Row],[Order Time]])<21,"Evening","Night"))) -> Evening | AM357: Weekday
A358: INV100356 | B358: 45469 | C358: =YEAR(Table2[[#This Row],[Invoice Date]]) -> 2024 | D358: =TEXT(Table2[[#This Row],[Invoice Date]],"mmm") -> Jun | E358: =Table2[[#This Row],[Store_ID]]&"-"&Table2[[#This Row],[Year]]&"-"&Table2[[#This Row],[Month]] -> STR105-2024-Jun | F358: CUST0331 | G358: =_xlfn.XLOOKUP(Table2[[#This Row],[Customer_ID]],Table3[Customer_ID],Table3[Customer Name],"Not Found") -> Anjali Bhat | H358: =_xlfn.XLOOKUP(Table2[[#This Row],[Customer_ID]],Table3[Customer_ID],Table3[Gender],"Female") -> Female | I358: =_xlfn.XLOOKUP(Table2[[#This Row],[Customer_ID]],Table3[Customer_ID],Table3[City],"Missing Memebership") -> Alappuzha | J358: =_xlfn.XLOOKUP(Table2[[#This Row],[Customer_ID]],Table3[Customer_ID],Table3[State],"Karnataka") -> Kerala | K358: =_xlfn.XLOOKUP(Table2[[#This Row],[Customer_ID]],Table3[Customer_ID],Table3[Membership],"Regular") -> Silver | L358: PRD0128 | M358: =_xlfn.XLOOKUP(Table2[[#This Row],[Product_ID]],Table4[Product_ID],Table4[Product_Name],"Not Found") -> Woodland Straight Kurti White | N358: =_xlfn.XLOOKUP(Table2[[#This Row],[Product_ID]],Table4[Product_ID],Table4[Category],"Not Found") -> Women Kurtis | O358: =_xlfn.XLOOKUP(Table2[[#This Row],[Product_ID]],Table4[Product_ID],Table4[Subcategory],"Not Found") -> Straight Kurti | P358: =_xlfn.XLOOKUP(Table2[[#This Row],[Product_ID]],Table4[Product_ID],Table4[Brand],"Missing Brand") -> Woodland | Q358: STR105 | R358: =_xlfn.XLOOKUP(Table2[[#This Row],[Store_ID]],Table6[Store_ID],Table6[Store Name],"Not Found") -> TrendMart Coimbatore Mall Kiosk | S358: =_xlfn.XLOOKUP(Table2[[#This Row],[Store_ID]],Table6[Store_ID],Table6[Monthly Target],"Missing Target") -> 2500000 | T358: =_xlfn.XLOOKUP(Table2[[#This Row],[Store_ID]],Table6[Store_ID],Table6[Region],"Not Found") -> South Zone 1 | U358: EMP0020 | V358: =_xlfn.XLOOKUP(Table2[[#This Row],[Employee_ID]],Table5[Employee_ID],Table5[Employee Name],"Not Found") -> Eswar Prasad | W358: 2 | X358: 1329.24 | Y358: 30 | Z358: 797.54 | AA358: 12 | AB358: 223.31 | AC358: 2084.25 | AD358: 1689.3 | AE358: =(AC358-AD358-AB358) -> 171.64 | AF358: Debit Card | AG358: =IFERROR(Table2[[#This Row],[Profit]]/Table2[[#This Row],[Sales Amount]],0) -> 0.082350966 | AH358: =TRIM(Table2[[#This Row],[Payment Modee]]) -> Debit Card | AI358: Offline | AJ358: Not Returned | AK358: 15:51 | AL358: =IF(HOUR(Table2[[#This Row],[Order Time]])<12,"Morning",IF(HOUR(Table2[[#This Row],[Order Time]])<17,"Afternoon",IF(HOUR(Table2[[#This Row],[Order Time]])<21,"Evening","Night"))) -> Afternoon | AM358: Weekday
A359: INV100357 | B359: 45529 | C359: =YEAR(Table2[[#This Row],[Invoice Date]]) -> 2024 | D359: =TEXT(Table2[[#This Row],[Invoice Date]],"mmm") -> Aug | E359: =Table2[[#This Row],[Store_ID]]&"-"&Table2[[#This Row],[Year]]&"-"&Table2[[#This Row],[Month]] -> STR076-2024-Aug | F359: CUST0645 | G359: =_xlfn.XLOOKUP(Table2[[#This Row],[Customer_ID]],Table3[Customer_ID],Table3[Customer Name],"Not Found") -> Ganapathy Hegde | H359: =_xlfn.XLOOKUP(Table2[[#This Row],[Customer_ID]],Table3[Customer_ID],Table3[Gender],"Female") -> Male | I359: =_xlfn.XLOOKUP(Table2[[#This Row],[Customer_ID]],Table3[Customer_ID],Table3[City],"Missing Memebership") -> Tiruchirappalli | J359: =_xlfn.XLOOKUP(Table2[[#This Row],[Customer_ID]],Table3[Customer_ID],Table3[State],"Karnataka") -> Tamil Nadu | K359: =_xlfn.XLOOKUP(Table2[[#This Row],[Customer_ID]],Table3[Customer_ID],Table3[Membership],"Regular") -> Silver | L359: PRD0141 | M359: =_xlfn.XLOOKUP(Table2[[#This Row],[Product_ID]],Table4[Product_ID],Table4[Product_Name],"Not Found") -> Indian Terrain Formal Top Maroon | N359: =_xlfn.XLOOKUP(Table2[[#This Row],[Product_ID]],Table4[Product_ID],Table4[Category],"Not Found") -> Women Tops | O359: =_xlfn.XLOOKUP(Table2[[#This Row],[Product_ID]],Table4[Product_ID],Table4[Subcategory],"Not Found") -> Formal Top | P359: =_xlfn.XLOOKUP(Table2[[#This Row],[Product_ID]],Table4[Product_ID],Table4[Brand],"Missing Brand") -> Indian Terrain | Q359: STR076 | R359: =_xlfn.XLOOKUP(Table2[[#This Row],[Store_ID]],Table6[Store_ID],Table6[Store Name],"Not Found") -> TrendMart Chennai Standard | S359: =_xlfn.XLOOKUP(Table2[[#This Row],[Store_ID]],Table6[Store_ID],Table6[Monthly Target],"Missing Target") -> 1500000 | T359: =_xlfn.XLOOKUP(Table2[[#This Row],[Store_ID]],Table6[Store_ID],Table6[Region],"Not Found") -> South Zone 1 | U359: EMP0160 | V359: =_xlfn.XLOOKUP(Table2[[#This Row],[Employee_ID]],Table5[Employee_ID],Table5[Employee Name],"Not Found") -> Ganesh Iyengar | W359: 1 | X359: 815.61 | Y359: 15 | Z359: 122.34 | AA359: 5 | AB359: 34.66 | AC359: 727.93 | AD359: 547.67 | AE359: =(AC359-AD359-AB359) -> 145.6 | AF359: UPI | AG359: =IFERROR(Table2[[#This Row],[Profit]]/Table2[[#This Row],[Sales Amount]],0) -> 0.20001923 | AH359: =TRIM(Table2[[#This Row],[Payment Modee]]) -> UPI | AI359: Online | AJ359: Not Returned | AK359: 11:33 | AL359: =IF(HOUR(Table2[[#This Row],[Order Time]])<12,"Morning",IF(HOUR(Table2[[#This Row],[Order Time]])<17,"Afternoon",IF(HOUR(Table2[[#This Row],[Order Time]])<21,"Evening","Night"))) -> Morning | AM359: Weekend
A360: INV100358 | B360: 45644 | C360: =YEAR(Table2[[#This Row],[Invoice Date]]) -> 2024 | D360: =TEXT(Table2[[#This Row],[Invoice Date]],"mmm") -> Dec | E360: =Table2[[#This Row],[Store_ID]]&"-"&Table2[[#This Row],[Year]]&"-"&Table2[[#This Row],[Month]] -> STR011-2024-Dec | F360: CUST0351 | G360: =_xlfn.XLOOKUP(Table2[[#This Row],[Customer_ID]],Table3[Customer_ID],Table3[Customer Name],"Not Found") -> Tara Subramaniam | H360: =_xlfn.XLOOKUP(Table2[[#This Row],[Customer_ID]],Table3[Customer_ID],Table3[Gender],"Female") -> Female | I360: =_xlfn.XLOOKUP(Table2[[#This Row],[Customer_ID]],Table3[Customer_ID],Table3[City],"Missing Memebership") -> Guntur | J360: =_xlfn.XLOOKUP(Table2[[#This Row],[Customer_ID]],Table3[Customer_ID],Table3[State],"Karnataka") -> Andhra Pradesh | K360: =_xlfn.XLOOKUP(Table2[[#This Row],[Customer_ID]],Table3[Customer_ID],Table3[Membership],"Regular") -> Platinum | L360: PRD0227 | M360: =_xlfn.XLOOKUP(Table2[[#This Row],[Product_ID]],Table4[Product_ID],Table4[Product_Name],"Not Found") -> Allen Solly Tie Pink | N360: =_xlfn.XLOOKUP(Table2[[#This Row],[Product_ID]],Table4[Product_ID],Table4[Category],"Not Found") -> Accessories | O360: =_xlfn.XLOOKUP(Table2[[#This Row],[Product_ID]],Table4[Product_ID],Table4[Subcategory],"Not Found") -> Tie | P360: =_xlfn.XLOOKUP(Table2[[#This Row],[Product_ID]],Table4[Product_ID],Table4[Brand],"Missing Brand") -> Allen Solly | Q360: STR011 | R360: =_xlfn.XLOOKUP(Table2[[#This Row],[Store_ID]],Table6[Store_ID],Table6[Store Name],"Not Found") -> TrendMart Tirupati Standard | S360: =_xlfn.XLOOKUP(Table2[[#This Row],[Store_ID]],Table6[Store_ID],Table6[Monthly Target],"Missing Target") -> 2000000 | T360: =_xlfn.XLOOKUP(Table2[[#This Row],[Store_ID]],Table6[Store_ID],Table6[Region],"Not Found") -> South Zone 3 | U360: EMP0204 | V360: =_xlfn.XLOOKUP(Table2[[#This Row],[Employee_ID]],Table5[Employee_ID],Table5[Employee Name],"Not Found") -> Rahul Krishnan | W360: 4 | X360: 721.33 | Y360: 15 | Z360: 432.8 | AA360: 5 | AB360: 122.63 | AC360: 2575.15 | AD360: 1772.76 | AE360: =(AC360-AD360-AB360) -> 679.76 | AF360: Debit Card | AG360: =IFERROR(Table2[[#This Row],[Profit]]/Table2[[#This Row],[Sales Amount]],0) -> 0.26396909 | AH360: =TRIM(Table2[[#This Row],[Payment Modee]]) -> Debit Card | AI360: Online | AJ360: Not Returned | AK360: 20:41 | AL360: =IF(HOUR(Table2[[#This Row],[Order Time]])<12,"Morning",IF(HOUR(Table2[[#This Row],[Order Time]])<17,"Afternoon",IF(HOUR(Table2[[#This Row],[Order Time]])<21,"Evening","Night"))) -> Evening | AM360: Weekday
A361: INV100359 | B361: 45603 | C361: =YEAR(Table2[[#This Row],[Invoice Date]]) -> 2024 | D361: =TEXT(Table2[[#This Row],[Invoice Date]],"mmm") -> Nov | E361: =Table2[[#This Row],[Store_ID]]&"-"&Table2[[#This Row],[Year]]&"-"&Table2[[#This Row],[Month]] -> STR037-2024-Nov | F361: CUST0526 | G361: =_xlfn.XLOOKUP(Table2[[#This Row],[Customer_ID]],Table3[Customer_ID],Table3[Customer Name],"Not Found") -> Manikandan Chettiar | H361: =_xlfn.XLOOKUP(Table2[[#This Row],[Customer_ID]],Table3[Customer_ID],Table3[Gender],"Female") -> Male | I361: =_xlfn.XLOOKUP(Table2[[#This Row],[Customer_ID]],Table3[Customer_ID],Table3[City],"Missing Memebership") -> Vijayawada | J361: =_xlfn.XLOOKUP(Table2[[#This Row],[Customer_ID]],Table3[Customer_ID],Table3[State],"Karnataka") -> Andhra Pradesh | K361: =_xlfn.XLOOKUP(Table2[[#This Row],[Customer_ID]],Table3[Customer_ID],Table3[Membership],"Regular") -> Regular | L361: PRD0146 | M361: =_xlfn.XLOOKUP(Table2[[#This Row],[Product_ID]],Table4[Product_ID],Table4[Product_Name],"Not Found") -> Metro Shoes Digital Watch Beige | N361: =_xlfn.XLOOKUP(Table2[[#This Row],[Product_ID]],Table4[Product_ID],Table4[Category],"Not Found") -> Watches | O361: =_xlfn.XLOOKUP(Table2[[#This Row],[Product_ID]],Table4[Product_ID],Table4[Subcategory],"Not Found") -> Digital Watch | P361: =_xlfn.XLOOKUP(Table2[[#This Row],[Product_ID]],Table4[Product_ID],Table4[Brand],"Missing Brand") -> Metro Shoes | Q361: STR037 | R361: =_xlfn.XLOOKUP(Table2[[#This Row],[Store_ID]],Table6[Store_ID],Table6[Store Name],"Not Found") -> TrendMart Vijayawada High Street | S361: =_xlfn.XLOOKUP(Table2[[#This Row],[Store_ID]],Table6[Store_ID],Table6[Monthly Target],"Missing Target") -> 1000000 | T361: =_xlfn.XLOOKUP(Table2[[#This Row],[Store_ID]],Table6[Store_ID],Table6[Region],"Not Found") -> South Zone 3 | U361: EMP0127 | V361: =_xlfn.XLOOKUP(Table2[[#This Row],[Employee_ID]],Table5[Employee_ID],Table5[Employee Name],"Not Found") -> Chandra Reddy | W361: 4 | X361: 6217 | Y361: 10 | Z361: 2486.8 | AA361: 12 | AB361: 2685.74 | AC361: 25066.94 | AD361: 15846.48 | AE361: =(AC361-AD361-AB361) -> 6534.72 | AF361: UPI | AG361: =IFERROR(Table2[[#This Row],[Profit]]/Table2[[#This Row],[Sales Amount]],0) -> 0.26069077 | AH361: =TRIM(Table2[[#This Row],[Payment Modee]]) -> UPI | AI361: Offline | AJ361: Not Returned | AK361: 10:04 | AL361: =IF(HOUR(Table2[[#This Row],[Order Time]])<12,"Morning",IF(HOUR(Table2[[#This Row],[Order Time]])<17,"Afternoon",IF(HOUR(Table2[[#This Row],[Order Time]])<21,"Evening","Night"))) -> Morning | AM361: Weekday
A362: INV100360 | B362: 45572 | C362: =YEAR(Table2[[#This Row],[Invoice Date]]) -> 2024 | D362: =TEXT(Table2[[#This Row],[Invoice Date]],"mmm") -> Oct | E362: =Table2[[#This Row],[Store_ID]]&"-"&Table2[[#This Row],[Year]]&"-"&Table2[[#This Row],[Month]] -> STR014-2024-Oct | F362: CUST0100 | G362: =_xlfn.XLOOKUP(Table2[[#This Row],[Customer_ID]],Table3[Customer_ID],Table3[Customer Name],"Not Found") -> Chidambaram Rao | H362: =_xlfn.XLOOKUP(Table2[[#This Row],[Customer_ID]],Table3[Customer_ID],Table3[Gender],"Female") -> Male | I362: =_xlfn.XLOOKUP(Table2[[#This Row],[Customer_ID]],Table3[Customer_ID],Table3[City],"Missing Memebership") -> Bengaluru | J362: =_xlfn.XLOOKUP(Table2[[#This Row],[Customer_ID]],Table3[Customer_ID],Table3[State],"Karnataka") -> Karnataka | K362: =_xlfn.XLOOKUP(Table2[[#This Row],[Customer_ID]],Table3[Customer_ID],Table3[Membership],"Regular") -> Platinum | L362: PRD0072 | M362: =_xlfn.XLOOKUP(Table2[[#This Row],[Product_ID]],Table4[Product_ID],Table4[Product_Name],"Not Found") -> Metro Shoes Straight Kurti Green | N362: =_xlfn.XLOOKUP(Table2[[#This Row],[Product_ID]],Table4[Product_ID],Table4[Category],"Not Found") -> Women Kurtis | O362: =_xlfn.XLOOKUP(Table2[[#This Row],[Product_ID]],Table4[Product_ID],Table4[Subcategory],"Not Found") -> Straight Kurti | P362: =_xlfn.XLOOKUP(Table2[[#This Row],[Product_ID]],Table4[Product_ID],Table4[Brand],"Missing Brand") -> Metro Shoes | Q362: STR014 | R362: =_xlfn.XLOOKUP(Table2[[#This Row],[Store_ID]],Table6[Store_ID],Table6[Store Name],"Not Found") -> TrendMart Tirupati Outlet | S362: =_xlfn.XLOOKUP(Table2[[#This Row],[Store_ID]],Table6[Store_ID],Table6[Monthly Target],"Missing Target") -> 1000000 | T362: =_xlfn.XLOOKUP(Table2[[#This Row],[Store_ID]],Table6[Store_ID],Table6[Region],"Not Found") -> South Zone 3 | U362: EMP0225 | V362: =_xlfn.XLOOKUP(Table2[[#This Row],[Employee_ID]],Table5[Employee_ID],Table5[Employee Name],"Not Found") -> Swathi Achari | W362: 1 | X362: 859.03 | Y362: 10 | Z362: 85.9 | AA362: 5 | AB362: 38.66 | AC362: 811.79 | AD362: 599.28 | AE362: =(AC362-AD362-AB362) -> 173.85 | AF362: UPI | AG362: =IFERROR(Table2[[#This Row],[Profit]]/Table2[[#This Row],[Sales Amount]],0) -> 0.21415637 | AH362: =TRIM(Table2[[#This Row],[Payment Modee]]) -> UPI | AI362: Online | AJ362: Not Returned | AK362: 16:58 | AL362: =IF(HOUR(Table2[[#This Row],[Order Time]])<12,"Morning",IF(HOUR(Table2[[#This Row],[Order Time]])<17,"Afternoon",IF(HOUR(Table2[[#This Row],[Order Time]])<21,"Evening","Night"))) -> Afternoon | AM362: Weekday
A363: INV100361 | B363: 45690 | C363: =YEAR(Table2[[#This Row],[Invoice Date]]) -> 2025 | D363: =TEXT(Table2[[#This Row],[Invoice Date]],"mmm") -> Feb | E363: =Table2[[#This Row],[Store_ID]]&"-"&Table2[[#This Row],[Year]]&"-"&Table2[[#This Row],[Month]] -> STR080-2025-Feb | F363: CUST0678 | G363: =_xlfn.XLOOKUP(Table2[[#This Row],[Customer_ID]],Table3[Customer_ID],Table3[Customer Name],"Not Found") -> Ganesh Kamath | H363: =_xlfn.XLOOKUP(Table2[[#This Row],[Customer_ID]],Table3[Customer_ID],Table3[Gender],"Female") -> Male | I363: =_xlfn.XLOOKUP(Table2[[#This Row],[Customer_ID]],Table3[Customer_ID],Table3[City],"Missing Memebership") -> Visakhapatnam | J363: =_xlfn.XLOOKUP(Table2[[#This Row],[Customer_ID]],Table3[Customer_ID],Table3[State],"Karnataka") -> Andhra Pradesh | K363: =_xlfn.XLOOKUP(Table2[[#This Row],[Customer_ID]],Table3[Customer_ID],Table3[Membership],"Regular") -> Gold | L363: PRD0126 | M363: =_xlfn.XLOOKUP(Table2[[#This Row],[Product_ID]],Table4[Product_ID],Table4[Product_Name],"Not Found") -> Van Heusen Formal Shirt Olive | N363: =_xlfn.XLOOKUP(Table2[[#This Row],[Product_ID]],Table4[Product_ID],Table4[Category],"Not Found") -> Men Shirts | O363: =_xlfn.XLOOKUP(Table2[[#This Row],[Product_ID]],Table4[Product_ID],Table4[Subcategory],"Not Found") -> Formal Shirt | P363: =_xlfn.XLOOKUP(Table2[[#This Row],[Product_ID]],Table4[Product_ID],Table4[Brand],"Missing Brand") -> Van Heusen | Q363: STR080 | R363: =_xlfn.XLOOKUP(Table2[[#This Row],[Store_ID]],Table6[Store_ID],Table6[Store Name],"Not Found") -> TrendMart Kochi High Street | S363: =_xlfn.XLOOKUP(Table2[[#This Row],[Store_ID]],Table6[Store_ID],Table6[Monthly Target],"Missing Target") -> 2000000 | T363: =_xlfn.XLOOKUP(Table2[[#This Row],[Store_ID]],Table6[Store_ID],Table6[Region],"Not Found") -> South Zone 1 | U363: EMP0225 | V363: =_xlfn.XLOOKUP(Table2[[#This Row],[Employee_ID]],Table5[Employee_ID],Table5[Employee Name],"Not Found") -> Swathi Achari | W363: 1 | X363: 1065.87 | Y363: 15 | Z363: 159.88 | AA363: 12 | AB363: 108.72 | AC363: 1014.71 | AD363: 645.59 | AE363: =(AC363-AD363-AB363) -> 260.4 | AF363: Cash | AG363: =IFERROR(Table2[[#This Row],[Profit]]/Table2[[#This Row],[Sales Amount]],0) -> 0.25662505 | AH363: =TRIM(Table2[[#This Row],[Payment Modee]]) -> Cash | AI363: Online | AJ363: Not Returned | AK363: 17:44 | AL363: =IF(HOUR(Table2[[#This Row],[Order Time]])<12,"Morning",IF(HOUR(Table2[[#This Row],[Order Time]])<17,"Afternoon",IF(HOUR(Table2[[#This Row],[Order Time]])<21,"Evening","Night"))) -> Evening | AM363: Weekend
A364: INV100362 | B364: 45602 | C364: =YEAR(Table2[[#This Row],[Invoice Date]]) -> 2024 | D364: =TEXT(Table2[[#This Row],[Invoice Date]],"mmm") -> Nov | E364: =Table2[[#This Row],[Store_ID]]&"-"&Table2[[#This Row],[Year]]&"-"&Table2[[#This Row],[Month]] -> STR066-2024-Nov | F364: CUST0289 | G364: =_xlfn.XLOOKUP(Table2[[#This Row],[Customer_ID]],Table3[Customer_ID],Table3[Customer Name],"Not Found") -> Balaji Kumar | H364: =_xlfn.XLOOKUP(Table2[[#This Row],[Customer_ID]],Table3[Customer_ID],Table3[Gender],"Female") -> Male | I364: =_xlfn.XLOOKUP(Table2[[#This Row],[Customer_ID]],Table3[Customer_ID],Table3[City],"Missing Memebership") -> Warangal | J364: =_xlfn.XLOOKUP(Table2[[#This Row],[Customer_ID]],Table3[Customer_ID],Table3[State],"Karnataka") -> Telangana | K364: =_xlfn.XLOOKUP(Table2[[#This Row],[Customer_ID]],Table3[Customer_ID],Table3[Membership],"Regular") -> Silver | L364: PRD0025 | M364: =_xlfn.XLOOKUP(Table2[[#This Row],[Product_ID]],Table4[Product_ID],Table4[Product_Name],"Not Found") -> Pothys Straight Fit Charcoal | N364: =_xlfn.XLOOKUP(Table2[[#This Row],[Product_ID]],Table4[Product_ID],Table4[Category],"Not Found") -> Women Jeans | O364: =_xlfn.XLOOKUP(Table2[[#This Row],[Product_ID]],Table4[Product_ID],Table4[Subcategory],"Not Found") -> Straight Fit | P364: =_xlfn.XLOOKUP(Table2[[#This Row],[Product_ID]],Table4[Product_ID],Table4[Brand],"Missing Brand") -> Pothys | Q364: STR066 | R364: =_xlfn.XLOOKUP(Table2[[#This Row],[Store_ID]],Table6[Store_ID],Table6[Store Name],"Not Found") -> TrendMart Dindigul Standard | S364: =_xlfn.XLOOKUP(Table2[[#This Row],[Store_ID]],Table6[Store_ID],Table6[Monthly Target],"Missing Target") -> 2500000 | T364: =_xlfn.XLOOKUP(Table2[[#This Row],[Store_ID]],Table6[Store_ID],Table6[Region],"Not Found") -> South Zone 1 | U364: EMP0173 | V364: =_xlfn.XLOOKUP(Table2[[#This Row],[Employee_ID]],Table5[Employee_ID],Table5[Employee Name],"Not Found") -> Logesh Gopalakrishnan | W364: 2 | X364: 1382.13 | Y364: 0 | Z364: 0 | AA364: 12 | AB364: 331.71 | AC364: 3095.97 | AD364: 2050.48 | AE364: =(AC364-AD364-AB364) -> 713.78 | AF364: UPI | AG364: =IFERROR(Table2[[#This Row],[Profit]]/Table2[[#This Row],[Sales Amount]],0) -> 0.23055133 | AH364: =TRIM(Table2[[#This Row],[Payment Modee]]) -> UPI | AI364: Offline | AJ364: Not Returned | AK364: 13:02 | AL364: =IF(HOUR(Table2[[#This Row],[Order Time]])<12,"Morning",IF(HOUR(Table2[[#This Row],[Order Time]])<17,"Afternoon",IF(HOUR(Table2[[#This Row],[Order Time]])<21,"Evening","Night"))) -> Afternoon | AM364: Weekday
A365: INV100363 | B365: 45663 | C365: =YEAR(Table2[[#This Row],[Invoice Date]]) -> 2025 | D365: =TEXT(Table2[[#This Row],[Invoice Date]],"mmm") -> Jan | E365: =Table2[[#This Row],[Store_ID]]&"-"&Table2[[#This Row],[Year]]&"-"&Table2[[#This Row],[Month]] -> STR049-2025-Jan | F365: CUST0815 | G365: =_xlfn.XLOOKUP(Table2[[#This Row],[Customer_ID]],Table3[Customer_ID],Table3[Customer Name],"Not Found") -> Varsha Chandran | H365: =_xlfn.XLOOKUP(Table2[[#This Row],[Customer_ID]],Table3[Customer_ID],Table3[Gender],"Female") -> Female | I365: =_xlfn.XLOOKUP(Table2[[#This Row],[Customer_ID]],Table3[Customer_ID],Table3[City],"Missing Memebership") -> Nellore | J365: =_xlfn.XLOOKUP(Table2[[#This Row],[Customer_ID]],Table3[Customer_ID],Table3[State],"Karnataka") -> Andhra Pradesh | K365: =_xlfn.XLOOKUP(Table2[[#This Row],[Customer_ID]],Table3[Customer_ID],Table3[Membership],"Regular") -> Regular | L365: PRD0175 | M365: =_xlfn.XLOOKUP(Table2[[#This Row],[Product_ID]],Table4[Product_ID],Table4[Product_Name],"Not Found") -> Fabindia Straight Kurti Olive | N365: =_xlfn.XLOOKUP(Table2[[#This Row],[Product_ID]],Table4[Product_ID],Table4[Category],"Not Found") -> Women Kurtis | O365: =_xlfn.XLOOKUP(Table2[[#This Row],[Product_ID]],Table4[Product_ID],Table4[Subcategory],"Not Found") -> Straight Kurti | P365: =_xlfn.XLOOKUP(Table2[[#This Row],[Product_ID]],Table4[Product_ID],Table4[Brand],"Missing Brand") -> Fabindia | Q365: STR049 | R365: =_xlfn.XLOOKUP(Table2[[#This Row],[Store_ID]],Table6[Store_ID],Table6[Store Name],"Not Found") -> TrendMart Bengaluru Flagship | S365: =_xlfn.XLOOKUP(Table2[[#This Row],[Store_ID]],Table6[Store_ID],Table6[Monthly Target],"Missing Target") -> 1200000 | T365: =_xlfn.XLOOKUP(Table2[[#This Row],[Store_ID]],Table6[Store_ID],Table6[Region],"Not Found") -> South Zone 2 | U365: EMP0205 | V365: =_xlfn.XLOOKUP(Table2[[#This Row],[Employee_ID]],Table5[Employee_ID],Table5[Employee Name],"Not Found") -> Malini Gowda | W365: 2 | X365: 768.22 | Y365: 0 | Z365: 0 | AA365: 5 | AB365: 76.82 | AC365: 1613.26 | AD365: 1142.18 | AE365: =(AC365-AD365-AB365) -> 394.26 | AF365: UPI | AG365: =IFERROR(Table2[[#This Row],[Profit]]/Table2[[#This Row],[Sales Amount]],0) -> 0.24438714 | AH365: =TRIM(Table2[[#This Row],[Payment Modee]]) -> UPI | AI365: Offline | AJ365: Not Returned | AK365: 20:48 | AL365: =IF(HOUR(Table2[[#This Row],[Order Time]])<12,"Morning",IF(HOUR(Table2[[#This Row],[Order Time]])<17,"Afternoon",IF(HOUR(Table2[[#This Row],[Order Time]])<21,"Evening","Night"))) -> Evening | AM365: Weekday
A366: INV100364 | B366: 45609 | C366: =YEAR(Table2[[#This Row],[Invoice Date]]) -> 2024 | D366: =TEXT(Table2[[#This Row],[Invoice Date]],"mmm") -> Nov | E366: =Table2[[#This Row],[Store_ID]]&"-"&Table2[[#This Row],[Year]]&"-"&Table2[[#This Row],[Month]] -> STR087-2024-Nov | F366: CUST0579 | G366: =_xlfn.XLOOKUP(Table2[[#This Row],[Customer_ID]],Table3[Customer_ID],Table3[Customer Name],"Not Found") -> Meena Rao | H366: =_xlfn.XLOOKUP(Table2[[#This Row],[Customer_ID]],Table3[Customer_ID],Table3[Gender],"Female") -> Female | I366: =_xlfn.XLOOKUP(Table2[[#This Row],[Customer_ID]],Table3[Customer_ID],Table3[City],"Missing Memebership") -> Khammam | J366: =_xlfn.XLOOKUP(Table2[[#This Row],[Customer_ID]],Table3[Customer_ID],Table3[State],"Karnataka") -> Telangana | K366: =_xlfn.XLOOKUP(Table2[[#This Row],[Customer_ID]],Table3[Customer_ID],Table3[Membership],"Regular") -> Platinum | L366: PRD0072 | M366: =_xlfn.XLOOKUP(Table2[[#This Row],[Product_ID]],Table4[Product_ID],Table4[Product_Name],"Not Found") -> Metro Shoes Straight Kurti Green | N366: =_xlfn.XLOOKUP(Table2[[#This Row],[Product_ID]],Table4[Product_ID],Table4[Category],"Not Found") -> Women Kurtis | O366: =_xlfn.XLOOKUP(Table2[[#This Row],[Product_ID]],Table4[Product_ID],Table4[Subcategory],"Not Found") -> Straight Kurti | P366: =_xlfn.XLOOKUP(Table2[[#This Row],[Product_ID]],Table4[Product_ID],Table4[Brand],"Missing Brand") -> Metro Shoes | Q366: STR087 | R366: =_xlfn.XLOOKUP(Table2[[#This Row],[Store_ID]],Table6[Store_ID],Table6[Store Name],"Not Found") -> TrendMart Salem Outlet | S366: =_xlfn.XLOOKUP(Table2[[#This Row],[Store_ID]],Table6[Store_ID],Table6[Monthly Target],"Missing Target") -> 2000000 | T366: =_xlfn.XLOOKUP(Table2[[#This Row],[Store_ID]],Table6[Store_ID],Table6[Region],"Not Found") -> South Zone 1 | U366: EMP0285 | V366: =_xlfn.XLOOKUP(Table2[[#This Row],[Employee_ID]],Table5[Employee_ID],Table5[Employee Name],"Not Found") -> Chandran Krishnan | W366: 1 | X366: 842.07 | Y366: 15 | Z366: 126.31 | AA366: 5 | AB366: 35.79 | AC366: 751.55 | AD366: 599.28 | AE366: =(AC366-AD366-AB366) -> 116.48 | AF366: Credit Card | AG366: =IFERROR(Table2[[#This Row],[Profit]]/Table2[[#This Row],[Sales Amount]],0) -> 0.15498636 | AH366: =TRIM(Table2[[#This Row],[Payment Modee]]) -> Credit Card | AI366: Offline | AJ366: Not Returned | AK366: 21:38 | AL366: =IF(HOUR(Table2[[#This Row],[Order Time]])<12,"Morning",IF(HOUR(Table2[[#This Row],[Order Time]])<17,"Afternoon",IF(HOUR(Table2[[#This Row],[Order Time]])<21,"Evening","Night"))) -> Night | AM366: Weekday
A367: INV100365 | B367: 45400 | C367: =YEAR(Table2[[#This Row],[Invoice Date]]) -> 2024 | D367: =TEXT(Table2[[#This Row],[Invoice Date]],"mmm") -> Apr | E367: =Table2[[#This Row],[Store_ID]]&"-"&Table2[[#This Row],[Year]]&"-"&Table2[[#This Row],[Month]] -> STR012-2024-Apr | F367: CUST0588 | G367: =_xlfn.XLOOKUP(Table2[[#This Row],[Customer_ID]],Table3[Customer_ID],Table3[Customer Name],"Not Found") -> Nisha Achari | H367: =_xlfn.XLOOKUP(Table2[[#This Row],[Customer_ID]],Table3[Customer_ID],Table3[Gender],"Female") -> Female | I367: =_xlfn.XLOOKUP(Table2[[#This Row],[Customer_ID]],Table3[Customer_ID],Table3[City],"Missing Memebership") -> Hyderabad | J367: =_xlfn.XLOOKUP(Table2[[#This Row],[Customer_ID]],Table3[Customer_ID],Table3[State],"Karnataka") -> Telangana | K367: =_xlfn.XLOOKUP(Table2[[#This Row],[Customer_ID]],Table3[Customer_ID],Table3[Membership],"Regular") -> Silver | L367: PRD0247 | M367: =_xlfn.XLOOKUP(Table2[[#This Row],[Product_ID]],Table4[Product_ID],Table4[Product_Name],"Not Found") -> Pantaloons Braided Belt Brown | N367: =_xlfn.XLOOKUP(Table2[[#This Row],[Product_ID]],Table4[Product_ID],Table4[Category],"Not Found") -> Belts | O367: =_xlfn.XLOOKUP(Table2[[#This Row],[Product_ID]],Table4[Product_ID],Table4[Subcategory],"Not Found") -> Braided Belt | P367: =_xlfn.XLOOKUP(Table2[[#This Row],[Product_ID]],Table4[Product_ID],Table4[Brand],"Missing Brand") -> Pantaloons | Q367: STR012 | R367: =_xlfn.XLOOKUP(Table2[[#This Row],[Store_ID]],Table6[Store_ID],Table6[Store Name],"Not Found") -> TrendMart Vijayawada Mall Kiosk | S367: =_xlfn.XLOOKUP(Table2[[#This Row],[Store_ID]],Table6[Store_ID],Table6[Monthly Target],"Missing Target") -> 2000000 | T367: =_xlfn.XLOOKUP(Table2[[#This Row],[Store_ID]],Table6[Store_ID],Table6[Region],"Not Found") -> South Zone 3 | U367: EMP0225 | V367: =_xlfn.XLOOKUP(Table2[[#This Row],[Employee_ID]],Table5[Employee_ID],Table5[Employee Name],"Not Found") -> Swathi Achari | W367: 1 | X367: 1118.69 | Y367: 0 | Z367: 0 | AA367: 12 | AB367: 134.24 | AC367: 1252.93 | AD367: 765.23 | AE367: =(AC367-AD367-AB367) -> 353.46 | AF367: UPI | AG367: =IFERROR(Table2[[#This Row],[Profit]]/Table2[[#This Row],[Sales Amount]],0) -> 0.28210674 | AH367: =TRIM(Table2[[#This Row],[Payment Modee]]) -> UPI | AI367: Offline | AJ367: Not Returned | AK367: 15:59 | AL367: =IF(HOUR(Table2[[#This Row],[Order Time]])<12,"Morning",IF(HOUR(Table2[[#This Row],[Order Time]])<17,"Afternoon",IF(HOUR(Table2[[#This Row],[Order Time]])<21,"Evening","Night"))) -> Afternoon | AM367: Weekday
A368: INV100366 | B368: 45586 | C368: =YEAR(Table2[[#This Row],[Invoice Date]]) -> 2024 | D368: =TEXT(Table2[[#This Row],[Invoice Date]],"mmm") -> Oct | E368: =Table2[[#This Row],[Store_ID]]&"-"&Table2[[#This Row],[Year]]&"-"&Table2[[#This Row],[Month]] -> STR115-2024-Oct | F368: CUST0350 | G368: =_xlfn.XLOOKUP(Table2[[#This Row],[Customer_ID]],Table3[Customer_ID],Table3[Customer Name],"Not Found") -> Sanjay Chandran | H368: =_xlfn.XLOOKUP(Table2[[#This Row],[Customer_ID]],Table3[Customer_ID],Table3[Gender],"Female") -> Male | I368: =_xlfn.XLOOKUP(Table2[[#This Row],[Customer_ID]],Table3[Customer_ID],Table3[City],"Missing Memebership") -> Kozhikode | J368: =_xlfn.XLOOKUP(Table2[[#This Row],[Customer_ID]],Table3[Customer_ID],Table3[State],"Karnataka") -> Kerala | K368: =_xlfn.XLOOKUP(Table2[[#This Row],[Customer_ID]],Table3[Customer_ID],Table3[Membership],"Regular") -> Gold | L368: PRD0226 | M368: =_xlfn.XLOOKUP(Table2[[#This Row],[Product_ID]],Table4[Product_ID],Table4[Product_Name],"Not Found") -> Being Human Track Suit Mustard | N368: =_xlfn.XLOOKUP(Table2[[#This Row],[Product_ID]],Table4[Product_ID],Table4[Category],"Not Found") -> Sportswear | O368: =_xlfn.XLOOKUP(Table2[[#This Row],[Product_ID]],Table4[Product_ID],Table4[Subcategory],"Not Found") -> Track Suit | P368: =_xlfn.XLOOKUP(Table2[[#This Row],[Product_ID]],Table4[Product_ID],Table4[Brand],"Missing Brand") -> Being Human | Q368: STR115 | R368: =_xlfn.XLOOKUP(Table2[[#This Row],[Store_ID]],Table6[Store_ID],Table6[Store Name],"Not Found") -> TrendMart Bengaluru Standard | S368: =_xlfn.XLOOKUP(Table2[[#This Row],[Store_ID]],Table6[Store_ID],Table6[Monthly Target],"Missing Target") -> 1500000 | T368: =_xlfn.XLOOKUP(Table2[[#This Row],[Store_ID]],Table6[Store_ID],Table6[Region],"Not Found") -> South Zone 2 | U368: EMP0001 | V368: =_xlfn.XLOOKUP(Table2[[#This Row],[Employee_ID]],Table5[Employee_ID],Table5[Employee Name],"Not Found") -> Charulatha Kumar | W368: 2 | X368: 919.75 | Y368: 0 | Z368: 0 | AA368: 5 | AB368: 91.97 | AC368: 1931.47 | AD368: 1252.52 | AE368: =(AC368-AD368-AB368) -> 586.98 | AF368: UPI | AG368: =IFERROR(Table2[[#This Row],[Profit]]/Table2[[#This Row],[Sales Amount]],0) -> 0.30390324 | AH368: =TRIM(Table2[[#This Row],[Payment Modee]]) -> UPI | AI368: Offline | AJ368: Not Returned | AK368: 15:50 | AL368: =IF(HOUR(Table2[[#This Row],[Order Time]])<12,"Morning",IF(HOUR(Table2[[#This Row],[Order Time]])<17,"Afternoon",IF(HOUR(Table2[[#This Row],[Order Time]])<21,"Evening","Night"))) -> Afternoon | AM368: Weekday
A369: INV100367 | B369: 45410 | C369: =YEAR(Table2[[#This Row],[Invoice Date]]) -> 2024 | D369: =TEXT(Table2[[#This Row],[Invoice Date]],"mmm") -> Apr | E369: =Table2[[#This Row],[Store_ID]]&"-"&Table2[[#This Row],[Year]]&"-"&Table2[[#This Row],[Month]] -> STR120-2024-Apr | F369: CUST0792 | G369: =_xlfn.XLOOKUP(Table2[[#This Row],[Customer_ID]],Table3[Customer_ID],Table3[Customer Name],"Not Found") -> Varsha Kamath | H369: =_xlfn.XLOOKUP(Table2[[#This Row],[Customer_ID]],Table3[Customer_ID],Table3[Gender],"Female") -> Female | I369: =_xlfn.XLOOKUP(Table2[[#This Row],[Customer_ID]],Table3[Customer_ID],Table3[City],"Missing Memebership") -> Thoothukudi | J369: =_xlfn.XLOOKUP(Table2[[#This Row],[Customer_ID]],Table3[Customer_ID],Table3[State],"Karnataka") -> Tamil Nadu | K369: =_xlfn.XLOOKUP(Table2[[#This Row],[Customer_ID]],Table3[Customer_ID],Table3[Membership],"Regular") -> Gold | L369: PRD0061 | M369: =_xlfn.XLOOKUP(Table2[[#This Row],[Product_ID]],Table4[Product_ID],Table4[Product_Name],"Not Found") -> Allen Solly Kids Shorts Teal | N369: =_xlfn.XLOOKUP(Table2[[#This Row],[Product_ID]],Table4[Product_ID],Table4[Category],"Not Found") -> Kids Wear | O369: =_xlfn.XLOOKUP(Table2[[#This Row],[Product_ID]],Table4[Product_ID],Table4[Subcategory],"Not Found") -> Kids Shorts | P369: =_xlfn.XLOOKUP(Table2[[#This Row],[Product_ID]],Table4[Product_ID],Table4[Brand],"Missing Brand") -> Allen Solly | Q369: STR120 | R369: =_xlfn.XLOOKUP(Table2[[#This Row],[Store_ID]],Table6[Store_ID],Table6[Store Name],"Not Found") -> TrendMart Karimnagar Standard | S369: =_xlfn.XLOOKUP(Table2[[#This Row],[Store_ID]],Table6[Store_ID],Table6[Monthly Target],"Missing Target") -> 1500000 | T369: =_xlfn.XLOOKUP(Table2[[#This Row],[Store_ID]],Table6[Store_ID],Table6[Region],"Not Found") -> South Zone 2 | U369: EMP0215 | V369: =_xlfn.XLOOKUP(Table2[[#This Row],[Employee_ID]],Table5[Employee_ID],Table5[Employee Name],"Not Found") -> Praveen Gupta | W369: 2 | X369: 723.48 | Y369: 0 | Z369: 0 | AA369: 5 | AB369: 72.35 | AC369: 1519.31 | AD369: 1018.88 | AE369: =(AC369-AD369-AB369) -> 428.08 | AF369: UPI | AG369: =IFERROR(Table2[[#This Row],[Profit]]/Table2[[#This Row],[Sales Amount]],0) -> 0.28175948 | AH369: =TRIM(Table2[[#This Row],[Payment Modee]]) -> UPI | AI369: Offline | AJ369: Not Returned | AK369: 15:54 | AL369: =IF(HOUR(Table2[[#This Row],[Order Time]])<12,"Morning",IF(HOUR(Table2[[#This Row],[Order Time]])<17,"Afternoon",IF(HOUR(Table2[[#This Row],[Order Time]])<21,"Evening","Night"))) -> Afternoon | AM369: Weekend
... A387: INV100385 | B387: 45705 | C387: =YEAR(Table2[[#This Row],[Invoice Date]]) -> 2025 | D387: =TEXT(Table2[[#This Row],[Invoice Date]],"mmm") -> Feb | E387: =Table2[[#This Row],[Store_ID]]&"-"&Table2[[#This Row],[Year]]&"-"&Table2[[#This Row],[Month]] -> STR031-2025-Feb | F387: CUST0079 | G387: =_xlfn.XLOOKUP(Table2[[#This Row],[Customer_ID]],Table3[Customer_ID],Table3[Customer Name],"Not Found") -> Dhruv Natarajan | H387: =_xlfn.XLOOKUP(Table2[[#This Row],[Customer_ID]],Table3[Customer_ID],Table3[Gender],"Female") -> Male | I387: =_xlfn.XLOOKUP(Table2[[#This Row],[Customer_ID]],Table3[Customer_ID],Table3[City],"Missing Memebership") -> Nellore | J387: =_xlfn.XLOOKUP(Table2[[#This Row],[Customer_ID]],Table3[Customer_ID],Table3[State],"Karnataka") -> Andhra Pradesh | K387: =_xlfn.XLOOKUP(Table2[[#This Row],[Customer_ID]],Table3[Customer_ID],Table3[Membership],"Regular") -> Platinum | L387: PRD0182 | M387: =_xlfn.XLOOKUP(Table2[[#This Row],[Product_ID]],Table4[Product_ID],Table4[Product_Name],"Not Found") -> Tanishq Sling Bag Mustard | N387: =_xlfn.XLOOKUP(Table2[[#This Row],[Product_ID]],Table4[Product_ID],Table4[Category],"Not Found") -> Handbags | O387: =_xlfn.XLOOKUP(Table2[[#This Row],[Product_ID]],Table4[Product_ID],Table4[Subcategory],"Not Found") -> Sling Bag | P387: =_xlfn.XLOOKUP(Table2[[#This Row],[Product_ID]],Table4[Product_ID],Table4[Brand],"Missing Brand") -> Tanishq | Q387: STR031 | R387: =_xlfn.XLOOKUP(Table2[[#This Row],[Store_ID]],Table6[Store_ID],Table6[Store Name],"Not Found") -> TrendMart Kozhikode Mall Kiosk | S387: =_xlfn.XLOOKUP(Table2[[#This Row],[Store_ID]],Table6[Store_ID],Table6[Monthly Target],"Missing Target") -> 2000000 | T387: =_xlfn.XLOOKUP(Table2[[#This Row],[Store_ID]],Table6[Store_ID],Table6[Region],"Not Found") -> South Zone 1 | U387: EMP0141 | V387: =_xlfn.XLOOKUP(Table2[[#This Row],[Employee_ID]],Table5[Employee_ID],Table5[Employee Name],"Not Found") -> Dhruv Mishra | W387: 3 | X387: 3179.94 | Y387: 5 | Z387: 476.99 | AA387: 12 | AB387: 1087.54 | AC387: 10150.37 | AD387: 6407.55 | AE387: =(AC387-AD387-AB387) -> 2655.28 | AF387: Credit Card | AG387: =IFERROR(Table2[[#This Row],[Profit]]/Table2[[#This Row],[Sales Amount]],0) -> 0.2615944 | AH387: =TRIM(Table2[[#This Row],[Payment Modee]]) -> Credit Card | AI387: Offline | AJ387: Not Returned | AK387: 20:36 | AL387: =IF(HOUR(Table2[[#This Row],[Order Time]])<12,"Morning",IF(HOUR(Table2[[#This Row],[Order Time]])<17,"Afternoon",IF(HOUR(Table2[[#This Row],[Order Time]])<21,"Evening","Night"))) -> Evening | AM387: Weekday
A388: INV100386 | B388: 45518 | C388: =YEAR(Table2[[#This Row],[Invoice Date]]) -> 2024 | D388: =TEXT(Table2[[#This Row],[Invoice Date]],"mmm") -> Aug | E388: =Table2[[#This Row],[Store_ID]]&"-"&Table2[[#This Row],[Year]]&"-"&Table2[[#This Row],[Month]] -> STR091-2024-Aug | F388: CUST0200 | G388: =_xlfn.XLOOKUP(Table2[[#This Row],[Customer_ID]],Table3[Customer_ID],Table3[Customer Name],"Not Found") -> Balaji Chettiar | H388: =_xlfn.XLOOKUP(Table2[[#This Row],[Customer_ID]],Table3[Customer_ID],Table3[Gender],"Female") -> Male | I388: =_xlfn.XLOOKUP(Table2[[#This Row],[Customer_ID]],Table3[Customer_ID],Table3[City],"Missing Memebership") -> Davanagere | J388: =_xlfn.XLOOKUP(Table2[[#This Row],[Customer_ID]],Table3[Customer_ID],Table3[State],"Karnataka") -> Karnataka | K388: =_xlfn.XLOOKUP(Table2[[#This Row],[Customer_ID]],Table3[Customer_ID],Table3[Membership],"Regular") -> Gold | L388: PRD0043 | M388: =_xlfn.XLOOKUP(Table2[[#This Row],[Product_ID]],Table4[Product_ID],Table4[Product_Name],"Not Found") -> GRT Jewellers Sling Bag Olive | N388: =_xlfn.XLOOKUP(Table2[[#This Row],[Product_ID]],Table4[Product_ID],Table4[Category],"Not Found") -> Handbags | O388: =_xlfn.XLOOKUP(Table2[[#This Row],[Product_ID]],Table4[Product_ID],Table4[Subcategory],"Not Found") -> Sling Bag | P388: =_xlfn.XLOOKUP(Table2[[#This Row],[Product_ID]],Table4[Product_ID],Table4[Brand],"Missing Brand") -> GRT Jewellers | Q388: STR091 | R388: =_xlfn.XLOOKUP(Table2[[#This Row],[Store_ID]],Table6[Store_ID],Table6[Store Name],"Not Found") -> TrendMart Nizamabad Standard | S388: =_xlfn.XLOOKUP(Table2[[#This Row],[Store_ID]],Table6[Store_ID],Table6[Monthly Target],"Missing Target") -> 1500000 | T388: =_xlfn.XLOOKUP(Table2[[#This Row],[Store_ID]],Table6[Store_ID],Table6[Region],"Not Found") -> South Zone 2 | U388: EMP0215 | V388: =_xlfn.XLOOKUP(Table2[[#This Row],[Employee_ID]],Table5[Employee_ID],Table5[Employee Name],"Not Found") -> Praveen Gupta | W388: 0 | X388: 2923.57 | Y388: 15 | Z388: 0 | AA388: 12 | AB388: 0 | AC388: 0 | AD388: 0 | AE388: 0 | AF388: Credit Card | AG388: =IFERROR(Table2[[#This Row],[Profit]]/Table2[[#This Row],[Sales Amount]],0) -> 0 | AH388: =TRIM(Table2[[#This Row],[Payment Modee]]) -> Credit Card | AI388: Online | AJ388: Returned | AK388: 18:31 | AL388: =IF(HOUR(Table2[[#This Row],[Order Time]])<12,"Morning",IF(HOUR(Table2[[#This Row],[Order Time]])<17,"Afternoon",IF(HOUR(Table2[[#This Row],[Order Time]])<21,"Evening","Night"))) -> Evening | AM388: Weekday
A389: INV100387 | B389: 45601 | C389: =YEAR(Table2[[#This Row],[Invoice Date]]) -> 2024 | D389: =TEXT(Table2[[#This Row],[Invoice Date]],"mmm") -> Nov | E389: =Table2[[#This Row],[Store_ID]]&"-"&Table2[[#This Row],[Year]]&"-"&Table2[[#This Row],[Month]] -> STR085-2024-Nov | F389: CUST0749 | G389: =_xlfn.XLOOKUP(Table2[[#This Row],[Customer_ID]],Table3[Customer_ID],Table3[Customer Name],"Not Found") -> Anusuya Mudaliar | H389: =_xlfn.XLOOKUP(Table2[[#This Row],[Customer_ID]],Table3[Customer_ID],Table3[Gender],"Female") -> Female | I389: =_xlfn.XLOOKUP(Table2[[#This Row],[Customer_ID]],Table3[Customer_ID],Table3[City],"Missing Memebership") -> Kurnool | J389: =_xlfn.XLOOKUP(Table2[[#This Row],[Customer_ID]],Table3[Customer_ID],Table3[State],"Karnataka") -> Andhra Pradesh | K389: =_xlfn.XLOOKUP(Table2[[#This Row],[Customer_ID]],Table3[Customer_ID],Table3[Membership],"Regular") -> Silver | L389: PRD0087 | M389: =_xlfn.XLOOKUP(Table2[[#This Row],[Product_ID]],Table4[Product_ID],Table4[Product_Name],"Not Found") -> Blackberrys Formal Trouser Mustard | N389: =_xlfn.XLOOKUP(Table2[[#This Row],[Product_ID]],Table4[Product_ID],Table4[Category],"Not Found") -> Men Trousers | O389: =_xlfn.XLOOKUP(Table2[[#This Row],[Product_ID]],Table4[Product_ID],Table4[Subcategory],"Not Found") -> Formal Trouser | P389: =_xlfn.XLOOKUP(Table2[[#This Row],[Product_ID]],Table4[Product_ID],Table4[Brand],"Missing Brand") -> Missing Brand Name | Q389: STR085 | R389: =_xlfn.XLOOKUP(Table2[[#This Row],[Store_ID]],Table6[Store_ID],Table6[Store Name],"Not Found") -> TrendMart Nizamabad Outlet | S389: =_xlfn.XLOOKUP(Table2[[#This Row],[Store_ID]],Table6[Store_ID],Table6[Monthly Target],"Missing Target") -> 1500000 | T389: =_xlfn.XLOOKUP(Table2[[#This Row],[Store_ID]],Table6[Store_ID],Table6[Region],"Not Found") -> South Zone 2 | U389: EMP0020 | V389: =_xlfn.XLOOKUP(Table2[[#This Row],[Employee_ID]],Table5[Employee_ID],Table5[Employee Name],"Not Found") -> Eswar Prasad | W389: 2 | X389: 1265.63 | Y389: 10 | Z389: 253.13 | AA389: 12 | AB389: 273.38 | AC389: 2551.51 | AD389: 1746.86 | AE389: =(AC389-AD389-AB389) -> 531.27 | AF389: Debit Card | AG389: =IFERROR(Table2[[#This Row],[Profit]]/Table2[[#This Row],[Sales Amount]],0) -> 0.20821788 | AH389: =TRIM(Table2[[#This Row],[Payment Modee]]) -> Debit Card | AI389: Offline | AJ389: Not Returned | AK389: 16:17 | AL389: =IF(HOUR(Table2[[#This Row],[Order Time]])<12,"Morning",IF(HOUR(Table2[[#This Row],[Order Time]])<17,"Afternoon",IF(HOUR(Table2[[#This Row],[Order Time]])<21,"Evening","Night"))) -> Afternoon | AM389: Weekday
A390: INV100388 | B390: 45587 | C390: =YEAR(Table2[[#This Row],[Invoice Date]]) -> 2024 | D390: =TEXT(Table2[[#This Row],[Invoice Date]],"mmm") -> Oct | E390: =Table2[[#This Row],[Store_ID]]&"-"&Table2[[#This Row],[Year]]&"-"&Table2[[#This Row],[Month]] -> STR050-2024-Oct | F390: CUST0416 | G390: =_xlfn.XLOOKUP(Table2[[#This Row],[Customer_ID]],Table3[Customer_ID],Table3[Customer Name],"Not Found") -> Bharathi Prasad | H390: =_xlfn.XLOOKUP(Table2[[#This Row],[Customer_ID]],Table3[Customer_ID],Table3[Gender],"Female") -> Female | I390: =_xlfn.XLOOKUP(Table2[[#This Row],[Customer_ID]],Table3[Customer_ID],Table3[City],"Missing Memebership") -> Kannur | J390: =_xlfn.XLOOKUP(Table2[[#This Row],[Customer_ID]],Table3[Customer_ID],Table3[State],"Karnataka") -> Kerala | K390: =_xlfn.XLOOKUP(Table2[[#This Row],[Customer_ID]],Table3[Customer_ID],Table3[Membership],"Regular") -> Regular | L390: PRD0119 | M390: =_xlfn.XLOOKUP(Table2[[#This Row],[Product_ID]],Table4[Product_ID],Table4[Product_Name],"Not Found") -> Killer Jeans Round Neck Charcoal | N390: =_xlfn.XLOOKUP(Table2[[#This Row],[Product_ID]],Table4[Product_ID],Table4[Category],"Not Found") -> Men T-Shirts | O390: =_xlfn.XLOOKUP(Table2[[#This Row],[Product_ID]],Table4[Product_ID],Table4[Subcategory],"Not Found") -> Round Neck | P390: =_xlfn.XLOOKUP(Table2[[#This Row],[Product_ID]],Table4[Product_ID],Table4[Brand],"Missing Brand") -> Killer Jeans | Q390: STR050 | R390: =_xlfn.XLOOKUP(Table2[[#This Row],[Store_ID]],Table6[Store_ID],Table6[Store Name],"Not Found") -> TrendMart Thrissur High Street | S390: =_xlfn.XLOOKUP(Table2[[#This Row],[Store_ID]],Table6[Store_ID],Table6[Monthly Target],"Missing Target") -> 2000000 | T390: =_xlfn.XLOOKUP(Table2[[#This Row],[Store_ID]],Table6[Store_ID],Table6[Region],"Not Found") -> South Zone 1 | U390: EMP0147 | V390: =_xlfn.XLOOKUP(Table2[[#This Row],[Employee_ID]],Table5[Employee_ID],Table5[Employee Name],"Not Found") -> Yogesh Chettiar | W390: 1 | X390: 740.3 | Y390: 0 | Z390: 0 | AA390: 5 | AB390: 37.02 | AC390: 777.32 | AD390: 428.16 | AE390: =(AC390-AD390-AB390) -> 312.14 | AF390: Credit Card | AG390: =IFERROR(Table2[[#This Row],[Profit]]/Table2[[#This Row],[Sales Amount]],0) -> 0.4015592 | AH390: =TRIM(Table2[[#This Row],[Payment Modee]]) -> Credit Card | AI390: Offline | AJ390: Not Returned | AK390: 20:36 | AL390: =IF(HOUR(Table2[[#This Row],[Order Time]])<12,"Morning",IF(HOUR(Table2[[#This Row],[Order Time]])<17,"Afternoon",IF(HOUR(Table2[[#This Row],[Order Time]])<21,"Evening","Night"))) -> Evening | AM390: Weekday
A391: INV100389 | B391: 45500 | C391: =YEAR(Table2[[#This Row],[Invoice Date]]) -> 2024 | D391: =TEXT(Table2[[#This Row],[Invoice Date]],"mmm") -> Jul | E391: =Table2[[#This Row],[Store_ID]]&"-"&Table2[[#This Row],[Year]]&"-"&Table2[[#This Row],[Month]] -> STR058-2024-Jul | F391: CUST0057 | G391: =_xlfn.XLOOKUP(Table2[[#This Row],[Customer_ID]],Table3[Customer_ID],Table3[Customer Name],"Not Found") -> Bharathi Natarajan | H391: =_xlfn.XLOOKUP(Table2[[#This Row],[Customer_ID]],Table3[Customer_ID],Table3[Gender],"Female") -> Female | I391: =_xlfn.XLOOKUP(Table2[[#This Row],[Customer_ID]],Table3[Customer_ID],Table3[City],"Missing Memebership") -> Kalaburagi | J391: =_xlfn.XLOOKUP(Table2[[#This Row],[Customer_ID]],Table3[Customer_ID],Table3[State],"Karnataka") -> Karnataka | K391: =_xlfn.XLOOKUP(Table2[[#This Row],[Customer_ID]],Table3[Customer_ID],Table3[Membership],"Regular") -> Gold | L391: PRD0202 | M391: =_xlfn.XLOOKUP(Table2[[#This Row],[Product_ID]],Table4[Product_ID],Table4[Product_Name],"Not Found") -> Skechers Casual Belt Sky Blue | N391: =_xlfn.XLOOKUP(Table2[[#This Row],[Product_ID]],Table4[Product_ID],Table4[Category],"Not Found") -> Belts | O391: =_xlfn.XLOOKUP(Table2[[#This Row],[Product_ID]],Table4[Product_ID],Table4[Subcategory],"Not Found") -> Casual Belt | P391: =_xlfn.XLOOKUP(Table2[[#This Row],[Product_ID]],Table4[Product_ID],Table4[Brand],"Missing Brand") -> Skechers | Q391: STR058 | R391: =_xlfn.XLOOKUP(Table2[[#This Row],[Store_ID]],Table6[Store_ID],Table6[Store Name],"Not Found") -> TrendMart Thoothukudi Flagship | S391: =_xlfn.XLOOKUP(Table2[[#This Row],[Store_ID]],Table6[Store_ID],Table6[Monthly Target],"Missing Target") -> 1200000 | T391: =_xlfn.XLOOKUP(Table2[[#This Row],[Store_ID]],Table6[Store_ID],Table6[Region],"Not Found") -> South Zone 1 | U391: EMP0149 | V391: =_xlfn.XLOOKUP(Table2[[#This Row],[Employee_ID]],Table5[Employee_ID],Table5[Employee Name],"Not Found") -> Vasanthi Kamath | W391: 2 | X391: 869.16 | Y391: 15 | Z391: 260.75 | AA391: 5 | AB391: 73.88 | AC391: 1551.45 | AD391: 1180.04 | AE391: =(AC391-AD391-AB391) -> 297.53 | AF391: Debit Card | AG391: =IFERROR(Table2[[#This Row],[Profit]]/Table2[[#This Row],[Sales Amount]],0) -> 0.19177544 | AH391: =TRIM(Table2[[#This Row],[Payment Modee]]) -> Debit Card | AI391: Offline | AJ391: Not Returned | AK391: 13:44 | AL391: =IF(HOUR(Table2[[#This Row],[Order Time]])<12,"Morning",IF(HOUR(Table2[[#This Row],[Order Time]])<17,"Afternoon",IF(HOUR(Table2[[#This Row],[Order Time]])<21,"Evening","Night"))) -> Afternoon | AM391: Weekend
A392: INV100390 | B392: 45558 | C392: =YEAR(Table2[[#This Row],[Invoice Date]]) -> 2024 | D392: =TEXT(Table2[[#This Row],[Invoice Date]],"mmm") -> Sep | E392: =Table2[[#This Row],[Store_ID]]&"-"&Table2[[#This Row],[Year]]&"-"&Table2[[#This Row],[Month]] -> STR041-2024-Sep | F392: CUST0266 | G392: =_xlfn.XLOOKUP(Table2[[#This Row],[Customer_ID]],Table3[Customer_ID],Table3[Customer Name],"Not Found") -> Chandra Subramaniam | H392: =_xlfn.XLOOKUP(Table2[[#This Row],[Customer_ID]],Table3[Customer_ID],Table3[Gender],"Female") -> Male | I392: =_xlfn.XLOOKUP(Table2[[#This Row],[Customer_ID]],Table3[Customer_ID],Table3[City],"Missing Memebership") -> Alappuzha | J392: =_xlfn.XLOOKUP(Table2[[#This Row],[Customer_ID]],Table3[Customer_ID],Table3[State],"Karnataka") -> Kerala | K392: =_xlfn.XLOOKUP(Table2[[#This Row],[Customer_ID]],Table3[Customer_ID],Table3[Membership],"Regular") -> Silver | L392: PRD0050 | M392: =_xlfn.XLOOKUP(Table2[[#This Row],[Product_ID]],Table4[Product_ID],Table4[Product_Name],"Not Found") -> Ramraj Cotton A-Line Dress Brown | N392: =_xlfn.XLOOKUP(Table2[[#This Row],[Product_ID]],Table4[Product_ID],Table4[Category],"Not Found") -> Women Dresses | O392: =_xlfn.XLOOKUP(Table2[[#This Row],[Product_ID]],Table4[Product_ID],Table4[Subcategory],"Not Found") -> A-Line Dress | P392: =_xlfn.XLOOKUP(Table2[[#This Row],[Product_ID]],Table4[Product_ID],Table4[Brand],"Missing Brand") -> Ramraj Cotton | Q392: STR041 | R392: =_xlfn.XLOOKUP(Table2[[#This Row],[Store_ID]],Table6[Store_ID],Table6[Store Name],"Not Found") -> TrendMart Thiruvananthapuram Standard | S392: =_xlfn.XLOOKUP(Table2[[#This Row],[Store_ID]],Table6[Store_ID],Table6[Monthly Target],"Missing Target") -> 2500000 | T392: =_xlfn.XLOOKUP(Table2[[#This Row],[Store_ID]],Table6[Store_ID],Table6[Region],"Not Found") -> South Zone 1 | U392: EMP0063 | V392: =_xlfn.XLOOKUP(Table2[[#This Row],[Employee_ID]],Table5[Employee_ID],Table5[Employee Name],"Not Found") -> Anusuya Subramaniam | W392: 1 | X392: 1132.58 | Y392: 0 | Z392: 0 | AA392: 12 | AB392: 135.91 | AC392: 1268.49 | AD392: 769.63 | AE392: =(AC392-AD392-AB392) -> 362.95 | AF392: Cash | AG392: =IFERROR(Table2[[#This Row],[Profit]]/Table2[[#This Row],[Sales Amount]],0) -> 0.2861276 | AH392: =TRIM(Table2[[#This Row],[Payment Modee]]) -> Cash | AI392: Online | AJ392: Not Returned | AK392: 15:32 | AL392: =IF(HOUR(Table2[[#This Row],[Order Time]])<12,"Morning",IF(HOUR(Table2[[#This Row],[Order Time]])<17,"Afternoon",IF(HOUR(Table2[[#This Row],[Order Time]])<21,"Evening","Night"))) -> Afternoon | AM392: Weekday
A393: INV100391 | B393: 45611 | C393: =YEAR(Table2[[#This Row],[Invoice Date]]) -> 2024 | D393: =TEXT(Table2[[#This Row],[Invoice Date]],"mmm") -> Nov | E393: =Table2[[#This Row],[Store_ID]]&"-"&Table2[[#This Row],[Year]]&"-"&Table2[[#This Row],[Month]] -> STR006-2024-Nov | F393: CUST0374 | G393: =_xlfn.XLOOKUP(Table2[[#This Row],[Customer_ID]],Table3[Customer_ID],Table3[Customer Name],"Not Found") -> Varsha Rao | H393: =_xlfn.XLOOKUP(Table2[[#This Row],[Customer_ID]],Table3[Customer_ID],Table3[Gender],"Female") -> Female | I393: =_xlfn.XLOOKUP(Table2[[#This Row],[Customer_ID]],Table3[Customer_ID],Table3[City],"Missing Memebership") -> Mysuru | J393: =_xlfn.XLOOKUP(Table2[[#This Row],[Customer_ID]],Table3[Customer_ID],Table3[State],"Karnataka") -> Karnataka | K393: =_xlfn.XLOOKUP(Table2[[#This Row],[Customer_ID]],Table3[Customer_ID],Table3[Membership],"Regular") -> Regular | L393: PRD0043 | M393: =_xlfn.XLOOKUP(Table2[[#This Row],[Product_ID]],Table4[Product_ID],Table4[Product_Name],"Not Found") -> GRT Jewellers Sling Bag Olive | N393: =_xlfn.XLOOKUP(Table2[[#This Row],[Product_ID]],Table4[Product_ID],Table4[Category],"Not Found") -> Handbags | O393: =_xlfn.XLOOKUP(Table2[[#This Row],[Product_ID]],Table4[Product_ID],Table4[Subcategory],"Not Found") -> Sling Bag | P393: =_xlfn.XLOOKUP(Table2[[#This Row],[Product_ID]],Table4[Product_ID],Table4[Brand],"Missing Brand") -> GRT Jewellers | Q393: STR006 | R393: =_xlfn.XLOOKUP(Table2[[#This Row],[Store_ID]],Table6[Store_ID],Table6[Store Name],"Not Found") -> TrendMart Vellore Standard | S393: =_xlfn.XLOOKUP(Table2[[#This Row],[Store_ID]],Table6[Store_ID],Table6[Monthly Target],"Missing Target") -> 2000000 | T393: =_xlfn.XLOOKUP(Table2[[#This Row],[Store_ID]],Table6[Store_ID],Table6[Region],"Not Found") -> South Zone 1 | U393: EMP0203 | V393: =_xlfn.XLOOKUP(Table2[[#This Row],[Employee_ID]],Table5[Employee_ID],Table5[Employee Name],"Not Found") -> Rani Mishra | W393: 4 | X393: 3074.18 | Y393: 25 | Z393: 3074.18 | AA393: 12 | AB393: 1106.7 | AC393: 10329.24 | AD393: 8136.04 | AE393: =(AC393-AD393-AB393) -> 1086.5 | AF393: UPI | AG393: =IFERROR(Table2[[#This Row],[Profit]]/Table2[[#This Row],[Sales Amount]],0) -> 0.10518683 | AH393: =TRIM(Table2[[#This Row],[Payment Modee]]) -> UPI | AI393: Offline | AJ393: Returned | AK393: 12:22 | AL393: =IF(HOUR(Table2[[#This Row],[Order Time]])<12,"Morning",IF(HOUR(Table2[[#This Row],[Order Time]])<17,"Afternoon",IF(HOUR(Table2[[#This Row],[Order Time]])<21,"Evening","Night"))) -> Afternoon | AM393: Weekday
A394: INV100392 | B394: 45416 | C394: =YEAR(Table2[[#This Row],[Invoice Date]]) -> 2024 | D394: =TEXT(Table2[[#This Row],[Invoice Date]],"mmm") -> May | E394: =Table2[[#This Row],[Store_ID]]&"-"&Table2[[#This Row],[Year]]&"-"&Table2[[#This Row],[Month]] -> STR029-2024-May | F394: CUST0130 | G394: =_xlfn.XLOOKUP(Table2[[#This Row],[Customer_ID]],Table3[Customer_ID],Table3[Customer Name],"Not Found") -> Tejaswini Murthy | H394: =_xlfn.XLOOKUP(Table2[[#This Row],[Customer_ID]],Table3[Customer_ID],Table3[Gender],"Female") -> Female | I394: =_xlfn.XLOOKUP(Table2[[#This Row],[Customer_ID]],Table3[Customer_ID],Table3[City],"Missing Memebership") -> Guntur | J394: =_xlfn.XLOOKUP(Table2[[#This Row],[Customer_ID]],Table3[Customer_ID],Table3[State],"Karnataka") -> Andhra Pradesh | K394: =_xlfn.XLOOKUP(Table2[[#This Row],[Customer_ID]],Table3[Customer_ID],Table3[Membership],"Regular") -> Regular | L394: PRD0198 | M394: =_xlfn.XLOOKUP(Table2[[#This Row],[Product_ID]],Table4[Product_ID],Table4[Product_Name],"Not Found") -> Van Heusen Formal Trouser Maroon | N394: =_xlfn.XLOOKUP(Table2[[#This Row],[Product_ID]],Table4[Product_ID],Table4[Category],"Not Found") -> Men Trousers | O394: =_xlfn.XLOOKUP(Table2[[#This Row],[Product_ID]],Table4[Product_ID],Table4[Subcategory],"Not Found") -> Formal Trouser | P394: =_xlfn.XLOOKUP(Table2[[#This Row],[Product_ID]],Table4[Product_ID],Table4[Brand],"Missing Brand") -> Van Heusen | Q394: STR029 | R394: =_xlfn.XLOOKUP(Table2[[#This Row],[Store_ID]],Table6[Store_ID],Table6[Store Name],"Not Found") -> TrendMart Davanagere High Street | S394: =_xlfn.XLOOKUP(Table2[[#This Row],[Store_ID]],Table6[Store_ID],Table6[Monthly Target],"Missing Target") -> 800000 | T394: =_xlfn.XLOOKUP(Table2[[#This Row],[Store_ID]],Table6[Store_ID],Table6[Region],"Not Found") -> South Zone 2 | U394: EMP0255 | V394: =_xlfn.XLOOKUP(Table2[[#This Row],[Employee_ID]],Table5[Employee_ID],Table5[Employee Name],"Not Found") -> Venkat Sharma | W394: 0 | X394: 822.23 | Y394: 10 | Z394: 0 | AA394: 5 | AB394: 0 | AC394: 0 | AD394: 0 | AE394: 0 | AF394: Debit Card | AG394: =IFERROR(Table2[[#This Row],[Profit]]/Table2[[#This Row],[Sales Amount]],0) -> 0 | AH394: =TRIM(Table2[[#This Row],[Payment Modee]]) -> Debit Card | AI394: Offline | AJ394: Not Returned | AK394: 18:10 | AL394: =IF(HOUR(Table2[[#This Row],[Order Time]])<12,"Morning",IF(HOUR(Table2[[#This Row],[Order Time]])<17,"Afternoon",IF(HOUR(Table2[[#This Row],[Order Time]])<21,"Evening","Night"))) -> Evening | AM394: Weekend
A395: INV100393 | B395: 45430 | C395: =YEAR(Table2[[#This Row],[Invoice Date]]) -> 2024 | D395: =TEXT(Table2[[#This Row],[Invoice Date]],"mmm") -> May | E395: =Table2[[#This Row],[Store_ID]]&"-"&Table2[[#This Row],[Year]]&"-"&Table2[[#This Row],[Month]] -> STR098-2024-May | F395: CUST0331 | G395: =_xlfn.XLOOKUP(Table2[[#This Row],[Customer_ID]],Table3[Customer_ID],Table3[Customer Name],"Not Found") -> Anjali Bhat | H395: =_xlfn.XLOOKUP(Table2[[#This Row],[Customer_ID]],Table3[Customer_ID],Table3[Gender],"Female") -> Female | I395: =_xlfn.XLOOKUP(Table2[[#This Row],[Customer_ID]],Table3[Customer_ID],Table3[City],"Missing Memebership") -> Alappuzha | J395: =_xlfn.XLOOKUP(Table2[[#This Row],[Customer_ID]],Table3[Customer_ID],Table3[State],"Karnataka") -> Kerala | K395: =_xlfn.XLOOKUP(Table2[[#This Row],[Customer_ID]],Table3[Customer_ID],Table3[Membership],"Regular") -> Silver | L395: PRD0070 | M395: =_xlfn.XLOOKUP(Table2[[#This Row],[Product_ID]],Table4[Product_ID],Table4[Product_Name],"Not Found") -> Woodland Boys Shirt White | N395: =_xlfn.XLOOKUP(Table2[[#This Row],[Product_ID]],Table4[Product_ID],Table4[Category],"Not Found") -> Kids Wear | O395: =_xlfn.XLOOKUP(Table2[[#This Row],[Product_ID]],Table4[Product_ID],Table4[Subcategory],"Not Found") -> Boys Shirt | P395: =_xlfn.XLOOKUP(Table2[[#This Row],[Product_ID]],Table4[Product_ID],Table4[Brand],"Missing Brand") -> Woodland | Q395: STR098 | R395: =_xlfn.XLOOKUP(Table2[[#This Row],[Store_ID]],Table6[Store_ID],Table6[Store Name],"Not Found") -> TrendMart Guntur High Street | S395: =_xlfn.XLOOKUP(Table2[[#This Row],[Store_ID]],Table6[Store_ID],Table6[Monthly Target],"Missing Target") -> 1200000 | T395: =_xlfn.XLOOKUP(Table2[[#This Row],[Store_ID]],Table6[Store_ID],Table6[Region],"Not Found") -> South Zone 3 | U395: EMP0090 | V395: =_xlfn.XLOOKUP(Table2[[#This Row],[Employee_ID]],Table5[Employee_ID],Table5[Employee Name],"Not Found") -> Padma Gounder | W395: 2 | X395: 859.76 | Y395: 5 | Z395: 85.98 | AA395: 5 | AB395: 81.68 | AC395: 1715.22 | AD395: 1130.9 | AE395: =(AC395-AD395-AB395) -> 502.64 | AF395: Cash | AG395: =IFERROR(Table2[[#This Row],[Profit]]/Table2[[#This Row],[Sales Amount]],0) -> 0.29304696 | AH395: =TRIM(Table2[[#This Row],[Payment Modee]]) -> Cash | AI395: Offline | AJ395: Not Returned | AK395: 17:21 | AL395: =IF(HOUR(Table2[[#This Row],[Order Time]])<12,"Morning",IF(HOUR(Table2[[#This Row],[Order Time]])<17,"Afternoon",IF(HOUR(Table2[[#This Row],[Order Time]])<21,"Evening","Night"))) -> Evening | AM395: Weekend
A396: INV100394 | B396: 45588 | C396: =YEAR(Table2[[#This Row],[Invoice Date]]) -> 2024 | D396: =TEXT(Table2[[#This Row],[Invoice Date]],"mmm") -> Oct | E396: =Table2[[#This Row],[Store_ID]]&"-"&Table2[[#This Row],[Year]]&"-"&Table2[[#This Row],[Month]] -> STR037-2024-Oct | F396: CUST0188 | G396: =_xlfn.XLOOKUP(Table2[[#This Row],[Customer_ID]],Table3[Customer_ID],Table3[Customer Name],"Not Found") -> Vasanthi Srinivasan | H396: =_xlfn.XLOOKUP(Table2[[#This Row],[Customer_ID]],Table3[Customer_ID],Table3[Gender],"Female") -> Female | I396: =_xlfn.XLOOKUP(Table2[[#This Row],[Customer_ID]],Table3[Customer_ID],Table3[City],"Missing Memebership") -> Karimnagar | J396: =_xlfn.XLOOKUP(Table2[[#This Row],[Customer_ID]],Table3[Customer_ID],Table3[State],"Karnataka") -> Telangana | K396: =_xlfn.XLOOKUP(Table2[[#This Row],[Customer_ID]],Table3[Customer_ID],Table3[Membership],"Regular") -> Silver | L396: PRD0122 | M396: =_xlfn.XLOOKUP(Table2[[#This Row],[Product_ID]],Table4[Product_ID],Table4[Product_Name],"Not Found") -> Aurelia Necklace Grey | N396: =_xlfn.XLOOKUP(Table2[[#This Row],[Product_ID]],Table4[Product_ID],Table4[Category],"Not Found") -> Jewellery | O396: =_xlfn.XLOOKUP(Table2[[#This Row],[Product_ID]],Table4[Product_ID],Table4[Subcategory],"Not Found") -> Necklace | P396: =_xlfn.XLOOKUP(Table2[[#This Row],[Product_ID]],Table4[Product_ID],Table4[Brand],"Missing Brand") -> Aurelia | Q396: STR037 | R396: =_xlfn.XLOOKUP(Table2[[#This Row],[Store_ID]],Table6[Store_ID],Table6[Store Name],"Not Found") -> TrendMart Vijayawada High Street | S396: =_xlfn.XLOOKUP(Table2[[#This Row],[Store_ID]],Table6[Store_ID],Table6[Monthly Target],"Missing Target") -> 1000000 | T396: =_xlfn.XLOOKUP(Table2[[#This Row],[Store_ID]],Table6[Store_ID],Table6[Region],"Not Found") -> South Zone 3 | U396: EMP0100 | V396: =_xlfn.XLOOKUP(Table2[[#This Row],[Employee_ID]],Table5[Employee_ID],Table5[Employee Name],"Not Found") -> Priya Balasubramaniam | W396: 1 | X396: 725.13 | Y396: 5 | Z396: 36.26 | AA396: 3 | AB396: 20.67 | AC396: 709.54 | AD396: 556.99 | AE396: =(AC396-AD396-AB396) -> 131.88 | AF396: Debit Card | AG396: =IFERROR(Table2[[#This Row],[Profit]]/Table2[[#This Row],[Sales Amount]],0) -> 0.1858669 | AH396: =TRIM(Table2[[#This Row],[Payment Modee]]) -> Debit Card | AI396: Online | AJ396: Not Returned | AK396: 18:15 | AL396: =IF(HOUR(Table2[[#This Row],[Order Time]])<12,"Morning",IF(HOUR(Table2[[#This Row],[Order Time]])<17,"Afternoon",IF(HOUR(Table2[[#This Row],[Order Time]])<21,"Evening","Night"))) -> Evening | AM396: Weekday
A397: INV100395 | B397: 45464 | C397: =YEAR(Table2[[#This Row],[Invoice Date]]) -> 2024 | D397: =TEXT(Table2[[#This Row],[Invoice Date]],"mmm") -> Jun | E397: =Table2[[#This Row],[Store_ID]]&"-"&Table2[[#This Row],[Year]]&"-"&Table2[[#This Row],[Month]] -> STR087-2024-Jun | F397: CUST0482 | G397: =_xlfn.XLOOKUP(Table2[[#This Row],[Customer_ID]],Table3[Customer_ID],Table3[Customer Name],"Not Found") -> Suresh Mishra | H397: =_xlfn.XLOOKUP(Table2[[#This Row],[Customer_ID]],Table3[Customer_ID],Table3[Gender],"Female") -> Male | I397: =_xlfn.XLOOKUP(Table2[[#This Row],[Customer_ID]],Table3[Customer_ID],Table3[City],"Missing Memebership") -> Vijayawada | J397: =_xlfn.XLOOKUP(Table2[[#This Row],[Customer_ID]],Table3[Customer_ID],Table3[State],"Karnataka") -> Andhra Pradesh | K397: =_xlfn.XLOOKUP(Table2[[#This Row],[Customer_ID]],Table3[Customer_ID],Table3[Membership],"Regular") -> Silver | L397: PRD0213 | M397: =_xlfn.XLOOKUP(Table2[[#This Row],[Product_ID]],Table4[Product_ID],Table4[Product_Name],"Not Found") -> Global Desi Earrings Green | N397: =_xlfn.XLOOKUP(Table2[[#This Row],[Product_ID]],Table4[Product_ID],Table4[Category],"Not Found") -> Jewellery | O397: =_xlfn.XLOOKUP(Table2[[#This Row],[Product_ID]],Table4[Product_ID],Table4[Subcategory],"Not Found") -> Earrings | P397: =_xlfn.XLOOKUP(Table2[[#This Row],[Product_ID]],Table4[Product_ID],Table4[Brand],"Missing Brand") -> Global Desi | Q397: STR087 | R397: =_xlfn.XLOOKUP(Table2[[#This Row],[Store_ID]],Table6[Store_ID],Table6[Store Name],"Not Found") -> TrendMart Salem Outlet | S397: =_xlfn.XLOOKUP(Table2[[#This Row],[Store_ID]],Table6[Store_ID],Table6[Monthly Target],"Missing Target") -> 2000000 | T397: =_xlfn.XLOOKUP(Table2[[#This Row],[Store_ID]],Table6[Store_ID],Table6[Region],"Not Found") -> South Zone 1 | U397: EMP0285 | V397: =_xlfn.XLOOKUP(Table2[[#This Row],[Employee_ID]],Table5[Employee_ID],Table5[Employee Name],"Not Found") -> Chandran Krishnan | W397: 3 | X397: 6700.89 | Y397: 25 | Z397: 5025.67 | AA397: 3 | AB397: 452.31 | AC397: 15529.31 | AD397: 14601.63 | AE397: =(AC397-AD397-AB397) -> 475.37 | AF397: Debit Card | AG397: =IFERROR(Table2[[#This Row],[Profit]]/Table2[[#This Row],[Sales Amount]],0) -> 0.030611148 | AH397: =TRIM(Table2[[#This Row],[Payment Modee]]) -> Debit Card | AI397: Online | AJ397: Not Returned | AK397: 14:12 | AL397: =IF(HOUR(Table2[[#This Row],[Order Time]])<12,"Morning",IF(HOUR(Table2[[#This Row],[Order Time]])<17,"Afternoon",IF(HOUR(Table2[[#This Row],[Order Time]])<21,"Evening","Night"))) -> Afternoon | AM397: Weekday
A398: INV100396 | B398: 45472 | C398: =YEAR(Table2[[#This Row],[Invoice Date]]) -> 2024 | D398: =TEXT(Table2[[#This Row],[Invoice Date]],"mmm") -> Jun | E398: =Table2[[#This Row],[Store_ID]]&"-"&Table2[[#This Row],[Year]]&"-"&Table2[[#This Row],[Month]] -> STR060-2024-Jun | F398: CUST0532 | G398: =_xlfn.XLOOKUP(Table2[[#This Row],[Customer_ID]],Table3[Customer_ID],Table3[Customer Name],"Not Found") -> Ravi Subramaniam | H398: =_xlfn.XLOOKUP(Table2[[#This Row],[Customer_ID]],Table3[Customer_ID],Table3[Gender],"Female") -> Male | I398: =_xlfn.XLOOKUP(Table2[[#This Row],[Customer_ID]],Table3[Customer_ID],Table3[City],"Missing Memebership") -> Warangal | J398: =_xlfn.XLOOKUP(Table2[[#This Row],[Customer_ID]],Table3[Customer_ID],Table3[State],"Karnataka") -> Telangana | K398: =_xlfn.XLOOKUP(Table2[[#This Row],[Customer_ID]],Table3[Customer_ID],Table3[Membership],"Regular") -> Regular | L398: PRD0130 | M398: =_xlfn.XLOOKUP(Table2[[#This Row],[Product_ID]],Table4[Product_ID],Table4[Product_Name],"Not Found") -> Spykar Cotton Saree Black | N398: =_xlfn.XLOOKUP(Table2[[#This Row],[Product_ID]],Table4[Product_ID],Table4[Category],"Not Found") -> Women Sarees | O398: =_xlfn.XLOOKUP(Table2[[#This Row],[Product_ID]],Table4[Product_ID],Table4[Subcategory],"Not Found") -> Cotton Saree | P398: =_xlfn.XLOOKUP(Table2[[#This Row],[Product_ID]],Table4[Product_ID],Table4[Brand],"Missing Brand") -> Spykar | Q398: STR060 | R398: =_xlfn.XLOOKUP(Table2[[#This Row],[Store_ID]],Table6[Store_ID],Table6[Store Name],"Not Found") -> TrendMart Tirunelveli Flagship | S398: =_xlfn.XLOOKUP(Table2[[#This Row],[Store_ID]],Table6[Store_ID],Table6[Monthly Target],"Missing Target") -> 1000000 | T398: =_xlfn.XLOOKUP(Table2[[#This Row],[Store_ID]],Table6[Store_ID],Table6[Region],"Not Found") -> South Zone 1 | U398: EMP0170 | V398: =_xlfn.XLOOKUP(Table2[[#This Row],[Employee_ID]],Table5[Employee_ID],Table5[Employee Name],"Not Found") -> Jyothi Prasad | W398: 1 | X398: 1522 | Y398: 10 | Z398: 152.2 | AA398: 12 | AB398: 164.38 | AC398: 1534.18 | AD398: 962.17 | AE398: =(AC398-AD398-AB398) -> 407.63 | AF398: UPI | AG398: =IFERROR(Table2[[#This Row],[Profit]]/Table2[[#This Row],[Sales Amount]],0) -> 0.26569894 | AH398: =TRIM(Table2[[#This Row],[Payment Modee]]) -> UPI | AI398: Online | AJ398: Not Returned | AK398: 20:41 | AL398: =IF(HOUR(Table2[[#This Row],[Order Time]])<12,"Morning",IF(HOUR(Table2[[#This Row],[Order Time]])<17,"Afternoon",IF(HOUR(Table2[[#This Row],[Order Time]])<21,"Evening","Night"))) -> Evening | AM398: Weekend
A399: INV100397 | B399: 45473 | C399: =YEAR(Table2[[#This Row],[Invoice Date]]) -> 2024 | D399: =TEXT(Table2[[#This Row],[Invoice Date]],"mmm") -> Jun | E399: =Table2[[#This Row],[Store_ID]]&"-"&Table2[[#This Row],[Year]]&"-"&Table2[[#This Row],[Month]] -> STR112-2024-Jun | F399: CUST0277 | G399: =_xlfn.XLOOKUP(Table2[[#This Row],[Customer_ID]],Table3[Customer_ID],Table3[Customer Name],"Not Found") -> Kiran Gupta | H399: =_xlfn.XLOOKUP(Table2[[#This Row],[Customer_ID]],Table3[Customer_ID],Table3[Gender],"Female") -> Male | I399: =_xlfn.XLOOKUP(Table2[[#This Row],[Customer_ID]],Table3[Customer_ID],Table3[City],"Missing Memebership") -> Guntur | J399: =_xlfn.XLOOKUP(Table2[[#This Row],[Customer_ID]],Table3[Customer_ID],Table3[State],"Karnataka") -> Andhra Pradesh | K399: =_xlfn.XLOOKUP(Table2[[#This Row],[Customer_ID]],Table3[Customer_ID],Table3[Membership],"Regular") -> Gold | L399: PRD0048 | M399: =_xlfn.XLOOKUP(Table2[[#This Row],[Product_ID]],Table4[Product_ID],Table4[Product_Name],"Not Found") -> Indian Terrain Denim Shirt Wine | N399: =_xlfn.XLOOKUP(Table2[[#This Row],[Product_ID]],Table4[Product_ID],Table4[Category],"Not Found") -> Accessories | O399: =_xlfn.XLOOKUP(Table2[[#This Row],[Product_ID]],Table4[Product_ID],Table4[Subcategory],"Not Found") -> Tie | P399: =_xlfn.XLOOKUP(Table2[[#This Row],[Product_ID]],Table4[Product_ID],Table4[Brand],"Missing Brand") -> Being Human | Q399: STR112 | R399: =_xlfn.XLOOKUP(Table2[[#This Row],[Store_ID]],Table6[Store_ID],Table6[Store Name],"Not Found") -> TrendMart Guntur Outlet | S399: =_xlfn.XLOOKUP(Table2[[#This Row],[Store_ID]],Table6[Store_ID],Table6[Monthly Target],"Missing Target") -> 1500000 | T399: =_xlfn.XLOOKUP(Table2[[#This Row],[Store_ID]],Table6[Store_ID],Table6[Region],"Not Found") -> South Zone 3 | U399: EMP0285 | V399: =_xlfn.XLOOKUP(Table2[[#This Row],[Employee_ID]],Table5[Employee_ID],Table5[Employee Name],"Not Found") -> Chandran Krishnan | W399: 2 | X399: 1175.1 | Y399: 0 | Z399: 0 | AA399: 12 | AB399: 282.02 | AC399: 2632.22 | AD399: 1167.72 | AE399: =(AC399-AD399-AB399) -> 1182.48 | AF399: UPI | AG399: =IFERROR(Table2[[#This Row],[Profit]]/Table2[[#This Row],[Sales Amount]],0) -> 0.44923297 | AH399: =TRIM(Table2[[#This Row],[Payment Modee]]) -> UPI | AI399: Offline | AJ399: Not Returned | AK399: 19:18 | AL399: =IF(HOUR(Table2[[#This Row],[Order Time]])<12,"Morning",IF(HOUR(Table2[[#This Row],[Order Time]])<17,"Afternoon",IF(HOUR(Table2[[#This Row],[Order Time]])<21,"Evening","Night"))) -> Evening | AM399: Weekend
